Workbook

Sheet Data
A1: Symbol | B1: Issuer Name | C1: Required Yield (IRR) | D1: Annualised Required Yield (IRR) | F1: Ask Price | G1: Currency | H1: Face Value/ Maturity Value | J1: Volume | M1: Coupon | N1: Issue Date | O1: Maturity | P1: Term (In Years) | Q1: Coupon Yield | R1: Frequency (Yearly) | S1: Frequency (Period) | U1: No. of coupons | V1: Coupon Amount (INR) | W1: IRR | X1: Yield (Annual) | Y1: Macaulay Duration in Years | Z1: Modified Duration in Years | AA1: Dollar Duration | AB1: Bond Type | AC1: Country | AD1: Yearly Payment Frequency
A3: 10BML25 | B3: Belstar Microfinance Ltd. | C3: =RATE(U3,V3,-F3,H3) -> 0.39761212 | D3: =C3*AD3 -> 1.5904485 | F3: 12724.84 | G3: INR | H3: 100000 | J3: 10 | M3: 0.1 | N3: 45139 | O3: 45870 | P3: =ROUND(YEARFRAC(N3,O3),0) -> 2 | Q3: =(M3*H3)/F3 -> 0.7858645 | R3: =IF(S3="Quarterly",4,IF(S3="Semi-annual",2,IF(S3="Annual",1,IF(S3="Pays at maturity",0,IF(S3="Monthly",12,0))))) -> 4 | S3: Quarterly | U3: =R3*P3 -> 8 | V3: =(H3*M3)/AD3 -> 2500 | Y3: =DURATION(N3,O3,M3,D3,AD3) -> 1.4161488 | Z3: =Y3/(1+C3) -> 1.0132631 | AA3: =-Z3*F3 -> -12893.611 | AB3: None | AC3: India | AD3: =_xlfn.SWITCH(PROPER(TRIM(S3)), "Annual",1, "Semi-Annual",2, "Quarterly",4, "Monthly",12, "") -> 4
A4: 85KFL25 | B4: Kosamattam Finance Ltd. | C4: =RATE(U4,V4,-F4,H4) -> 0.08584701 | D4: =C4*AD4 -> 0.08584701 | F4: 997.84 | G4: INR | H4: 1000 | J4: 220 | L4: 11.444721 | M4: 0.085 | N4: 44784 | O4: 45879 | P4: =ROUND(YEARFRAC(N4,O4),0) -> 3 | Q4: =(M4*H4)/F4 -> 0.085183997 | R4: =IF(S4="Quarterly",4,IF(S4="Semi-annual",2,IF(S4="Annual",1,IF(S4="Pays at maturity",0,IF(S4="Monthly",12,0))))) -> 1 | S4: Annual | U4: =R4*P4 -> 3 | V4: =(H4*M4)/AD4 -> 85 | W4: =RATE(U4,V4,-F4,H4) -> 0.08584701 | X4: =W4*AD4 -> 0.08584701 | Y4: =DURATION(N4,O4,M4,D4,AD4) -> 2.7680764 | Z4: =Y4/(1+C4) -> 2.5492324 | AA4: =-Z4*F4 -> -2543.726 | AB4: None | AC4: India | AD4: =_xlfn.SWITCH(PROPER(TRIM(S4)), "Annual",1, "Semi-Annual",2, "Quarterly",4, "Monthly",12, "") -> 1
A6: 950CCIL25 | B6: Chemmanur Credits & Investments Ltd. | C6: =RATE(U6,V6,-F6,H6) -> 0.095 | D6: =C6*AD6 -> 0.095 | F6: 1000 | G6: INR | H6: 1000 | J6: 100 | L6: 9.5 | M6: 0.095 | N6: 45518 | O6: 45884 | P6: =ROUND(YEARFRAC(N6,O6),0) -> 1 | Q6: =(M6*H6)/F6 -> 0.095 | R6: =IF(S6="Quarterly",4,IF(S6="Semi-annual",2,IF(S6="Annual",1,IF(S6="Pays at maturity",0,IF(S6="Monthly",12,0))))) -> 1 | S6: Annual | U6: =R6*P6 -> 1 | V6: =(H6*M6)/AD6 -> 95 | W6: =RATE(U6,V6,-F6,H6) -> 0.095 | X6: =W6*AD6 -> 0.095 | Y6: =DURATION(N6,O6,M6,D6,AD6) -> 0.91601979 | Z6: =Y6/(1+C6) -> 0.83654775 | AA6: =-Z6*F6 -> -836.54775 | AB6: None | AC6: India | AD6: =_xlfn.SWITCH(PROPER(TRIM(S6)), "Annual",1, "Semi-Annual",2, "Quarterly",4, "Monthly",12, "") -> 1
A8: 934WBSE25 | B8: West Bengal State Electricity Distribution Co. Ltd. | C8: =RATE(U8,V8,-F8,H8) -> 0.0467 | D8: =C8*AD8 -> 0.0934 | F8: 1000000 | G8: INR | H8: 1000000 | J8: 1 | M8: 0.0934 | N8: 40406 | O8: 45885 | P8: =ROUND(YEARFRAC(N8,O8),0) -> 15 | Q8: =(M8*H8)/F8 -> 0.0934 | R8: =IF(S8="Quarterly",4,IF(S8="Semi-annual",2,IF(S8="Annual",1,IF(S8="Pays at maturity",0,IF(S8="Monthly",12,0))))) -> 2 | S8: Semi-annual | U8: =R8*P8 -> 30 | V8: =(H8*M8)/AD8 -> 46700 | W8: =RATE(U8,V8,-F8,H8) -> 0.0467 | X8: =W8*AD8 -> 0.0934 | Y8: =DURATION(N8,O8,M8,D8,AD8) -> 8.3568759 | Z8: =Y8/(1+C8) -> 7.9840221 | AA8: =-Z8*F8 -> -7984022.1 | AB8: None | AC8: India | AD8: =_xlfn.SWITCH(PROPER(TRIM(S8)), "Annual",1, "Semi-Annual",2, "Quarterly",4, "Monthly",12, "") -> 2
A9: 1075NBSL25 | B9: Nirmal Bang Securities Pvt Ltd. | C9: =RATE(U9,V9,-F9,H9) -> 0.026540883 | D9: =C9*AD9 -> 0.10616353 | F9: 100238 | G9: INR | H9: 100000 | J9: 5 | M9: 0.1075 | N9: 45342 | O9: 45889 | P9: =ROUND(YEARFRAC(N9,O9),0) -> 2 | Q9: =(M9*H9)/F9 -> 0.10724476 | R9: =IF(S9="Quarterly",4,IF(S9="Semi-annual",2,IF(S9="Annual",1,IF(S9="Pays at maturity",0,IF(S9="Monthly",12,0))))) -> 4 | S9: Quarterly | U9: =R9*P9 -> 8 | V9: =(H9*M9)/AD9 -> 2687.5 | W9: =RATE(U9,V9,-F9,H9) -> 0.026540883 | X9: =W9*AD9 -> 0.10616353 | Y9: =DURATION(N9,O9,M9,D9,AD9) -> 1.4053172 | Z9: =Y9/(1+C9) -> 1.3689832 | AA9: =-Z9*F9 -> -137224.14 | AB9: Callable | AC9: India | AD9: =_xlfn.SWITCH(PROPER(TRIM(S9)), "Annual",1, "Semi-Annual",2, "Quarterly",4, "Monthly",12, "") -> 4
A10: 715NTPC25 | B10: Ntpc Ltd. | C10: =RATE(U10,V10,-F10,H10) -> 0.057215909 | D10: =C10*AD10 -> 0.057215909 | F10: 1106532.9 | G10: INR | H10: 1000000 | J10: 8 | L10: 3.4759956 | M10: 0.0715 | N10: 42237 | O10: 45890 | P10: =ROUND(YEARFRAC(N10,O10),0) -> 10 | Q10: =(M10*H10)/F10 -> 0.064616244 | R10: =IF(S10="Quarterly",4,IF(S10="Semi-annual",2,IF(S10="Annual",1,IF(S10="Pays at maturity",0,IF(S10="Monthly",12,0))))) -> 1 | S10: Annual | U10: =R10*P10 -> 10 | V10: =(H10*M10)/AD10 -> 71500 | W10: =RATE(U10,V10,-F10,H10) -> 0.057215909 | X10: =W10*AD10 -> 0.057215909 | Y10: =DURATION(N10,O10,M10,D10,AD10) -> 7.6113042 | Z10: =Y10/(1+C10) -> 7.1993849 | AA10: =-Z10*F10 -> -7966356.2 | AB10: None | AC10: India | AD10: =_xlfn.SWITCH(PROPER(TRIM(S10)), "Annual",1, "Semi-Annual",2, "Quarterly",4, "Monthly",12, "") -> 1
A11: 715IRFC25 | B11: Indian Railway Finance Corp. Ltd. | C11: =RATE(U11,V11,-F11,H11) -> 0.060599662 | D11: =C11*AD11 -> 0.060599662 | F11: 1080000 | G11: INR | H11: 1000000 | J11: 7 | L11: 0.8432257 | M11: 0.0715 | N11: 42237 | O11: 45890 | P11: =ROUND(YEARFRAC(N11,O11),0) -> 10 | Q11: =(M11*H11)/F11 -> 0.066203704 | R11: =IF(S11="Quarterly",4,IF(S11="Semi-annual",2,IF(S11="Annual",1,IF(S11="Pays at maturity",0,IF(S11="Monthly",12,0))))) -> 1 | S11: Annual | U11: =R11*P11 -> 10 | V11: =(H11*M11)/AD11 -> 71500 | W11: =RATE(U11,V11,-F11,H11) -> 0.060599662 | X11: =W11*AD11 -> 0.060599662 | Y11: =DURATION(N11,O11,M11,D11,AD11) -> 7.5790461 | Z11: =Y11/(1+C11) -> 7.1460009 | AA11: =-Z11*F11 -> -7717681 | AB11: None | AC11: India | AD11: =_xlfn.SWITCH(PROPER(TRIM(S11)), "Annual",1, "Semi-Annual",2, "Quarterly",4, "Monthly",12, "") -> 1
A12: 990VCL25 | B12: Vivriti Capital Pvt Ltd. | C12: =RATE(U12,V12,-F12,H12) -> 0.026058789 | D12: =C12*AD12 -> 0.10423516 | F12: 99508.89 | G12: INR | H12: 100000 | J12: 1 | M12: 0.099 | N12: 45463 | O12: 45891 | P12: =ROUND(YEARFRAC(N12,O12),0) -> 1 | Q12: =(M12*H12)/F12 -> 0.099488598 | R12: =IF(S12="Quarterly",4,IF(S12="Semi-annual",2,IF(S12="Annual",1,IF(S12="Pays at maturity",0,IF(S12="Monthly",12,0))))) -> 4 | S12: Quarterly | U12: =R12*P12 -> 4 | V12: =(H12*M12)/AD12 -> 2475 | W12: =RATE(U12,V12,-F12,H12) -> 0.026058789 | X12: =W12*AD12 -> 0.10423516 | Y12: =DURATION(N12,O12,M12,D12,AD12) -> 1.1130723 | Z12: =Y12/(1+C12) -> 1.0848036 | AA12: =-Z12*F12 -> -107947.6 | AB12: None | AC12: India | AD12: =_xlfn.SWITCH(PROPER(TRIM(S12)), "Annual",1, "Semi-Annual",2, "Quarterly",4, "Monthly",12, "") -> 4
A14: 950AFL25 | B14: Aye Finance Ltd. | C14: =RATE(U14,V14,-F14,H14) -> 0.095 | D14: =C14*AD14 -> 0.095 | F14: 100000 | G14: INR | H14: 100000 | J14: 1 | L14: 9.5 | M14: 0.095 | N14: 45345 | O14: 45892 | P14: =ROUND(YEARFRAC(N14,O14),0) -> 2 | Q14: =(M14*H14)/F14 -> 0.095 | R14: =IF(S14="Quarterly",4,IF(S14="Semi-annual",2,IF(S14="Annual",1,IF(S14="Pays at maturity",0,IF(S14="Monthly",12,0))))) -> 1 | S14: Annual | U14: =R14*P14 -> 2 | V14: =(H14*M14)/AD14 -> 9500 | W14: =RATE(U14,V14,-F14,H14) -> 0.095 | X14: =W14*AD14 -> 0.095 | Y14: =DURATION(N14,O14,M14,D14,AD14) -> 1.413242 | Z14: =Y14/(1+C14) -> 1.290632 | AA14: =-Z14*F14 -> -129063.2 | AB14: None | AC14: India | AD14: =_xlfn.SWITCH(PROPER(TRIM(S14)), "Annual",1, "Semi-Annual",2, "Quarterly",4, "Monthly",12, "") -> 1
A15: 1255NEO25 | B15: NeoGrowth Credit Pvt Ltd. | C15: =RATE(U15,V15,-F15,H15) -> 0.19017603 | D15: =C15*AD15 -> 0.19017603 | F15: 90000 | G15: INR | H15: 100000 | J15: 1 | L15: 23.811976 | M15: 0.1255 | N15: 45286 | O15: 45895 | P15: =ROUND(YEARFRAC(N15,O15),0) -> 2 | Q15: =(M15*H15)/F15 -> 0.13944444 | R15: =IF(S15="Quarterly",4,IF(S15="Semi-annual",2,IF(S15="Annual",1,IF(S15="Pays at maturity",0,IF(S15="Monthly",12,0))))) -> 1 | S15: Annual | U15: =R15*P15 -> 2 | V15: =(H15*M15)/AD15 -> 12550 | W15: =RATE(U15,V15,-F15,H15) -> 0.19017603 | X15: =W15*AD15 -> 0.19017603 | Y15: =DURATION(N15,O15,M15,D15,AD15) -> 1.5495038 | Z15: =Y15/(1+C15) -> 1.3019114 | AA15: =-Z15*F15 -> -117172.03 | AB15: Putable | AC15: India | AD15: =_xlfn.SWITCH(PROPER(TRIM(S15)), "Annual",1, "Semi-Annual",2, "Quarterly",4, "Monthly",12, "") -> 1
A16: 1025UCL25 | B16: Ugro Capital Ltd. | C16: =RATE(U16,V16,-F16,H16) -> 0.10338558 | D16: =C16*AD16 -> 0.10338558 | F16: 998.47 | G16: INR | H16: 1000 | J16: 1 | L16: 11.863723 | M16: 0.1025 | N16: 45349 | O16: 45896 | P16: =ROUND(YEARFRAC(N16,O16),0) -> 2 | Q16: =(M16*H16)/F16 -> 0.10265707 | R16: =IF(S16="Quarterly",4,IF(S16="Semi-annual",2,IF(S16="Annual",1,IF(S16="Pays at maturity",0,IF(S16="Monthly",12,0))))) -> 1 | S16: Annual | U16: =R16*P16 -> 2 | V16: =(H16*M16)/AD16 -> 102.5 | W16: =RATE(U16,V16,-F16,H16) -> 0.10338558 | X16: =W16*AD16 -> 0.10338558 | Y16: =DURATION(N16,O16,M16,D16,AD16) -> 1.4069617 | Z16: =Y16/(1+C16) -> 1.2751315 | AA16: =-Z16*F16 -> -1273.1806 | AB16: None | AC16: India | AD16: =_xlfn.SWITCH(PROPER(TRIM(S16)), "Annual",1, "Semi-Annual",2, "Quarterly",4, "Monthly",12, "") -> 1
A17: 1075UCL25 | B17: Ugro Capital Ltd. | C17: =RATE(U17,V17,-F17,H17) -> 0.085164418 | D17: =C17*AD17 -> 0.085164418 | F17: 1039.55 | G17: INR | H17: 1000 | J17: 4 | L17: -19.204811 | M17: 0.1075 | N17: 45349 | O17: 45896 | P17: =ROUND(YEARFRAC(N17,O17),0) -> 2 | Q17: =(M17*H17)/F17 -> 0.10341013 | R17: =IF(S17="Quarterly",4,IF(S17="Semi-annual",2,IF(S17="Annual",1,IF(S17="Pays at maturity",0,IF(S17="Monthly",12,0))))) -> 1 | S17: Annual | U17: =R17*P17 -> 2 | V17: =(H17*M17)/AD17 -> 107.5 | W17: =RATE(U17,V17,-F17,H17) -> 0.085164418 | X17: =W17*AD17 -> 0.085164418 | Y17: =DURATION(N17,O17,M17,D17,AD17) -> 1.4047056 | Z17: =Y17/(1+C17) -> 1.2944633 | AA17: =-Z17*F17 -> -1345.6594 | AB17: None | AC17: India | AD17: =_xlfn.SWITCH(PROPER(TRIM(S17)), "Annual",1, "Semi-Annual",2, "Quarterly",4, "Monthly",12, "") -> 1
A18: 001CSSL25 | B18: Creixent Special Steels Ltd. | C18: =RATE(U18,V18,-F18,H18) -> -0.051132153 | D18: =C18*AD18 -> -0.051132153 | F18: 1444844 | G18: INR | H18: 1000000 | J18: 1863 | L18: -8.1778983 | M18: 0.0001 | N18: 43340 | O18: 45897 | P18: =ROUND(YEARFRAC(N18,O18),0) -> 7 | Q18: =(M18*H18)/F18 -> 6.9211624e-05 | R18: =IF(S18="Quarterly",4,IF(S18="Semi-annual",2,IF(S18="Annual",1,IF(S18="Pays at maturity",0,IF(S18="Monthly",12,0))))) -> 1 | S18: Annual | U18: =R18*P18 -> 7 | V18: =(H18*M18)/AD18 -> 100 | W18: =RATE(U18,V18,-F18,H18) -> -0.051132153 | X18: =W18*AD18 -> -0.051132153 | Y18: =DURATION(N18,O18,M18,D18,AD18) -> #NUM! | Z18: =Y18/(1+C18) -> #NUM! | AA18: =-Z18*F18 -> #NUM! | AB18: None | AC18: India | AD18: =_xlfn.SWITCH(PROPER(TRIM(S18)), "Annual",1, "Semi-Annual",2, "Quarterly",4, "Monthly",12, "") -> 1
A19: 10SFL25 | B19: Sakthi Finance Ltd. | C19: =RATE(U19,V19,-F19,H19) -> 0.10208836 | D19: =C19*AD19 -> 0.10208836 | F19: 993.41 | G19: INR | H19: 1000 | J19: 17 | L19: 12.051015 | M19: 0.1 | N19: 44406 | O19: 45898 | P19: =ROUND(YEARFRAC(N19,O19),0) -> 4 | Q19: =(M19*H19)/F19 -> 0.10066337 | R19: =IF(S19="Quarterly",4,IF(S19="Semi-annual",2,IF(S19="Annual",1,IF(S19="Pays at maturity",0,IF(S19="Monthly",12,0))))) -> 1 | S19: Annual | U19: =R19*P19 -> 4 | V19: =(H19*M19)/AD19 -> 100 | W19: =RATE(U19,V19,-F19,H19) -> 0.10208836 | X19: =W19*AD19 -> 0.10208836 | Y19: =DURATION(N19,O19,M19,D19,AD19) -> 3.2496304 | Z19: =Y19/(1+C19) -> 2.9486115 | AA19: =-Z19*F19 -> -2929.1802 | AB19: None | AC19: India | AD19: =_xlfn.SWITCH(PROPER(TRIM(S19)), "Annual",1, "Semi-Annual",2, "Quarterly",4, "Monthly",12, "") -> 1
A21: 1085SFL25 | B21: Satin Finserv Ltd. | C21: =RATE(U21,V21,-F21,H21) -> 0.11319127 | D21: =C21*AD21 -> 0.11319127 | F21: 99200 | G21: INR | H21: 100000 | J21: 3 | L21: 14.483944 | M21: 0.1085 | N21: 45355 | O21: 45904 | P21: =ROUND(YEARFRAC(N21,O21),0) -> 2 | Q21: =(M21*H21)/F21 -> 0.109375 | R21: =IF(S21="Quarterly",4,IF(S21="Semi-annual",2,IF(S21="Annual",1,IF(S21="Pays at maturity",0,IF(S21="Monthly",12,0))))) -> 1 | S21: Annual | U21: =R21*P21 -> 2 | V21: =(H21*M21)/AD21 -> 10850 | W21: =RATE(U21,V21,-F21,H21) -> 0.11319127 | X21: =W21*AD21 -> 0.11319127 | Y21: =DURATION(N21,O21,M21,D21,AD21) -> 1.4017464 | Z21: =Y21/(1+C21) -> 1.2592144 | AA21: =-Z21*F21 -> -124914.07 | AB21: None | AC21: India | AD21: =_xlfn.SWITCH(PROPER(TRIM(S21)), "Annual",1, "Semi-Annual",2, "Quarterly",4, "Monthly",12, "") -> 1
A22: 1050VCL25 | B22: Vivriti Capital Pvt Ltd. | C22: =RATE(U22,V22,-F22,H22) -> 0.061183405 | D22: =C22*AD22 -> 0.061183405 | F22: 1080.2 | G22: INR | H22: 1000 | J22: 9 | L22: -50.500936 | M22: 0.105 | N22: 45175 | O22: 45906 | P22: =ROUND(YEARFRAC(N22,O22),0) -> 2 | Q22: =(M22*H22)/F22 -> 0.097204221 | R22: =IF(S22="Quarterly",4,IF(S22="Semi-annual",2,IF(S22="Annual",1,IF(S22="Pays at maturity",0,IF(S22="Monthly",12,0))))) -> 1 | S22: Annual | U22: =R22*P22 -> 2 | V22: =(H22*M22)/AD22 -> 105 | W22: =RATE(U22,V22,-F22,H22) -> 0.061183405 | X22: =W22*AD22 -> 0.061183405 | Y22: =DURATION(N22,O22,M22,D22,AD22) -> 1.9084002 | Z22: =Y22/(1+C22) -> 1.7983698 | AA22: =-Z22*F22 -> -1942.599 | AB22: None | AC22: India | AD22: =_xlfn.SWITCH(PROPER(TRIM(S22)), "Annual",1, "Semi-Annual",2, "Quarterly",4, "Monthly",12, "") -> 1
A23: 1003VCL25 | B23: Vivriti Capital Pvt Ltd. | C23: =RATE(U23,V23,-F23,H23) -> 0.11200985 | D23: =C23*AD23 -> 0.11200985 | F23: 980 | G23: INR | H23: 1000 | J23: 50 | L23: 26.787982 | M23: 0.1003 | N23: 45175 | O23: 45906 | P23: =ROUND(YEARFRAC(N23,O23),0) -> 2 | Q23: =(M23*H23)/F23 -> 0.10234694 | R23: =IF(S23="Quarterly",4,IF(S23="Semi-annual",2,IF(S23="Annual",1,IF(S23="Pays at maturity",0,IF(S23="Monthly",12,0))))) -> 1 | S23: Annual | U23: =R23*P23 -> 2 | V23: =(H23*M23)/AD23 -> 100.3 | W23: =RATE(U23,V23,-F23,H23) -> 0.11200985 | X23: =W23*AD23 -> 0.11200985 | Y23: =DURATION(N23,O23,M23,D23,AD23) -> 1.9079622 | Z23: =Y23/(1+C23) -> 1.7157781 | AA23: =-Z23*F23 -> -1681.4626 | AB23: None | AC23: India | AD23: =_xlfn.SWITCH(PROPER(TRIM(S23)), "Annual",1, "Semi-Annual",2, "Quarterly",4, "Monthly",12, "") -> 1
A24: 965VCL25 | B24: Vivriti Capital Pvt Ltd. | C24: =RATE(U24,V24,-F24,H24) -> 0.24775758 | D24: =C24*AD24 -> 0.99103031 | F24: 251 | G24: INR | H24: 1000 | J24: 1786 | M24: 0.0965 | N24: 45175 | O24: 45906 | P24: =ROUND(YEARFRAC(N24,O24),0) -> 2 | Q24: =(M24*H24)/F24 -> 0.38446215 | R24: =IF(S24="Quarterly",4,IF(S24="Semi-annual",2,IF(S24="Annual",1,IF(S24="Pays at maturity",0,IF(S24="Monthly",12,0))))) -> 4 | S24: Quarterly | U24: =R24*P24 -> 8 | V24: =(H24*M24)/AD24 -> 24.125 | W24: =RATE(U24,V24,-F24,H24) -> 0.24775758 | X24: =W24*AD24 -> 0.99103031 | Y24: =DURATION(N24,O24,M24,D24,AD24) -> 1.6294228 | Z24: =Y24/(1+C24) -> 1.3058809 | AA24: =-Z24*F24 -> -327.77611 | AB24: None | AC24: India | AD24: =_xlfn.SWITCH(PROPER(TRIM(S24)), "Annual",1, "Semi-Annual",2, "Quarterly",4, "Monthly",12, "") -> 4
A25: 910CAGL25 | B25: CreditAccess Grameen Ltd. | C25: =RATE(U25,V25,-F25,H25) -> 0.090118731 | D25: =C25*AD25 -> 0.090118731 | F25: 1001.55 | G25: INR | H25: 1000 | J25: 25 | L25: 8.4053452 | M25: 0.091 | N25: 45176 | O25: 45907 | P25: =ROUND(YEARFRAC(N25,O25),0) -> 2 | Q25: =(M25*H25)/F25 -> 0.090859168 | R25: =IF(S25="Quarterly",4,IF(S25="Semi-annual",2,IF(S25="Annual",1,IF(S25="Pays at maturity",0,IF(S25="Monthly",12,0))))) -> 1 | S25: Annual | U25: =R25*P25 -> 2 | V25: =(H25*M25)/AD25 -> 91 | W25: =RATE(U25,V25,-F25,H25) -> 0.090118731 | X25: =W25*AD25 -> 0.090118731 | Y25: =DURATION(N25,O25,M25,D25,AD25) -> 1.916652 | Z25: =Y25/(1+C25) -> 1.7582049 | AA25: =-Z25*F25 -> -1760.9301 | AB25: None | AC25: India | AD25: =_xlfn.SWITCH(PROPER(TRIM(S25)), "Annual",1, "Semi-Annual",2, "Quarterly",4, "Monthly",12, "") -> 1
A27: 1050CCI25 | B27: Chemmanur Credits & Investments Ltd. | C27: =RATE(U27,V27,-F27,H27) -> 0.11055276 | D27: =C27*AD27 -> 0.11055276 | F27: 995 | G27: INR | H27: 1000 | J27: 10 | L27: 13.418656 | M27: 0.105 | N27: 45362 | O27: 45910 | P27: =ROUND(YEARFRAC(N27,O27),0) -> 1 | Q27: =(M27*H27)/F27 -> 0.10552764 | R27: =IF(S27="Quarterly",4,IF(S27="Semi-annual",2,IF(S27="Annual",1,IF(S27="Pays at maturity",0,IF(S27="Monthly",12,0))))) -> 1 | S27: Annual | U27: =R27*P27 -> 1 | V27: =(H27*M27)/AD27 -> 105 | W27: =RATE(U27,V27,-F27,H27) -> 0.11055276 | X27: =W27*AD27 -> 0.11055276 | Y27: =DURATION(N27,O27,M27,D27,AD27) -> 1.4017677 | Z27: =Y27/(1+C27) -> 1.2622252 | AA27: =-Z27*F27 -> -1255.9141 | AB27: None | AC27: India | AD27: =_xlfn.SWITCH(PROPER(TRIM(S27)), "Annual",1, "Semi-Annual",2, "Quarterly",4, "Monthly",12, "") -> 1
A28: 950KLM25 | B28: KLM Axiva Finvest Ltd. | C28: =RATE(U28,V28,-F28,H28) -> 0.10076784 | D28: =C28*AD28 -> 0.10076784 | F28: 990 | G28: INR | H28: 1000 | J28: 10 | L28: 12.476326 | M28: 0.095 | N28: 45181 | O28: 45911 | P28: =ROUND(YEARFRAC(N28,O28),0) -> 2 | Q28: =(M28*H28)/F28 -> 0.095959596 | R28: =IF(S28="Quarterly",4,IF(S28="Semi-annual",2,IF(S28="Annual",1,IF(S28="Pays at maturity",0,IF(S28="Monthly",12,0))))) -> 1 | S28: Annual | U28: =R28*P28 -> 2 | V28: =(H28*M28)/AD28 -> 95 | W28: =RATE(U28,V28,-F28,H28) -> 0.10076784 | X28: =W28*AD28 -> 0.10076784 | Y28: =DURATION(N28,O28,M28,D28,AD28) -> 1.9100471 | Z28: =Y28/(1+C28) -> 1.7351952 | AA28: =-Z28*F28 -> -1717.8432 | AB28: None | AC28: India | AD28: =_xlfn.SWITCH(PROPER(TRIM(S28)), "Annual",1, "Semi-Annual",2, "Quarterly",4, "Monthly",12, "") -> 1
A29: 95KAFL25 | B29: KLM Axiva Finvest Ltd. | C29: =RATE(U29,V29,-F29,H29) -> 0.11620795 | D29: =C29*AD29 -> 0.11620795 | F29: 981 | G29: INR | H29: 1000 | J29: 10 | L29: 22.086306 | M29: 0.095 | N29: 45512 | O29: 45911 | P29: =ROUND(YEARFRAC(N29,O29),0) -> 1 | Q29: =(M29*H29)/F29 -> 0.096839959 | R29: =IF(S29="Quarterly",4,IF(S29="Semi-annual",2,IF(S29="Annual",1,IF(S29="Pays at maturity",0,IF(S29="Monthly",12,0))))) -> 1 | S29: Annual | U29: =R29*P29 -> 1 | V29: =(H29*M29)/AD29 -> 95 | W29: =RATE(U29,V29,-F29,H29) -> 0.11620795 | X29: =W29*AD29 -> 0.11620795 | Y29: =DURATION(N29,O29,M29,D29,AD29) -> 1.0033767 | Z29: =Y29/(1+C29) -> 0.89891557 | AA29: =-Z29*F29 -> -881.83617 | AB29: None | AC29: India | AD29: =_xlfn.SWITCH(PROPER(TRIM(S29)), "Annual",1, "Semi-Annual",2, "Quarterly",4, "Monthly",12, "") -> 1
A30: 10NFL25 | B30: Navi Finserv Ltd. | C30: =RATE(U30,V30,-F30,H30) -> 0.10173259 | D30: =C30*AD30 -> 0.10173259 | F30: 997 | G30: INR | H30: 1000 | J30: 20 | L30: 12.102345 | M30: 0.1 | N30: 45364 | O30: 45913 | P30: =ROUND(YEARFRAC(N30,O30),0) -> 2 | Q30: =(M30*H30)/F30 -> 0.1003009 | R30: =IF(S30="Quarterly",4,IF(S30="Semi-annual",2,IF(S30="Annual",1,IF(S30="Pays at maturity",0,IF(S30="Monthly",12,0))))) -> 1 | S30: Annual | U30: =R30*P30 -> 2 | V30: =(H30*M30)/AD30 -> 100 | W30: =RATE(U30,V30,-F30,H30) -> 0.10173259 | X30: =W30*AD30 -> 0.10173259 | Y30: =DURATION(N30,O30,M30,D30,AD30) -> 1.4089608 | Z30: =Y30/(1+C30) -> 1.2788591 | AA30: =-Z30*F30 -> -1275.0225 | AB30: None | AC30: India | AD30: =_xlfn.SWITCH(PROPER(TRIM(S30)), "Annual",1, "Semi-Annual",2, "Quarterly",4, "Monthly",12, "") -> 1
A31: 895NHFL25 | B31: Nido Home Finance Ltd. | C31: =RATE(U31,V31,-F31,H31) -> 0.056474072 | D31: =C31*AD31 -> 0.056474072 | F31: 1060.85 | G31: INR | H31: 1000 | J31: 14 | L31: -29.629328 | M31: 0.0895 | N31: 45184 | O31: 45915 | P31: =ROUND(YEARFRAC(N31,O31),0) -> 2 | Q31: =(M31*H31)/F31 -> 0.08436631 | R31: =IF(S31="Quarterly",4,IF(S31="Semi-annual",2,IF(S31="Annual",1,IF(S31="Pays at maturity",0,IF(S31="Monthly",12,0))))) -> 1 | S31: Annual | U31: =R31*P31 -> 2 | V31: =(H31*M31)/AD31 -> 89.5 | W31: =RATE(U31,V31,-F31,H31) -> 0.056474072 | X31: =W31*AD31 -> 0.056474072 | Y31: =DURATION(N31,O31,M31,D31,AD31) -> 1.9201435 | Z31: =Y31/(1+C31) -> 1.8175018 | AA31: =-Z31*F31 -> -1928.0968 | AB31: None | AC31: India | AD31: =_xlfn.SWITCH(PROPER(TRIM(S31)), "Annual",1, "Semi-Annual",2, "Quarterly",4, "Monthly",12, "") -> 1
A32: 1025NFL25A | B32: Navi Finserv Ltd. | C32: =RATE(U32,V32,-F32,H32) -> 0.025260973 | D32: =C32*AD32 -> 0.10104389 | F32: 100136.86 | G32: INR | H32: 100000 | J32: 1 | M32: 0.1025 | N32: 45447 | O32: 45915 | P32: =ROUND(YEARFRAC(N32,O32),0) -> 1 | Q32: =(M32*H32)/F32 -> 0.10235991 | R32: =IF(S32="Quarterly",4,IF(S32="Semi-annual",2,IF(S32="Annual",1,IF(S32="Pays at maturity",0,IF(S32="Monthly",12,0))))) -> 4 | S32: Quarterly | U32: =R32*P32 -> 4 | V32: =(H32*M32)/AD32 -> 2562.5 | W32: =RATE(U32,V32,-F32,H32) -> 0.025260973 | X32: =W32*AD32 -> 0.10104389 | Y32: =DURATION(N32,O32,M32,D32,AD32) -> 1.1900335 | Z32: =Y32/(1+C32) -> 1.1607127 | AA32: =-Z32*F32 -> -116230.13 | AB32: None | AC32: India | AD32: =_xlfn.SWITCH(PROPER(TRIM(S32)), "Annual",1, "Semi-Annual",2, "Quarterly",4, "Monthly",12, "") -> 4
A34: 11IML25 | B34: Indel Money Pvt Ltd. | C34: =RATE(U34,V34,-F34,H34) -> 0.11949556 | D34: =C34*AD34 -> 0.11949556 | F34: 99151.8 | G34: INR | H34: 100000 | J34: 1 | L34: 13.108561 | M34: 0.11 | N34: 45462 | O34: 45919 | P34: =ROUND(YEARFRAC(N34,O34),0) -> 1 | Q34: =(M34*H34)/F34 -> 0.110941 | R34: =IF(S34="Quarterly",4,IF(S34="Semi-annual",2,IF(S34="Annual",1,IF(S34="Pays at maturity",0,IF(S34="Monthly",12,0))))) -> 1 | S34: Annual | U34: =R34*P34 -> 1 | V34: =(H34*M34)/AD34 -> 11000 | W34: =RATE(U34,V34,-F34,H34) -> 0.11949556 | X34: =W34*AD34 -> 0.11949556 | Y34: =DURATION(N34,O34,M34,D34,AD34) -> 1.1501378 | Z34: =Y34/(1+C34) -> 1.0273715 | AA34: =-Z34*F34 -> -101865.73 | AB34: None | AC34: India | AD34: =_xlfn.SWITCH(PROPER(TRIM(S34)), "Annual",1, "Semi-Annual",2, "Quarterly",4, "Monthly",12, "") -> 1
A35: 9MFL25A | B35: Muthoot Fincorp Ltd. | C35: =RATE(U35,V35,-F35,H35) -> 0.050701231 | D35: =C35*AD35 -> 0.050701231 | F35: 1073 | G35: INR | H35: 1000 | J35: 1 | L35: -29.815757 | M35: 0.09 | N35: 45189 | O35: 45920 | P35: =ROUND(YEARFRAC(N35,O35),0) -> 2 | Q35: =(M35*H35)/F35 -> 0.08387698 | R35: =IF(S35="Quarterly",4,IF(S35="Semi-annual",2,IF(S35="Annual",1,IF(S35="Pays at maturity",0,IF(S35="Monthly",12,0))))) -> 1 | S35: Annual | U35: =R35*P35 -> 2 | V35: =(H35*M35)/AD35 -> 90 | W35: =RATE(U35,V35,-F35,H35) -> 0.050701231 | X35: =W35*AD35 -> 0.050701231 | Y35: =DURATION(N35,O35,M35,D35,AD35) -> 1.9201705 | Z35: =Y35/(1+C35) -> 1.8275133 | AA35: =-Z35*F35 -> -1960.9218 | AB35: None | AC35: India | AD35: =_xlfn.SWITCH(PROPER(TRIM(S35)), "Annual",1, "Semi-Annual",2, "Quarterly",4, "Monthly",12, "") -> 1
A36: 865MFL25A | B36: Muthoot Fincorp Ltd. | C36: =RATE(U36,V36,-F36,H36) -> 0.092086768 | D36: =C36*AD36 -> 0.092086768 | F36: 990.2 | G36: INR | H36: 1000 | J36: 21 | L36: 14.756278 | M36: 0.0865 | N36: 45189 | O36: 45920 | P36: =ROUND(YEARFRAC(N36,O36),0) -> 2 | Q36: =(M36*H36)/F36 -> 0.08735609 | R36: =IF(S36="Quarterly",4,IF(S36="Semi-annual",2,IF(S36="Annual",1,IF(S36="Pays at maturity",0,IF(S36="Monthly",12,0))))) -> 1 | S36: Annual | U36: =R36*P36 -> 2 | V36: =(H36*M36)/AD36 -> 86.5 | W36: =RATE(U36,V36,-F36,H36) -> 0.092086768 | X36: =W36*AD36 -> 0.092086768 | Y36: =DURATION(N36,O36,M36,D36,AD36) -> 1.9200099 | Z36: =Y36/(1+C36) -> 1.7581112 | AA36: =-Z36*F36 -> -1740.8817 | AB36: None | AC36: India | AD36: =_xlfn.SWITCH(PROPER(TRIM(S36)), "Annual",1, "Semi-Annual",2, "Quarterly",4, "Monthly",12, "") -> 1
A39: 1025KFL25 | B39: Kosamattam Finance Ltd. | C39: =RATE(U39,V39,-F39,H39) -> 0.10353902 | D39: =C39*AD39 -> 0.10353902 | F39: 995 | G39: INR | H39: 1000 | J39: 313 | L39: 11.200611 | M39: 0.1025 | N39: 43367 | O39: 45923 | P39: =ROUND(YEARFRAC(N39,O39),0) -> 7 | Q39: =(M39*H39)/F39 -> 0.10301508 | R39: =IF(S39="Quarterly",4,IF(S39="Semi-annual",2,IF(S39="Annual",1,IF(S39="Pays at maturity",0,IF(S39="Monthly",12,0))))) -> 1 | S39: Annual | U39: =R39*P39 -> 7 | V39: =(H39*M39)/AD39 -> 102.5 | W39: =RATE(U39,V39,-F39,H39) -> 0.10353902 | X39: =W39*AD39 -> 0.10353902 | Y39: =DURATION(N39,O39,M39,D39,AD39) -> 5.3162326 | Z39: =Y39/(1+C39) -> 4.8174396 | AA39: =-Z39*F39 -> -4793.3524 | AB39: None | AC39: India | AD39: =_xlfn.SWITCH(PROPER(TRIM(S39)), "Annual",1, "Semi-Annual",2, "Quarterly",4, "Monthly",12, "") -> 1
A42: 925SCL25 | B42: Sammaan Capital Ltd. | C42: =RATE(U42,V42,-F42,H42) -> 0.09857653 | D42: =C42*AD42 -> 0.09857653 | F42: 983 | G42: INR | H42: 1000 | J42: 200 | L42: 15.474703 | M42: 0.0888 | N42: 45195 | O42: 45926 | P42: =ROUND(YEARFRAC(N42,O42),0) -> 2 | Q42: =(M42*H42)/F42 -> 0.090335707 | R42: =IF(S42="Quarterly",4,IF(S42="Semi-annual",2,IF(S42="Annual",1,IF(S42="Pays at maturity",0,IF(S42="Monthly",12,0))))) -> 1 | S42: Annual | U42: =R42*P42 -> 2 | V42: =(H42*M42)/AD42 -> 88.8 | W42: =RATE(U42,V42,-F42,H42) -> 0.09857653 | X42: =W42*AD42 -> 0.09857653 | Y42: =DURATION(N42,O42,M42,D42,AD42) -> 1.9177702 | Z42: =Y42/(1+C42) -> 1.7456865 | AA42: =-Z42*F42 -> -1716.0098 | AB42: None | AC42: India | AD42: =_xlfn.SWITCH(PROPER(TRIM(S42)), "Annual",1, "Semi-Annual",2, "Quarterly",4, "Monthly",12, "") -> 1
A43: 965SCL25E | B43: Sammaan Capital Ltd. | C43: =RATE(U43,V43,-F43,H43) -> 0.056447068 | D43: =C43*AD43 -> 0.056447068 | F43: 1073.8 | G43: INR | H43: 1000 | J43: 325 | L43: -25.854442 | M43: 0.0965 | N43: 45195 | O43: 45926 | P43: =ROUND(YEARFRAC(N43,O43),0) -> 2 | Q43: =(M43*H43)/F43 -> 0.089867759 | R43: =IF(S43="Quarterly",4,IF(S43="Semi-annual",2,IF(S43="Annual",1,IF(S43="Pays at maturity",0,IF(S43="Monthly",12,0))))) -> 1 | S43: Annual | U43: =R43*P43 -> 2 | V43: =(H43*M43)/AD43 -> 96.5 | W43: =RATE(U43,V43,-F43,H43) -> 0.056447068 | X43: =W43*AD43 -> 0.056447068 | Y43: =DURATION(N43,O43,M43,D43,AD43) -> 1.914934 | Z43: =Y43/(1+C43) -> 1.8126171 | AA43: =-Z43*F43 -> -1946.3882 | AB43: None | AC43: India | AD43: =_xlfn.SWITCH(PROPER(TRIM(S43)), "Annual",1, "Semi-Annual",2, "Quarterly",4, "Monthly",12, "") -> 1
A44: 1050UCL25 | B44: Ugro Capital Ltd. | C44: =RATE(U44,V44,-F44,H44) -> 0.10699059 | D44: =C44*AD44 -> 0.10699059 | F44: 995.11 | G44: INR | H44: 1000 | J44: 30 | L44: 13.269205 | M44: 0.105 | N44: 44830 | O44: 45926 | P44: =ROUND(YEARFRAC(N44,O44),0) -> 3 | Q44: =(M44*H44)/F44 -> 0.10551597 | R44: =IF(S44="Quarterly",4,IF(S44="Semi-annual",2,IF(S44="Annual",1,IF(S44="Pays at maturity",0,IF(S44="Monthly",12,0))))) -> 1 | S44: Annual | U44: =R44*P44 -> 3 | V44: =(H44*M44)/AD44 -> 105 | W44: =RATE(U44,V44,-F44,H44) -> 0.10699059 | X44: =W44*AD44 -> 0.10699059 | Y44: =DURATION(N44,O44,M44,D44,AD44) -> 2.7232589 | Z44: =Y44/(1+C44) -> 2.460056 | AA44: =-Z44*F44 -> -2448.0264 | AB44: None | AC44: India | AD44: =_xlfn.SWITCH(PROPER(TRIM(S44)), "Annual",1, "Semi-Annual",2, "Quarterly",4, "Monthly",12, "") -> 1
A45: 1115LFL25 | B45: Lendingkart Finance Ltd. | C45: =RATE(U45,V45,-F45,H45) -> 0.089036518 | D45: =C45*AD45 -> 1.0684382 | F45: 22000 | G45: INR | H45: 100000 | J45: 1 | M45: 0.1115 | N45: 45196 | O45: 45927 | P45: =ROUND(YEARFRAC(N45,O45),0) -> 2 | Q45: =(M45*H45)/F45 -> 0.50681818 | R45: =IF(S45="Quarterly",4,IF(S45="Semi-annual",2,IF(S45="Annual",1,IF(S45="Pays at maturity",0,IF(S45="Monthly",12,0))))) -> 12 | S45: Monthly | U45: =R45*P45 -> 24 | V45: =(H45*M45)/AD45 -> 929.16667 | W45: =RATE(U45,V45,-F45,H45) -> 0.089036518 | X45: =W45*AD45 -> 1.0684382 | Y45: =DURATION(N45,O45,M45,D45,AD45) -> #NUM! | Z45: =Y45/(1+C45) -> #NUM! | AA45: =-Z45*F45 -> #NUM! | AB45: None | AC45: India | AD45: =_xlfn.SWITCH(PROPER(TRIM(S45)), "Annual",1, "Semi-Annual",2, "Quarterly",4, "Monthly",12, "") -> 12
A46: 875KFL2025 | B46: Kosamattam Finance Ltd. | C46: =RATE(U46,V46,-F46,H46) -> 0.093209447 | D46: =C46*AD46 -> 0.093209447 | F46: 990 | G46: INR | H46: 1000 | J46: 500 | L46: 12.252151 | M46: 0.0875 | N46: 45197 | O46: 45927 | P46: =ROUND(YEARFRAC(N46,O46),0) -> 2 | Q46: =(M46*H46)/F46 -> 0.088383838 | R46: =IF(S46="Quarterly",4,IF(S46="Semi-annual",2,IF(S46="Annual",1,IF(S46="Pays at maturity",0,IF(S46="Monthly",12,0))))) -> 1 | S46: Annual | U46: =R46*P46 -> 2 | V46: =(H46*M46)/AD46 -> 87.5 | W46: =RATE(U46,V46,-F46,H46) -> 0.093209447 | X46: =W46*AD46 -> 0.093209447 | Y46: =DURATION(N46,O46,M46,D46,AD46) -> 1.9163742 | Z46: =Y46/(1+C46) -> 1.7529799 | AA46: =-Z46*F46 -> -1735.4501 | AB46: None | AC46: India | AD46: =_xlfn.SWITCH(PROPER(TRIM(S46)), "Annual",1, "Semi-Annual",2, "Quarterly",4, "Monthly",12, "") -> 1
A47: 847SCL25 | B47: Sammaan Capital Ltd. | C47: =RATE(U47,V47,-F47,H47) -> 0.069327694 | D47: =C47*AD47 -> 0.069327694 | F47: 1062.2 | G47: INR | H47: 1000 | J47: 25 | L47: -22.220767 | M47: 0.093 | N47: 44832 | O47: 45928 | P47: =ROUND(YEARFRAC(N47,O47),0) -> 3 | Q47: =(M47*H47)/F47 -> 0.087554133 | R47: =IF(S47="Quarterly",4,IF(S47="Semi-annual",2,IF(S47="Annual",1,IF(S47="Pays at maturity",0,IF(S47="Monthly",12,0))))) -> 1 | S47: Annual | U47: =R47*P47 -> 3 | V47: =(H47*M47)/AD47 -> 93 | W47: =RATE(U47,V47,-F47,H47) -> 0.069327694 | X47: =W47*AD47 -> 0.069327694 | Y47: =DURATION(N47,O47,M47,D47,AD47) -> 2.7596752 | Z47: =Y47/(1+C47) -> 2.5807572 | AA47: =-Z47*F47 -> -2741.2803 | AB47: None | AC47: India | AD47: =_xlfn.SWITCH(PROPER(TRIM(S47)), "Annual",1, "Semi-Annual",2, "Quarterly",4, "Monthly",12, "") -> 1
A48: 955SCL27 | B48: Sammaan Capital Ltd. | C48: =RATE(U48,V48,-F48,H48) -> 0.091380134 | D48: =C48*AD48 -> 0.091380134 | F48: 995 | G48: INR | H48: 1000 | J48: 1 | L48: 11.682235 | M48: 0.0894 | N48: 44832 | O48: 45928 | P48: =ROUND(YEARFRAC(N48,O48),0) -> 3 | Q48: =(M48*H48)/F48 -> 0.089849246 | R48: =IF(S48="Quarterly",4,IF(S48="Semi-annual",2,IF(S48="Annual",1,IF(S48="Pays at maturity",0,IF(S48="Monthly",12,0))))) -> 1 | S48: Annual | U48: =R48*P48 -> 3 | V48: =(H48*M48)/AD48 -> 89.4 | W48: =RATE(U48,V48,-F48,H48) -> 0.091380134 | X48: =W48*AD48 -> 0.091380134 | Y48: =DURATION(N48,O48,M48,D48,AD48) -> 2.7599143 | Z48: =Y48/(1+C48) -> 2.5288295 | AA48: =-Z48*F48 -> -2516.1854 | AB48: None | AC48: India | AD48: =_xlfn.SWITCH(PROPER(TRIM(S48)), "Annual",1, "Semi-Annual",2, "Quarterly",4, "Monthly",12, "") -> 1
A50: 105MMFL25B | B50: Muthoottu Mini Financiers Ltd. | C50: =RATE(U50,V50,-F50,H50) -> 0.11039786 | D50: =C50*AD50 -> 0.11039786 | F50: 980.07 | G50: INR | H50: 1000 | J50: 10 | L50: 15.533246 | M50: 0.105 | N50: 44104 | O50: 45929 | P50: =ROUND(YEARFRAC(N50,O50),0) -> 5 | Q50: =(M50*H50)/F50 -> 0.1071352 | R50: =IF(S50="Quarterly",4,IF(S50="Semi-annual",2,IF(S50="Annual",1,IF(S50="Pays at maturity",0,IF(S50="Monthly",12,0))))) -> 1 | S50: Annual | U50: =R50*P50 -> 5 | V50: =(H50*M50)/AD50 -> 105 | W50: =RATE(U50,V50,-F50,H50) -> 0.11039786 | X50: =W50*AD50 -> 0.11039786 | Y50: =DURATION(N50,O50,M50,D50,AD50) -> 4.1236381 | Z50: =Y50/(1+C50) -> 3.7136582 | AA50: =-Z50*F50 -> -3639.645 | AB50: None | AC50: India | AD50: =_xlfn.SWITCH(PROPER(TRIM(S50)), "Annual",1, "Semi-Annual",2, "Quarterly",4, "Monthly",12, "") -> 1
A51: 875ARKA25 | B51: Arka Fincap Ltd. | C51: =RATE(U51,V51,-F51,H51) -> 0.14385314 | D51: =C51*AD51 -> 0.14385314 | F51: 870010 | G51: INR | H51: 1000000 | J51: 2 | L51: 27.099671 | M51: 0.0875 | N51: 44833 | O51: 45929 | P51: =ROUND(YEARFRAC(N51,O51),0) -> 3 | Q51: =(M51*H51)/F51 -> 0.10057356 | R51: =IF(S51="Quarterly",4,IF(S51="Semi-annual",2,IF(S51="Annual",1,IF(S51="Pays at maturity",0,IF(S51="Monthly",12,0))))) -> 1 | S51: Annual | U51: =R51*P51 -> 3 | V51: =(H51*M51)/AD51 -> 87500 | W51: =RATE(U51,V51,-F51,H51) -> 0.14385314 | X51: =W51*AD51 -> 0.14385314 | Y51: =DURATION(N51,O51,M51,D51,AD51) -> 2.7472819 | Z51: =Y51/(1+C51) -> 2.4017786 | AA51: =-Z51*F51 -> -2089571.4 | AB51: None | AC51: India | AD51: =_xlfn.SWITCH(PROPER(TRIM(S51)), "Annual",1, "Semi-Annual",2, "Quarterly",4, "Monthly",12, "") -> 1
A52: 775MFLTD25 | B52: Muthoot Finance Ltd. | C52: =RATE(U52,V52,-F52,H52) -> 0.046976397 | D52: =C52*AD52 -> 0.046976397 | F52: 1057 | G52: INR | H52: 1000 | J52: 68 | L52: -13.171121 | M52: 0.0775 | N52: 45203 | O52: 45934 | P52: =ROUND(YEARFRAC(N52,O52),0) -> 2 | Q52: =(M52*H52)/F52 -> 0.073320719 | R52: =IF(S52="Quarterly",4,IF(S52="Semi-annual",2,IF(S52="Annual",1,IF(S52="Pays at maturity",0,IF(S52="Monthly",12,0))))) -> 1 | S52: Annual | U52: =R52*P52 -> 2 | V52: =(H52*M52)/AD52 -> 77.5 | W52: =RATE(U52,V52,-F52,H52) -> 0.046976397 | X52: =W52*AD52 -> 0.046976397 | Y52: =DURATION(N52,O52,M52,D52,AD52) -> 1.9299691 | Z52: =Y52/(1+C52) -> 1.843374 | AA52: =-Z52*F52 -> -1948.4463 | AB52: None | AC52: India | AD52: =_xlfn.SWITCH(PROPER(TRIM(S52)), "Annual",1, "Semi-Annual",2, "Quarterly",4, "Monthly",12, "") -> 1
A54: 736NTPC25D | B54: Ntpc Ltd. | C54: =RATE(U54,V54,-F54,H54) -> 0.066321749 | D54: =C54*AD54 -> 0.066321749 | F54: 1052 | G54: INR | H54: 1000 | J54: 9 | L54: -16.743046 | M54: 0.0736 | N54: 42282 | O54: 45935 | P54: =ROUND(YEARFRAC(N54,O54),0) -> 10 | Q54: =(M54*H54)/F54 -> 0.069961977 | R54: =IF(S54="Quarterly",4,IF(S54="Semi-annual",2,IF(S54="Annual",1,IF(S54="Pays at maturity",0,IF(S54="Monthly",12,0))))) -> 1 | S54: Annual | U54: =R54*P54 -> 10 | V54: =(H54*M54)/AD54 -> 73.6 | W54: =RATE(U54,V54,-F54,H54) -> 0.066321749 | X54: =W54*AD54 -> 0.066321749 | Y54: =DURATION(N54,O54,M54,D54,AD54) -> 7.487695 | Z54: =Y54/(1+C54) -> 7.0219847 | AA54: =-Z54*F54 -> -7387.1279 | AB54: None | AC54: India | AD54: =_xlfn.SWITCH(PROPER(TRIM(S54)), "Annual",1, "Semi-Annual",2, "Quarterly",4, "Monthly",12, "") -> 1
A55: 711NTPC25A | B55: Ntpc Ltd. | C55: =RATE(U55,V55,-F55,H55) -> 0.034213518 | D55: =C55*AD55 -> 0.034213518 | F55: 1307.99 | G55: INR | H55: 1000 | J55: 10 | L55: -14.186525 | M55: 0.0711 | N55: 42282 | O55: 45935 | P55: =ROUND(YEARFRAC(N55,O55),0) -> 10 | Q55: =(M55*H55)/F55 -> 0.054358214 | R55: =IF(S55="Quarterly",4,IF(S55="Semi-annual",2,IF(S55="Annual",1,IF(S55="Pays at maturity",0,IF(S55="Monthly",12,0))))) -> 1 | S55: Annual | U55: =R55*P55 -> 10 | V55: =(H55*M55)/AD55 -> 71.1 | W55: =RATE(U55,V55,-F55,H55) -> 0.034213518 | X55: =W55*AD55 -> 0.034213518 | Y55: =DURATION(N55,O55,M55,D55,AD55) -> 7.8318417 | Z55: =Y55/(1+C55) -> 7.5727513 | AA55: =-Z55*F55 -> -9905.0829 | AB55: None | AC55: India | AD55: =_xlfn.SWITCH(PROPER(TRIM(S55)), "Annual",1, "Semi-Annual",2, "Quarterly",4, "Monthly",12, "") -> 1
A56: 115ESPL25 | B56: EarlySalary Service Pvt Ltd. | C56: =RATE(U56,V56,-F56,H56) -> 0.1108462 | D56: =C56*AD56 -> 0.1108462 | F56: 100710.55 | G56: INR | H56: 100000 | J56: 2 | L56: 7.9852508 | M56: 0.115 | N56: 45371 | O56: 45936 | P56: =ROUND(YEARFRAC(N56,O56),0) -> 2 | Q56: =(M56*H56)/F56 -> 0.11418863 | R56: =IF(S56="Quarterly",4,IF(S56="Semi-annual",2,IF(S56="Annual",1,IF(S56="Pays at maturity",0,IF(S56="Monthly",12,0))))) -> 1 | S56: Annual | U56: =R56*P56 -> 2 | V56: =(H56*M56)/AD56 -> 11500 | W56: =RATE(U56,V56,-F56,H56) -> 0.1108462 | X56: =W56*AD56 -> 0.1108462 | Y56: =DURATION(N56,O56,M56,D56,AD56) -> 1.4416502 | Z56: =Y56/(1+C56) -> 1.2977946 | AA56: =-Z56*F56 -> -130701.61 | AB56: None | AC56: India | AD56: =_xlfn.SWITCH(PROPER(TRIM(S56)), "Annual",1, "Semi-Annual",2, "Quarterly",4, "Monthly",12, "") -> 1
A57: 830SFL25 | B57: Shriram City Union Finance Ltd. | C57: =RATE(U57,V57,-F57,H57) -> 0.085213903 | D57: =C57*AD57 -> 0.085213903 | F57: 994347.81 | G57: INR | H57: 1000000 | J57: 1 | L57: 8.9094499 | M57: 0.083 | N57: 44841 | O57: 45937 | P57: =ROUND(YEARFRAC(N57,O57),0) -> 3 | Q57: =(M57*H57)/F57 -> 0.083471798 | R57: =IF(S57="Quarterly",4,IF(S57="Semi-annual",2,IF(S57="Annual",1,IF(S57="Pays at maturity",0,IF(S57="Monthly",12,0))))) -> 1 | S57: Annual | U57: =R57*P57 -> 3 | V57: =(H57*M57)/AD57 -> 83000 | W57: =RATE(U57,V57,-F57,H57) -> 0.085213903 | X57: =W57*AD57 -> 0.085213903 | Y57: =DURATION(N57,O57,M57,D57,AD57) -> 2.7752877 | Z57: =Y57/(1+C57) -> 2.5573646 | AA57: =-Z57*F57 -> -2542909.9 | AB57: None | AC57: India | AD57: =_xlfn.SWITCH(PROPER(TRIM(S57)), "Annual",1, "Semi-Annual",2, "Quarterly",4, "Monthly",12, "") -> 1
A58: 1260MFL25A | B58: Manba Finance Ltd. | C58: =RATE(U58,V58,-F58,H58) -> 0.13262649 | D58: =C58*AD58 -> 1.5915179 | F58: 12552.49 | G58: INR | H58: 100000 | J58: 1 | M58: 0.126 | N58: 45209 | O58: 45940 | P58: =ROUND(YEARFRAC(N58,O58),0) -> 2 | Q58: =(M58*H58)/F58 -> 1.0037849 | R58: =IF(S58="Quarterly",4,IF(S58="Semi-annual",2,IF(S58="Annual",1,IF(S58="Pays at maturity",0,IF(S58="Monthly",12,0))))) -> 12 | S58: Monthly | U58: =R58*P58 -> 24 | V58: =(H58*M58)/AD58 -> 1050 | W58: =RATE(U58,V58,-F58,H58) -> 0.13262649 | X58: =W58*AD58 -> 1.5915179 | Y58: =DURATION(N58,O58,M58,D58,AD58) -> #NUM! | Z58: =Y58/(1+C58) -> #NUM! | AA58: =-Z58*F58 -> #NUM! | AB58: None | AC58: India | AD58: =_xlfn.SWITCH(PROPER(TRIM(S58)), "Annual",1, "Semi-Annual",2, "Quarterly",4, "Monthly",12, "") -> 12
A59: 925MRHFL25 | B59: Mahindra Rural Housing Finance Ltd. | C59: =RATE(U59,V59,-F59,H59) -> 0.092500158 | D59: =C59*AD59 -> 0.092500158 | F59: 999999 | G59: INR | H59: 1000000 | J59: 2 | L59: 9.2500922 | M59: 0.0925 | N59: 42290 | O59: 45943 | P59: =ROUND(YEARFRAC(N59,O59),0) -> 10 | Q59: =(M59*H59)/F59 -> 0.092500093 | R59: =IF(S59="Quarterly",4,IF(S59="Semi-annual",2,IF(S59="Annual",1,IF(S59="Pays at maturity",0,IF(S59="Monthly",12,0))))) -> 1 | S59: Annual | U59: =R59*P59 -> 10 | V59: =(H59*M59)/AD59 -> 92500 | W59: =RATE(U59,V59,-F59,H59) -> 0.092500158 | X59: =W59*AD59 -> 0.092500158 | Y59: =DURATION(N59,O59,M59,D59,AD59) -> 6.9347917 | Z59: =Y59/(1+C59) -> 6.3476345 | AA59: =-Z59*F59 -> -6347628.1 | AB59: None | AC59: India | AD59: =_xlfn.SWITCH(PROPER(TRIM(S59)), "Annual",1, "Semi-Annual",2, "Quarterly",4, "Monthly",12, "") -> 1
A60: 1206FCL25 | B60: Finstars Capital Ltd. | C60: =RATE(U60,V60,-F60,H60) -> 0.10955971 | D60: =C60*AD60 -> 0.10955971 | F60: 1027000 | G60: INR | H60: 1000000 | J60: 1 | L60: 8.8612858 | M60: 0.1206 | N60: 44847 | O60: 45943 | P60: =ROUND(YEARFRAC(N60,O60),0) -> 3 | Q60: =(M60*H60)/F60 -> 0.11742941 | R60: =IF(S60="Quarterly",4,IF(S60="Semi-annual",2,IF(S60="Annual",1,IF(S60="Pays at maturity",0,IF(S60="Monthly",12,0))))) -> 1 | S60: Annual | U60: =R60*P60 -> 3 | V60: =(H60*M60)/AD60 -> 120600 | W60: =RATE(U60,V60,-F60,H60) -> 0.10955971 | X60: =W60*AD60 -> 0.10955971 | Y60: =DURATION(N60,O60,M60,D60,AD60) -> 2.6929475 | Z60: =Y60/(1+C60) -> 2.4270416 | AA60: =-Z60*F60 -> -2492571.7 | AB60: None | AC60: India | AD60: =_xlfn.SWITCH(PROPER(TRIM(S60)), "Annual",1, "Semi-Annual",2, "Quarterly",4, "Monthly",12, "") -> 1
A61: TTM5059311 | B61: Jaguar Land Rover Automotive Plc | C61: =RATE(U61,V61,-F61,H61) -> 0.03862755 | D61: =C61*AD61 -> 0.0772551 | F61: 1001 | G61: USD | H61: 1000 | J61: 810000 | M61: 0.0775 | N61: 44117 | O61: 45945 | P61: =ROUND(YEARFRAC(N61,O61),0) -> 5 | Q61: =(M61*H61)/F61 -> 0.077422577 | R61: =IF(S61="Quarterly",4,IF(S61="Semi-annual",2,IF(S61="Annual",1,IF(S61="Pays at maturity",0,IF(S61="Monthly",12,0))))) -> 2 | S61: Semi-annual | U61: =R61*P61 -> 10 | V61: =(H61*M61)/AD61 -> 38.75 | W61: =RATE(U61,V61,-F61,H61) -> 0.03862755 | X61: =W61*AD61 -> 0.0772551 | Y61: =DURATION(N61,O61,M61,D61,AD61) -> 4.0869405 | Z61: =Y61/(1+C61) -> 3.9349433 | AA61: =-Z61*F61 -> -3938.8782 | AB61: Callable | AC61: India | AD61: =_xlfn.SWITCH(PROPER(TRIM(S61)), "Annual",1, "Semi-Annual",2, "Quarterly",4, "Monthly",12, "") -> 2
A63: 1070MML25 | B63: Muthoot Mercantile Ltd. | C63: =RATE(U63,V63,-F63,H63) -> 0.22863485 | D63: =C63*AD63 -> 0.22863485 | F63: 901 | G63: INR | H63: 1000 | J63: 10 | L63: 58.509924 | M63: 0.107 | N63: 45546 | O63: 45946 | P63: =ROUND(YEARFRAC(N63,O63),0) -> 1 | Q63: =(M63*H63)/F63 -> 0.11875694 | R63: =IF(S63="Quarterly",4,IF(S63="Semi-annual",2,IF(S63="Annual",1,IF(S63="Pays at maturity",0,IF(S63="Monthly",12,0))))) -> 1 | S63: Annual | U63: =R63*P63 -> 1 | V63: =(H63*M63)/AD63 -> 107 | W63: =RATE(U63,V63,-F63,H63) -> 0.22863485 | X63: =W63*AD63 -> 0.22863485 | Y63: =DURATION(N63,O63,M63,D63,AD63) -> 0.99107143 | Z63: =Y63/(1+C63) -> 0.80664441 | AA63: =-Z63*F63 -> -726.78661 | AB63: None | AC63: India | AD63: =_xlfn.SWITCH(PROPER(TRIM(S63)), "Annual",1, "Semi-Annual",2, "Quarterly",4, "Monthly",12, "") -> 1
A64: 711PFCL25 | B64: Power Finance Corp. Ltd. | C64: =RATE(U64,V64,-F64,H64) -> 0.041771107 | D64: =C64*AD64 -> 0.041771107 | F64: 1235.8 | G64: INR | H64: 1000 | J64: 8 | L64: -62.525823 | M64: 0.0711 | N64: 42294 | O64: 45947 | P64: =ROUND(YEARFRAC(N64,O64),0) -> 10 | Q64: =(M64*H64)/F64 -> 0.057533581 | R64: =IF(S64="Quarterly",4,IF(S64="Semi-annual",2,IF(S64="Annual",1,IF(S64="Pays at maturity",0,IF(S64="Monthly",12,0))))) -> 1 | S64: Annual | U64: =R64*P64 -> 10 | V64: =(H64*M64)/AD64 -> 71.1 | W64: =RATE(U64,V64,-F64,H64) -> 0.041771107 | X64: =W64*AD64 -> 0.041771107 | Y64: =DURATION(N64,O64,M64,D64,AD64) -> 7.7627467 | Z64: =Y64/(1+C64) -> 7.4514897 | AA64: =-Z64*F64 -> -9208.551 | AB64: None | AC64: India | AD64: =_xlfn.SWITCH(PROPER(TRIM(S64)), "Annual",1, "Semi-Annual",2, "Quarterly",4, "Monthly",12, "") -> 1
A65: 95KLM25 | B65: KLM Axiva Finvest Ltd. | C65: =RATE(U65,V65,-F65,H65) -> 0.099014171 | D65: =C65*AD65 -> 0.099014171 | F65: 990 | G65: INR | H65: 1000 | J65: 50 | L65: 13.246325 | M65: 0.095 | N65: 44852 | O65: 45947 | P65: =ROUND(YEARFRAC(N65,O65),0) -> 3 | Q65: =(M65*H65)/F65 -> 0.095959596 | R65: =IF(S65="Quarterly",4,IF(S65="Semi-annual",2,IF(S65="Annual",1,IF(S65="Pays at maturity",0,IF(S65="Monthly",12,0))))) -> 1 | S65: Annual | U65: =R65*P65 -> 3 | V65: =(H65*M65)/AD65 -> 95 | W65: =RATE(U65,V65,-F65,H65) -> 0.099014171 | X65: =W65*AD65 -> 0.099014171 | Y65: =DURATION(N65,O65,M65,D65,AD65) -> 2.7431459 | Z65: =Y65/(1+C65) -> 2.496006 | AA65: =-Z65*F65 -> -2471.0459 | AB65: None | AC65: India | AD65: =_xlfn.SWITCH(PROPER(TRIM(S65)), "Annual",1, "Semi-Annual",2, "Quarterly",4, "Monthly",12, "") -> 1
A66: 925KFIL25 | B66: Kosamattam Finance Ltd. | C66: =RATE(U66,V66,-F66,H66) -> 0.097706397 | D66: =C66*AD66 -> 0.097706397 | F66: 987 | G66: INR | H66: 1000 | J66: 6 | L66: 13.588937 | M66: 0.0925 | N66: 44669 | O66: 45947 | P66: =ROUND(YEARFRAC(N66,O66),0) -> 3 | Q66: =(M66*H66)/F66 -> 0.093718338 | R66: =IF(S66="Quarterly",4,IF(S66="Semi-annual",2,IF(S66="Annual",1,IF(S66="Pays at maturity",0,IF(S66="Monthly",12,0))))) -> 1 | S66: Annual | U66: =R66*P66 -> 3 | V66: =(H66*M66)/AD66 -> 92.5 | W66: =RATE(U66,V66,-F66,H66) -> 0.097706397 | X66: =W66*AD66 -> 0.097706397 | Y66: =DURATION(N66,O66,M66,D66,AD66) -> 3.0129246 | Z66: =Y66/(1+C66) -> 2.7447454 | AA66: =-Z66*F66 -> -2709.0637 | AB66: None | AC66: India | AD66: =_xlfn.SWITCH(PROPER(TRIM(S66)), "Annual",1, "Semi-Annual",2, "Quarterly",4, "Monthly",12, "") -> 1
A67: 736PFCL25 | B67: Power Finance Corp. Ltd. | C67: =RATE(U67,V67,-F67,H67) -> 0.064664069 | D67: =C67*AD67 -> 0.064664069 | F67: 1064.34 | G67: INR | H67: 1000 | J67: 1 | L67: -17.331589 | M67: 0.0736 | N67: 42294 | O67: 45947 | P67: =ROUND(YEARFRAC(N67,O67),0) -> 10 | Q67: =(M67*H67)/F67 -> 0.069150835 | R67: =IF(S67="Quarterly",4,IF(S67="Semi-annual",2,IF(S67="Annual",1,IF(S67="Pays at maturity",0,IF(S67="Monthly",12,0))))) -> 1 | S67: Annual | U67: =R67*P67 -> 10 | V67: =(H67*M67)/AD67 -> 73.6 | W67: =RATE(U67,V67,-F67,H67) -> 0.064664069 | X67: =W67*AD67 -> 0.064664069 | Y67: =DURATION(N67,O67,M67,D67,AD67) -> 7.503771 | Z67: =Y67/(1+C67) -> 7.0480175 | AA67: =-Z67*F67 -> -7501.487 | AB67: None | AC67: India | AD67: =_xlfn.SWITCH(PROPER(TRIM(S67)), "Annual",1, "Semi-Annual",2, "Quarterly",4, "Monthly",12, "") -> 1
A68: 1025NFL25 | B68: Navi Finserv Ltd. | C68: =RATE(U68,V68,-F68,H68) -> 0.094498562 | D68: =C68*AD68 -> 0.094498562 | F68: 1013.99 | G68: INR | H68: 1000 | J68: 1 | L68: 4.3859698 | M68: 0.1025 | N68: 45125 | O68: 45948 | P68: =ROUND(YEARFRAC(N68,O68),0) -> 2 | Q68: =(M68*H68)/F68 -> 0.10108581 | R68: =IF(S68="Quarterly",4,IF(S68="Semi-annual",2,IF(S68="Annual",1,IF(S68="Pays at maturity",0,IF(S68="Monthly",12,0))))) -> 1 | S68: Annual | U68: =R68*P68 -> 2 | V68: =(H68*M68)/AD68 -> 102.5 | W68: =RATE(U68,V68,-F68,H68) -> 0.094498562 | X68: =W68*AD68 -> 0.094498562 | Y68: =DURATION(N68,O68,M68,D68,AD68) -> 1.9825097 | Z68: =Y68/(1+C68) -> 1.8113407 | AA68: =-Z68*F68 -> -1836.6813 | AB68: None | AC68: India | AD68: =_xlfn.SWITCH(PROPER(TRIM(S68)), "Annual",1, "Semi-Annual",2, "Quarterly",4, "Monthly",12, "") -> 1
A69: 1075NFL25 | B69: Navi Finserv Ltd. | C69: =RATE(U69,V69,-F69,H69) -> 0.10517921 | D69: =C69*AD69 -> 0.10517921 | F69: 1004 | G69: INR | H69: 1000 | J69: 610 | L69: 9.0356963 | M69: 0.1075 | N69: 45125 | O69: 45948 | P69: =ROUND(YEARFRAC(N69,O69),0) -> 2 | Q69: =(M69*H69)/F69 -> 0.10707171 | R69: =IF(S69="Quarterly",4,IF(S69="Semi-annual",2,IF(S69="Annual",1,IF(S69="Pays at maturity",0,IF(S69="Monthly",12,0))))) -> 1 | S69: Annual | U69: =R69*P69 -> 2 | V69: =(H69*M69)/AD69 -> 107.5 | W69: =RATE(U69,V69,-F69,H69) -> 0.10517921 | X69: =W69*AD69 -> 0.10517921 | Y69: =DURATION(N69,O69,M69,D69,AD69) -> 1.969056 | Z69: =Y69/(1+C69) -> 1.7816622 | AA69: =-Z69*F69 -> -1788.7888 | AB69: None | AC69: India | AD69: =_xlfn.SWITCH(PROPER(TRIM(S69)), "Annual",1, "Semi-Annual",2, "Quarterly",4, "Monthly",12, "") -> 1
A71: 89EFSL25 | B71: Edelweiss Financial Services Ltd. | C71: =RATE(U71,V71,-F71,H71) -> 0.090383637 | D71: =C71*AD71 -> 0.090383637 | F71: 996.5 | G71: INR | H71: 1000 | J71: 150 | L71: 10.371694 | M71: 0.089 | N71: 44854 | O71: 45950 | P71: =ROUND(YEARFRAC(N71,O71),0) -> 3 | Q71: =(M71*H71)/F71 -> 0.089312594 | R71: =IF(S71="Quarterly",4,IF(S71="Semi-annual",2,IF(S71="Annual",1,IF(S71="Pays at maturity",0,IF(S71="Monthly",12,0))))) -> 1 | S71: Annual | U71: =R71*P71 -> 3 | V71: =(H71*M71)/AD71 -> 89 | W71: =RATE(U71,V71,-F71,H71) -> 0.090383637 | X71: =W71*AD71 -> 0.090383637 | Y71: =DURATION(N71,O71,M71,D71,AD71) -> 2.7610616 | Z71: =Y71/(1+C71) -> 2.5321928 | AA71: =-Z71*F71 -> -2523.3301 | AB71: None | AC71: India | AD71: =_xlfn.SWITCH(PROPER(TRIM(S71)), "Annual",1, "Semi-Annual",2, "Quarterly",4, "Monthly",12, "") -> 1
A72: 975UPPCL25 | B72: Uttar Pradesh Power Corp. Ltd. | C72: =RATE(U72,V72,-F72,H72) -> 0.059387738 | D72: =C72*AD72 -> 0.23755095 | F72: 503500 | G72: INR | H72: 1000000 | J72: 1 | M72: 0.0975 | N72: 43074 | O72: 45950 | P72: =ROUND(YEARFRAC(N72,O72),0) -> 8 | Q72: =(M72*H72)/F72 -> 0.19364449 | R72: =IF(S72="Quarterly",4,IF(S72="Semi-annual",2,IF(S72="Annual",1,IF(S72="Pays at maturity",0,IF(S72="Monthly",12,0))))) -> 4 | S72: Quarterly | U72: =R72*P72 -> 32 | V72: =(H72*M72)/AD72 -> 24375 | W72: =RATE(U72,V72,-F72,H72) -> 0.059387738 | X72: =W72*AD72 -> 0.23755095 | Y72: =DURATION(N72,O72,M72,D72,AD72) -> 4.4151531 | Z72: =Y72/(1+C72) -> 4.167646 | AA72: =-Z72*F72 -> -2098409.8 | AB72: None | AC72: India | AD72: =_xlfn.SWITCH(PROPER(TRIM(S72)), "Annual",1, "Semi-Annual",2, "Quarterly",4, "Monthly",12, "") -> 4
A73: 925EFSL25 | B73: Edelweiss Financial Services Ltd. | C73: =RATE(U73,V73,-F73,H73) -> 0.069651458 | D73: =C73*AD73 -> 0.069651458 | F73: 1060 | G73: INR | H73: 1000 | J73: 17 | L73: -13.977296 | M73: 0.0925 | N73: 44854 | O73: 45950 | P73: =ROUND(YEARFRAC(N73,O73),0) -> 3 | Q73: =(M73*H73)/F73 -> 0.087264151 | R73: =IF(S73="Quarterly",4,IF(S73="Semi-annual",2,IF(S73="Annual",1,IF(S73="Pays at maturity",0,IF(S73="Monthly",12,0))))) -> 1 | S73: Annual | U73: =R73*P73 -> 3 | V73: =(H73*M73)/AD73 -> 92.5 | W73: =RATE(U73,V73,-F73,H73) -> 0.069651458 | X73: =W73*AD73 -> 0.069651458 | Y73: =DURATION(N73,O73,M73,D73,AD73) -> 2.7605667 | Z73: =Y73/(1+C73) -> 2.5808096 | AA73: =-Z73*F73 -> -2735.6581 | AB73: None | AC73: India | AD73: =_xlfn.SWITCH(PROPER(TRIM(S73)), "Annual",1, "Semi-Annual",2, "Quarterly",4, "Monthly",12, "") -> 1
A74: 934WBSE25A | B74: West Bengal State Electricity Distribution Co. Ltd. | C74: =RATE(U74,V74,-F74,H74) -> 0.049945476 | D74: =C74*AD74 -> 0.099890951 | F74: 950078.06 | G74: INR | H74: 1000000 | J74: 1 | M74: 0.0934 | N74: 40476 | O74: 45955 | P74: =ROUND(YEARFRAC(N74,O74),0) -> 15 | Q74: =(M74*H74)/F74 -> 0.098307712 | R74: =IF(S74="Quarterly",4,IF(S74="Semi-annual",2,IF(S74="Annual",1,IF(S74="Pays at maturity",0,IF(S74="Monthly",12,0))))) -> 2 | S74: Semi-annual | U74: =R74*P74 -> 30 | V74: =(H74*M74)/AD74 -> 46700 | W74: =RATE(U74,V74,-F74,H74) -> 0.049945476 | X74: =W74*AD74 -> 0.099890951 | Y74: =DURATION(N74,O74,M74,D74,AD74) -> 8.1848929 | Z74: =Y74/(1+C74) -> 7.7955409 | AA74: =-Z74*F74 -> -7406372.3 | AB74: None | AC74: India | AD74: =_xlfn.SWITCH(PROPER(TRIM(S74)), "Annual",1, "Semi-Annual",2, "Quarterly",4, "Monthly",12, "") -> 2
A76: 895EFSL25A | B76: Edelweiss Financial Services Ltd. | C76: =RATE(U76,V76,-F76,H76) -> 0.06214611 | D76: =C76*AD76 -> 0.06214611 | F76: 1050 | G76: INR | H76: 1000 | J76: 100 | L76: -9.5813492 | M76: 0.0895 | N76: 45225 | O76: 45956 | P76: =ROUND(YEARFRAC(N76,O76),0) -> 2 | Q76: =(M76*H76)/F76 -> 0.085238095 | R76: =IF(S76="Quarterly",4,IF(S76="Semi-annual",2,IF(S76="Annual",1,IF(S76="Pays at maturity",0,IF(S76="Monthly",12,0))))) -> 1 | S76: Annual | U76: =R76*P76 -> 2 | V76: =(H76*M76)/AD76 -> 89.5 | W76: =RATE(U76,V76,-F76,H76) -> 0.06214611 | X76: =W76*AD76 -> 0.06214611 | Y76: =DURATION(N76,O76,M76,D76,AD76) -> 1.9197492 | Z76: =Y76/(1+C76) -> 1.8074248 | AA76: =-Z76*F76 -> -1897.796 | AB76: None | AC76: India | AD76: =_xlfn.SWITCH(PROPER(TRIM(S76)), "Annual",1, "Semi-Annual",2, "Quarterly",4, "Monthly",12, "") -> 1
A79: 96MFL25 | B79: Muthoot Fincorp Ltd. | C79: =RATE(U79,V79,-F79,H79) -> 0.080911392 | D79: =C79*AD79 -> 0.080911392 | F79: 1060.1 | G79: INR | H79: 1000 | J79: 30 | L79: -10.651735 | M79: 0.096 | N79: 44132 | O79: 45958 | P79: =ROUND(YEARFRAC(N79,O79),0) -> 5 | Q79: =(M79*H79)/F79 -> 0.090557495 | R79: =IF(S79="Quarterly",4,IF(S79="Semi-annual",2,IF(S79="Annual",1,IF(S79="Pays at maturity",0,IF(S79="Monthly",12,0))))) -> 1 | S79: Annual | U79: =R79*P79 -> 5 | V79: =(H79*M79)/AD79 -> 96 | W79: =RATE(U79,V79,-F79,H79) -> 0.080911392 | X79: =W79*AD79 -> 0.080911392 | Y79: =DURATION(N79,O79,M79,D79,AD79) -> 4.2226121 | Z79: =Y79/(1+C79) -> 3.9065294 | AA79: =-Z79*F79 -> -4141.3118 | AB79: None | AC79: India | AD79: =_xlfn.SWITCH(PROPER(TRIM(S79)), "Annual",1, "Semi-Annual",2, "Quarterly",4, "Monthly",12, "") -> 1
A80: 915MFL25 | B80: Muthoot Fincorp Ltd. | C80: =RATE(U80,V80,-F80,H80) -> 0.089983221 | D80: =C80*AD80 -> 0.089983221 | F80: 1005.9 | G80: INR | H80: 1000 | J80: 1 | L80: 6.9117716 | M80: 0.0915 | N80: 44132 | O80: 45958 | P80: =ROUND(YEARFRAC(N80,O80),0) -> 5 | Q80: =(M80*H80)/F80 -> 0.090963316 | R80: =IF(S80="Quarterly",4,IF(S80="Semi-annual",2,IF(S80="Annual",1,IF(S80="Pays at maturity",0,IF(S80="Monthly",12,0))))) -> 1 | S80: Annual | U80: =R80*P80 -> 5 | V80: =(H80*M80)/AD80 -> 91.5 | W80: =RATE(U80,V80,-F80,H80) -> 0.089983221 | X80: =W80*AD80 -> 0.089983221 | Y80: =DURATION(N80,O80,M80,D80,AD80) -> 4.2315595 | Z80: =Y80/(1+C80) -> 3.8822245 | AA80: =-Z80*F80 -> -3905.1296 | AB80: None | AC80: India | AD80: =_xlfn.SWITCH(PROPER(TRIM(S80)), "Annual",1, "Semi-Annual",2, "Quarterly",4, "Monthly",12, "") -> 1
A82: 1075CCL25 | B82: Chemmanur Credits & Investments Ltd. | C82: =RATE(U82,V82,-F82,H82) -> 0.1075 | D82: =C82*AD82 -> 0.1075 | F82: 1000 | G82: INR | H82: 1000 | J82: 5 | L82: 10.75 | M82: 0.1075 | N82: 45233 | O82: 45962 | P82: =ROUND(YEARFRAC(N82,O82),0) -> 2 | Q82: =(M82*H82)/F82 -> 0.1075 | R82: =IF(S82="Quarterly",4,IF(S82="Semi-annual",2,IF(S82="Annual",1,IF(S82="Pays at maturity",0,IF(S82="Monthly",12,0))))) -> 1 | S82: Annual | U82: =R82*P82 -> 2 | V82: =(H82*M82)/AD82 -> 107.5 | W82: =RATE(U82,V82,-F82,H82) -> 0.1075 | X82: =W82*AD82 -> 0.1075 | Y82: =DURATION(N82,O82,M82,D82,AD82) -> 1.897379 | Z82: =Y82/(1+C82) -> 1.713209 | AA82: =-Z82*F82 -> -1713.209 | AB82: None | AC82: India | AD82: =_xlfn.SWITCH(PROPER(TRIM(S82)), "Annual",1, "Semi-Annual",2, "Quarterly",4, "Monthly",12, "") -> 1
A84: 9MFL25 | B84: Muthoot Fincorp Ltd. | C84: =RATE(U84,V84,-F84,H84) -> 0.0636838 | D84: =C84*AD84 -> 0.0636838 | F84: 1048 | G84: INR | H84: 1000 | J84: 50 | L84: -3.6148103 | M84: 0.09 | N84: 45231 | O84: 45962 | P84: =ROUND(YEARFRAC(N84,O84),0) -> 2 | Q84: =(M84*H84)/F84 -> 0.085877863 | R84: =IF(S84="Quarterly",4,IF(S84="Semi-annual",2,IF(S84="Annual",1,IF(S84="Pays at maturity",0,IF(S84="Monthly",12,0))))) -> 1 | S84: Annual | U84: =R84*P84 -> 2 | V84: =(H84*M84)/AD84 -> 90 | W84: =RATE(U84,V84,-F84,H84) -> 0.0636838 | X84: =W84*AD84 -> 0.0636838 | Y84: =DURATION(N84,O84,M84,D84,AD84) -> 1.9192637 | Z84: =Y84/(1+C84) -> 1.8043555 | AA84: =-Z84*F84 -> -1890.9646 | AB84: None | AC84: India | AD84: =_xlfn.SWITCH(PROPER(TRIM(S84)), "Annual",1, "Semi-Annual",2, "Quarterly",4, "Monthly",12, "") -> 1
A85: 865MF25 | B85: Muthoot Fincorp Ltd. | C85: =RATE(U85,V85,-F85,H85) -> 0.089453849 | D85: =C85*AD85 -> 0.089453849 | F85: 994.8 | G85: INR | H85: 1000 | J85: 200 | L85: 10.325917 | M85: 0.0865 | N85: 45231 | O85: 45962 | P85: =ROUND(YEARFRAC(N85,O85),0) -> 2 | Q85: =(M85*H85)/F85 -> 0.086952151 | R85: =IF(S85="Quarterly",4,IF(S85="Semi-annual",2,IF(S85="Annual",1,IF(S85="Pays at maturity",0,IF(S85="Monthly",12,0))))) -> 1 | S85: Annual | U85: =R85*P85 -> 2 | V85: =(H85*M85)/AD85 -> 86.5 | W85: =RATE(U85,V85,-F85,H85) -> 0.089453849 | X85: =W85*AD85 -> 0.089453849 | Y85: =DURATION(N85,O85,M85,D85,AD85) -> 1.9201874 | Z85: =Y85/(1+C85) -> 1.7625229 | AA85: =-Z85*F85 -> -1753.3578 | AB85: None | AC85: India | AD85: =_xlfn.SWITCH(PROPER(TRIM(S85)), "Annual",1, "Semi-Annual",2, "Quarterly",4, "Monthly",12, "") -> 1
A87: MFLTDI25 | B87: Muthoot Finance Ltd. | C87: =RATE(U87,V87,-F87,H87) -> 0.073837261 | D87: =C87*AD87 -> 0.073837261 | F87: 990 | G87: INR | H87: 1000 | J87: 999 | L87: 10.453155 | M87: 0.07 | N87: 44868 | O87: 45964 | P87: =ROUND(YEARFRAC(N87,O87),0) -> 3 | Q87: =(M87*H87)/F87 -> 0.070707071 | R87: =IF(S87="Quarterly",4,IF(S87="Semi-annual",2,IF(S87="Annual",1,IF(S87="Pays at maturity",0,IF(S87="Monthly",12,0))))) -> 1 | S87: Annual | U87: =R87*P87 -> 3 | V87: =(H87*M87)/AD87 -> 70 | W87: =RATE(U87,V87,-F87,H87) -> 0.073837261 | X87: =W87*AD87 -> 0.073837261 | Y87: =DURATION(N87,O87,M87,D87,AD87) -> 2.8069918 | Z87: =Y87/(1+C87) -> 2.6139825 | AA87: =-Z87*F87 -> -2587.8427 | AB87: None | AC87: India | AD87: =_xlfn.SWITCH(PROPER(TRIM(S87)), "Annual",1, "Semi-Annual",2, "Quarterly",4, "Monthly",12, "") -> 1
A89: 87SCL27A | B89: Sammaan Capital Ltd. | C89: =RATE(U89,V89,-F89,H89) -> 0.0894 | D89: =C89*AD89 -> 0.0894 | F89: 1000 | G89: INR | H89: 1000 | J89: 99 | L89: 8.94 | M89: 0.0894 | N89: 44868 | O89: 45964 | P89: =ROUND(YEARFRAC(N89,O89),0) -> 3 | Q89: =(M89*H89)/F89 -> 0.0894 | R89: =IF(S89="Quarterly",4,IF(S89="Semi-annual",2,IF(S89="Annual",1,IF(S89="Pays at maturity",0,IF(S89="Monthly",12,0))))) -> 1 | S89: Annual | U89: =R89*P89 -> 3 | V89: =(H89*M89)/AD89 -> 89.4 | W89: =RATE(U89,V89,-F89,H89) -> 0.0894 | X89: =W89*AD89 -> 0.0894 | Y89: =DURATION(N89,O89,M89,D89,AD89) -> 2.7605439 | Z89: =Y89/(1+C89) -> 2.5340039 | AA89: =-Z89*F89 -> -2534.0039 | AB89: None | AC89: India | AD89: =_xlfn.SWITCH(PROPER(TRIM(S89)), "Annual",1, "Semi-Annual",2, "Quarterly",4, "Monthly",12, "") -> 1
A90: 9PEL25 | B90: Piramal Enterprises Ltd. | C90: =RATE(U90,V90,-F90,H90) -> 0.057393286 | D90: =C90*AD90 -> 0.057393286 | F90: 1060 | G90: INR | H90: 1000 | J90: 12 | L90: -11.568053 | M90: 0.09 | N90: 45233 | O90: 45964 | P90: =ROUND(YEARFRAC(N90,O90),0) -> 2 | Q90: =(M90*H90)/F90 -> 0.08490566 | R90: =IF(S90="Quarterly",4,IF(S90="Semi-annual",2,IF(S90="Annual",1,IF(S90="Pays at maturity",0,IF(S90="Monthly",12,0))))) -> 1 | S90: Annual | U90: =R90*P90 -> 2 | V90: =(H90*M90)/AD90 -> 90 | W90: =RATE(U90,V90,-F90,H90) -> 0.057393286 | X90: =W90*AD90 -> 0.057393286 | Y90: =DURATION(N90,O90,M90,D90,AD90) -> 1.9197029 | Z90: =Y90/(1+C90) -> 1.8155051 | AA90: =-Z90*F90 -> -1924.4354 | AB90: None | AC90: India | AD90: =_xlfn.SWITCH(PROPER(TRIM(S90)), "Annual",1, "Semi-Annual",2, "Quarterly",4, "Monthly",12, "") -> 1
A91: MFLIV25 | B91: Muthoot Finance Ltd. | C91: =RATE(U91,V91,-F91,H91) -> 0.058327788 | D91: =C91*AD91 -> 0.058327788 | F91: 1038 | G91: INR | H91: 1000 | J91: 50 | L91: -5.8637172 | M91: 0.0725 | N91: 44868 | O91: 45964 | P91: =ROUND(YEARFRAC(N91,O91),0) -> 3 | Q91: =(M91*H91)/F91 -> 0.069845857 | R91: =IF(S91="Quarterly",4,IF(S91="Semi-annual",2,IF(S91="Annual",1,IF(S91="Pays at maturity",0,IF(S91="Monthly",12,0))))) -> 1 | S91: Annual | U91: =R91*P91 -> 3 | V91: =(H91*M91)/AD91 -> 72.5 | W91: =RATE(U91,V91,-F91,H91) -> 0.058327788 | X91: =W91*AD91 -> 0.058327788 | Y91: =DURATION(N91,O91,M91,D91,AD91) -> 2.805648 | Z91: =Y91/(1+C91) -> 2.6510199 | AA91: =-Z91*F91 -> -2751.7586 | AB91: None | AC91: India | AD91: =_xlfn.SWITCH(PROPER(TRIM(S91)), "Annual",1, "Semi-Annual",2, "Quarterly",4, "Monthly",12, "") -> 1
A93: 88SCL25 | B93: Sammaan Capital Ltd. | C93: =RATE(U93,V93,-F93,H93) -> 0.080236024 | D93: =C93*AD93 -> 0.080236024 | F93: 1020 | G93: INR | H93: 1000 | J93: 100 | L93: 4.7588765 | M93: 0.088 | N93: 44868 | O93: 45964 | P93: =ROUND(YEARFRAC(N93,O93),0) -> 3 | Q93: =(M93*H93)/F93 -> 0.08627451 | R93: =IF(S93="Quarterly",4,IF(S93="Semi-annual",2,IF(S93="Annual",1,IF(S93="Pays at maturity",0,IF(S93="Monthly",12,0))))) -> 1 | S93: Annual | U93: =R93*P93 -> 3 | V93: =(H93*M93)/AD93 -> 88 | W93: =RATE(U93,V93,-F93,H93) -> 0.080236024 | X93: =W93*AD93 -> 0.080236024 | Y93: =DURATION(N93,O93,M93,D93,AD93) -> 2.7663331 | Z93: =Y93/(1+C93) -> 2.5608599 | AA93: =-Z93*F93 -> -2612.0771 | AB93: None | AC93: India | AD93: =_xlfn.SWITCH(PROPER(TRIM(S93)), "Annual",1, "Semi-Annual",2, "Quarterly",4, "Monthly",12, "") -> 1
A94: 93SCL25 | B94: Sammaan Capital Ltd. | C94: =RATE(U94,V94,-F94,H94) -> 0.081331026 | D94: =C94*AD94 -> 0.081331026 | F94: 1030 | G94: INR | H94: 1000 | J94: 150 | L94: 2.5467677 | M94: 0.093 | N94: 44868 | O94: 45964 | P94: =ROUND(YEARFRAC(N94,O94),0) -> 3 | Q94: =(M94*H94)/F94 -> 0.090291262 | R94: =IF(S94="Quarterly",4,IF(S94="Semi-annual",2,IF(S94="Annual",1,IF(S94="Pays at maturity",0,IF(S94="Monthly",12,0))))) -> 1 | S94: Annual | U94: =R94*P94 -> 3 | V94: =(H94*M94)/AD94 -> 93 | W94: =RATE(U94,V94,-F94,H94) -> 0.081331026 | X94: =W94*AD94 -> 0.081331026 | Y94: =DURATION(N94,O94,M94,D94,AD94) -> 2.75578 | Z94: =Y94/(1+C94) -> 2.5485073 | AA94: =-Z94*F94 -> -2624.9625 | AB94: None | AC94: India | AD94: =_xlfn.SWITCH(PROPER(TRIM(S94)), "Annual",1, "Semi-Annual",2, "Quarterly",4, "Monthly",12, "") -> 1
... A105: 925SCL25A | B105: Sammaan Capital Ltd. | C105: =RATE(U105,V105,-F105,H105) -> 0.13148145 | D105: =C105*AD105 -> 0.13148145 | F105: 935.1 | G105: INR | H105: 1000 | J105: 12 | L105: 32.714139 | M105: 0.0925 | N105: 45239 | O105: 45970 | P105: =ROUND(YEARFRAC(N105,O105),0) -> 2 | Q105: =(M105*H105)/F105 -> 0.098919902 | R105: =IF(S105="Quarterly",4,IF(S105="Semi-annual",2,IF(S105="Annual",1,IF(S105="Pays at maturity",0,IF(S105="Monthly",12,0))))) -> 1 | S105: Annual | U105: =R105*P105 -> 2 | V105: =(H105*M105)/AD105 -> 92.5 | W105: =RATE(U105,V105,-F105,H105) -> 0.13148145 | X105: =W105*AD105 -> 0.13148145 | Y105: =DURATION(N105,O105,M105,D105,AD105) -> 1.9125749 | Z105: =Y105/(1+C105) -> 1.6903281 | AA105: =-Z105*F105 -> -1580.6258 | AB105: None | AC105: India | AD105: =_xlfn.SWITCH(PROPER(TRIM(S105)), "Annual",1, "Semi-Annual",2, "Quarterly",4, "Monthly",12, "") -> 1
A107: 881TFC25 | B107: Tourism Finance Corp. of India Ltd. | C107: =RATE(U107,V107,-F107,H107) -> 0.04329257 | D107: =C107*AD107 -> 0.086585141 | F107: 101000 | G107: INR | H107: 100000 | J107: 10 | M107: 0.0881 | N107: 42317 | O107: 45970 | P107: =ROUND(YEARFRAC(N107,O107),0) -> 10 | Q107: =(M107*H107)/F107 -> 0.087227723 | R107: =IF(S107="Quarterly",4,IF(S107="Semi-annual",2,IF(S107="Annual",1,IF(S107="Pays at maturity",0,IF(S107="Monthly",12,0))))) -> 2 | S107: Semi-annual | U107: =R107*P107 -> 20 | V107: =(H107*M107)/AD107 -> 4405 | W107: =RATE(U107,V107,-F107,H107) -> 0.04329257 | X107: =W107*AD107 -> 0.086585141 | Y107: =DURATION(N107,O107,M107,D107,AD107) -> 6.8639566 | Z107: =Y107/(1+C107) -> 6.5791291 | AA107: =-Z107*F107 -> -664492.04 | AB107: None | AC107: India | AD107: =_xlfn.SWITCH(PROPER(TRIM(S107)), "Annual",1, "Semi-Annual",2, "Quarterly",4, "Monthly",12, "") -> 2
A109: 966IFSL25 | B109: InCred Financial Services Ltd. | C109: =RATE(U109,V109,-F109,H109) -> 0.10530443 | D109: =C109*AD109 -> 0.10530443 | F109: 985 | G109: INR | H109: 1000 | J109: 8 | L109: 13.281091 | M109: 0.0966 | N109: 45240 | O109: 45971 | P109: =ROUND(YEARFRAC(N109,O109),0) -> 2 | Q109: =(M109*H109)/F109 -> 0.098071066 | R109: =IF(S109="Quarterly",4,IF(S109="Semi-annual",2,IF(S109="Annual",1,IF(S109="Pays at maturity",0,IF(S109="Monthly",12,0))))) -> 1 | S109: Annual | U109: =R109*P109 -> 2 | V109: =(H109*M109)/AD109 -> 96.6 | W109: =RATE(U109,V109,-F109,H109) -> 0.10530443 | X109: =W109*AD109 -> 0.10530443 | Y109: =DURATION(N109,O109,M109,D109,AD109) -> 1.9112723 | Z109: =Y109/(1+C109) -> 1.7291818 | AA109: =-Z109*F109 -> -1703.2441 | AB109: None | AC109: India | AD109: =_xlfn.SWITCH(PROPER(TRIM(S109)), "Annual",1, "Semi-Annual",2, "Quarterly",4, "Monthly",12, "") -> 1
A110: 10MMFL25 | B110: Muthoottu Mini Financiers Ltd. | C110: =RATE(U110,V110,-F110,H110) -> 0.1 | D110: =C110*AD110 -> 0.1 | F110: 100000 | G110: INR | H110: 100000 | J110: 1 | L110: 10 | M110: 0.1 | N110: 45240 | O110: 45971 | P110: =ROUND(YEARFRAC(N110,O110),0) -> 2 | Q110: =(M110*H110)/F110 -> 0.1 | R110: =IF(S110="Quarterly",4,IF(S110="Semi-annual",2,IF(S110="Annual",1,IF(S110="Pays at maturity",0,IF(S110="Monthly",12,0))))) -> 1 | S110: Annual | U110: =R110*P110 -> 2 | V110: =(H110*M110)/AD110 -> 10000 | W110: =RATE(U110,V110,-F110,H110) -> 0.1 | X110: =W110*AD110 -> 0.1 | Y110: =DURATION(N110,O110,M110,D110,AD110) -> 1.9090909 | Z110: =Y110/(1+C110) -> 1.7355372 | AA110: =-Z110*F110 -> -173553.72 | AB110: None | AC110: India | AD110: =_xlfn.SWITCH(PROPER(TRIM(S110)), "Annual",1, "Semi-Annual",2, "Quarterly",4, "Monthly",12, "") -> 1
A111: 975CIFCP25 | B111: Chaitanya India Fin Credit Pvt Ltd. | C111: =RATE(U111,V111,-F111,H111) -> 0.097423689 | D111: =C111*AD111 -> 0.097423689 | F111: 100013.29 | G111: INR | H111: 100000 | J111: 7 | L111: 9.7230419 | M111: 0.0975 | N111: 45240 | O111: 45971 | P111: =ROUND(YEARFRAC(N111,O111),0) -> 2 | Q111: =(M111*H111)/F111 -> 0.097487044 | R111: =IF(S111="Quarterly",4,IF(S111="Semi-annual",2,IF(S111="Annual",1,IF(S111="Pays at maturity",0,IF(S111="Monthly",12,0))))) -> 1 | S111: Annual | U111: =R111*P111 -> 2 | V111: =(H111*M111)/AD111 -> 9750 | W111: =RATE(U111,V111,-F111,H111) -> 0.097423689 | X111: =W111*AD111 -> 0.097423689 | Y111: =DURATION(N111,O111,M111,D111,AD111) -> 1.9111674 | Z111: =Y111/(1+C111) -> 1.7415036 | AA111: =-Z111*F111 -> -174173.51 | AB111: None | AC111: India | AD111: =_xlfn.SWITCH(PROPER(TRIM(S111)), "Annual",1, "Semi-Annual",2, "Quarterly",4, "Monthly",12, "") -> 1
A112: 955IFSL25 | B112: InCred Financial Services Ltd. | C112: =RATE(U112,V112,-F112,H112) -> 0.24692916 | D112: =C112*AD112 -> 0.98771662 | F112: 251.25 | G112: INR | H112: 1000 | J112: 1 | M112: 0.0955 | N112: 45240 | O112: 45971 | P112: =ROUND(YEARFRAC(N112,O112),0) -> 2 | Q112: =(M112*H112)/F112 -> 0.3800995 | R112: =IF(S112="Quarterly",4,IF(S112="Semi-annual",2,IF(S112="Annual",1,IF(S112="Pays at maturity",0,IF(S112="Monthly",12,0))))) -> 4 | S112: Quarterly | U112: =R112*P112 -> 8 | V112: =(H112*M112)/AD112 -> 23.875 | W112: =RATE(U112,V112,-F112,H112) -> 0.24692916 | X112: =W112*AD112 -> 0.98771662 | Y112: =DURATION(N112,O112,M112,D112,AD112) -> 1.6330393 | Z112: =Y112/(1+C112) -> 1.3096488 | AA112: =-Z112*F112 -> -329.04926 | AB112: None | AC112: India | AD112: =_xlfn.SWITCH(PROPER(TRIM(S112)), "Annual",1, "Semi-Annual",2, "Quarterly",4, "Monthly",12, "") -> 4
A113: 7IIL25 | B113: India Infradebt Ltd. | C113: =RATE(U113,V113,-F113,H113) -> 0.066697377 | D113: =C113*AD113 -> 0.066697377 | F113: 1013662 | G113: INR | H113: 1000000 | J113: 10 | L113: 6.6201401 | M113: 0.07 | N113: 44147 | O113: 45973 | P113: =ROUND(YEARFRAC(N113,O113),0) -> 5 | Q113: =(M113*H113)/F113 -> 0.069056549 | R113: =IF(S113="Quarterly",4,IF(S113="Semi-annual",2,IF(S113="Annual",1,IF(S113="Pays at maturity",0,IF(S113="Monthly",12,0))))) -> 1 | S113: Annual | U113: =R113*P113 -> 5 | V113: =(H113*M113)/AD113 -> 70000 | W113: =RATE(U113,V113,-F113,H113) -> 0.066697377 | X113: =W113*AD113 -> 0.066697377 | Y113: =DURATION(N113,O113,M113,D113,AD113) -> 4.3918429 | Z113: =Y113/(1+C113) -> 4.1172342 | AA113: =-Z113*F113 -> -4173483.9 | AB113: None | AC113: India | AD113: =_xlfn.SWITCH(PROPER(TRIM(S113)), "Annual",1, "Semi-Annual",2, "Quarterly",4, "Monthly",12, "") -> 1
A115: 875JMFSL25 | B115: JM Financial Services Ltd. | C115: =RATE(U115,V115,-F115,H115) -> 0.059842212 | D115: =C115*AD115 -> 0.059842212 | F115: 105071.88 | G115: INR | H115: 100000 | J115: 1 | L115: 3.9119032 | M115: 0.0875 | N115: 45250 | O115: 45981 | P115: =ROUND(YEARFRAC(N115,O115),0) -> 2 | Q115: =(M115*H115)/F115 -> 0.083276325 | R115: =IF(S115="Quarterly",4,IF(S115="Semi-annual",2,IF(S115="Annual",1,IF(S115="Pays at maturity",0,IF(S115="Monthly",12,0))))) -> 1 | S115: Annual | U115: =R115*P115 -> 2 | V115: =(H115*M115)/AD115 -> 8750 | W115: =RATE(U115,V115,-F115,H115) -> 0.059842212 | X115: =W115*AD115 -> 0.059842212 | Y115: =DURATION(N115,O115,M115,D115,AD115) -> 1.9214257 | Z115: =Y115/(1+C115) -> 1.8129357 | AA115: =-Z115*F115 -> -190488.56 | AB115: None | AC115: India | AD115: =_xlfn.SWITCH(PROPER(TRIM(S115)), "Annual",1, "Semi-Annual",2, "Quarterly",4, "Monthly",12, "") -> 1
A116: 105MMFL25C | B116: Muthoottu Mini Financiers Ltd. | C116: =RATE(U116,V116,-F116,H116) -> 0.10714906 | D116: =C116*AD116 -> 0.10714906 | F116: 992 | G116: INR | H116: 1000 | J116: 200 | L116: 12.643103 | M116: 0.105 | N116: 44159 | O116: 45982 | P116: =ROUND(YEARFRAC(N116,O116),0) -> 5 | Q116: =(M116*H116)/F116 -> 0.10584677 | R116: =IF(S116="Quarterly",4,IF(S116="Semi-annual",2,IF(S116="Annual",1,IF(S116="Pays at maturity",0,IF(S116="Monthly",12,0))))) -> 1 | S116: Annual | U116: =R116*P116 -> 5 | V116: =(H116*M116)/AD116 -> 105 | W116: =RATE(U116,V116,-F116,H116) -> 0.10714906 | X116: =W116*AD116 -> 0.10714906 | Y116: =DURATION(N116,O116,M116,D116,AD116) -> 4.12377 | Z116: =Y116/(1+C116) -> 3.7246746 | AA116: =-Z116*F116 -> -3694.8772 | AB116: None | AC116: India | AD116: =_xlfn.SWITCH(PROPER(TRIM(S116)), "Annual",1, "Semi-Annual",2, "Quarterly",4, "Monthly",12, "") -> 1
A118: 960CAGL25 | B118: CreditAccess Grameen Ltd. | C118: =RATE(U118,V118,-F118,H118) -> 0.1000213 | D118: =C118*AD118 -> 0.1000213 | F118: 990 | G118: INR | H118: 1000 | J118: 20 | L118: 12.577336 | M118: 0.096 | N118: 44888 | O118: 45984 | P118: =ROUND(YEARFRAC(N118,O118),0) -> 3 | Q118: =(M118*H118)/F118 -> 0.096969697 | R118: =IF(S118="Quarterly",4,IF(S118="Semi-annual",2,IF(S118="Annual",1,IF(S118="Pays at maturity",0,IF(S118="Monthly",12,0))))) -> 1 | S118: Annual | U118: =R118*P118 -> 3 | V118: =(H118*M118)/AD118 -> 96 | W118: =RATE(U118,V118,-F118,H118) -> 0.1000213 | X118: =W118*AD118 -> 0.1000213 | Y118: =DURATION(N118,O118,M118,D118,AD118) -> 2.7435577 | Z118: =Y118/(1+C118) -> 2.4940951 | AA118: =-Z118*F118 -> -2469.1541 | AB118: None | AC118: India | AD118: =_xlfn.SWITCH(PROPER(TRIM(S118)), "Annual",1, "Semi-Annual",2, "Quarterly",4, "Monthly",12, "") -> 1
A119: 1315MFL25 | B119: MoneyBoxx Finance Ltd. | C119: =RATE(U119,V119,-F119,H119) -> 0.234228 | D119: =C119*AD119 -> 0.93691199 | F119: 30000 | G119: INR | H119: 100000 | J119: 1 | M119: 0.1315 | N119: 45254 | O119: 45984 | P119: =ROUND(YEARFRAC(N119,O119),0) -> 2 | Q119: =(M119*H119)/F119 -> 0.43833333 | R119: =IF(S119="Quarterly",4,IF(S119="Semi-annual",2,IF(S119="Annual",1,IF(S119="Pays at maturity",0,IF(S119="Monthly",12,0))))) -> 4 | S119: Quarterly | U119: =R119*P119 -> 8 | V119: =(H119*M119)/AD119 -> 3287.5 | W119: =RATE(U119,V119,-F119,H119) -> 0.234228 | X119: =W119*AD119 -> 0.93691199 | Y119: =DURATION(N119,O119,M119,D119,AD119) -> 1.5633825 | Z119: =Y119/(1+C119) -> 1.2666885 | AA119: =-Z119*F119 -> -38000.656 | AB119: None | AC119: India | AD119: =_xlfn.SWITCH(PROPER(TRIM(S119)), "Annual",1, "Semi-Annual",2, "Quarterly",4, "Monthly",12, "") -> 4
A120: 105MML25 | B120: Muthoot Mercantile Ltd. | C120: =RATE(U120,V120,-F120,H120) -> 0.11842105 | D120: =C120*AD120 -> 0.11842105 | F120: 988 | G120: INR | H120: 1000 | J120: 41 | L120: 11.597596 | M120: 0.105 | N120: 45439 | O120: 45987 | P120: =ROUND(YEARFRAC(N120,O120),0) -> 1 | Q120: =(M120*H120)/F120 -> 0.1062753 | R120: =IF(S120="Quarterly",4,IF(S120="Semi-annual",2,IF(S120="Annual",1,IF(S120="Pays at maturity",0,IF(S120="Monthly",12,0))))) -> 1 | S120: Annual | U120: =R120*P120 -> 1 | V120: =(H120*M120)/AD120 -> 105 | W120: =RATE(U120,V120,-F120,H120) -> 0.11842105 | X120: =W120*AD120 -> 0.11842105 | Y120: =DURATION(N120,O120,M120,D120,AD120) -> 1.4011563 | Z120: =Y120/(1+C120) -> 1.2527986 | AA120: =-Z120*F120 -> -1237.765 | AB120: None | AC120: India | AD120: =_xlfn.SWITCH(PROPER(TRIM(S120)), "Annual",1, "Semi-Annual",2, "Quarterly",4, "Monthly",12, "") -> 1
A121: 962APSB25A | B121: Andhra Pradesh State Beverages Corp. Ltd. | C121: =RATE(U121,V121,-F121,H121) -> 0.039450879 | D121: =C121*AD121 -> 0.15780352 | F121: 855000 | G121: INR | H121: 1000000 | J121: 3 | M121: 0.0962 | N121: 44916 | O121: 45989 | P121: =ROUND(YEARFRAC(N121,O121),0) -> 3 | Q121: =(M121*H121)/F121 -> 0.11251462 | R121: =IF(S121="Quarterly",4,IF(S121="Semi-annual",2,IF(S121="Annual",1,IF(S121="Pays at maturity",0,IF(S121="Monthly",12,0))))) -> 4 | S121: Quarterly | U121: =R121*P121 -> 12 | V121: =(H121*M121)/AD121 -> 24050 | W121: =RATE(U121,V121,-F121,H121) -> 0.039450879 | X121: =W121*AD121 -> 0.15780352 | Y121: =DURATION(N121,O121,M121,D121,AD121) -> 2.5415485 | Z121: =Y121/(1+C121) -> 2.4450876 | AA121: =-Z121*F121 -> -2090549.9 | AB121: None | AC121: India | AD121: =_xlfn.SWITCH(PROPER(TRIM(S121)), "Annual",1, "Semi-Annual",2, "Quarterly",4, "Monthly",12, "") -> 4
A123: 1160KFL25 | B123: Keertana Finserv Pvt Ltd. | C123: =RATE(U123,V123,-F123,H123) -> 0.082229102 | D123: =C123*AD123 -> 0.98674923 | F123: 24999.96 | G123: INR | H123: 100000 | J123: 7 | M123: 0.116 | N123: 45258 | O123: 45989 | P123: =ROUND(YEARFRAC(N123,O123),0) -> 2 | Q123: =(M123*H123)/F123 -> 0.46400074 | R123: =IF(S123="Quarterly",4,IF(S123="Semi-annual",2,IF(S123="Annual",1,IF(S123="Pays at maturity",0,IF(S123="Monthly",12,0))))) -> 12 | S123: Monthly | U123: =R123*P123 -> 24 | V123: =(H123*M123)/AD123 -> 966.66667 | W123: =RATE(U123,V123,-F123,H123) -> 0.082229102 | X123: =W123*AD123 -> 0.98674923 | Y123: =DURATION(N123,O123,M123,D123,AD123) -> #NUM! | Z123: =Y123/(1+C123) -> #NUM! | AA123: =-Z123*F123 -> #NUM! | AB123: None | AC123: India | AD123: =_xlfn.SWITCH(PROPER(TRIM(S123)), "Annual",1, "Semi-Annual",2, "Quarterly",4, "Monthly",12, "") -> 12
A127: 997MCSL25 | B127: Muthoot Capital Services Ltd. | C127: =RATE(U127,V127,-F127,H127) -> 0.034165939 | D127: =C127*AD127 -> 0.034165939 | F127: 106336.9 | G127: INR | H127: 100000 | J127: 1 | L127: -4.5672962 | M127: 0.0997 | N127: 45601 | O127: 45996 | P127: =ROUND(YEARFRAC(N127,O127),0) -> 1 | Q127: =(M127*H127)/F127 -> 0.093758611 | R127: =IF(S127="Quarterly",4,IF(S127="Semi-annual",2,IF(S127="Annual",1,IF(S127="Pays at maturity",0,IF(S127="Monthly",12,0))))) -> 1 | S127: Annual | U127: =R127*P127 -> 1 | V127: =(H127*M127)/AD127 -> 9970 | W127: =RATE(U127,V127,-F127,H127) -> 0.034165939 | X127: =W127*AD127 -> 0.034165939 | Y127: =DURATION(N127,O127,M127,D127,AD127) -> 0.99761185 | Z127: =Y127/(1+C127) -> 0.96465356 | AA127: =-Z127*F127 -> -102578.27 | AB127: None | AC127: India | AD127: =_xlfn.SWITCH(PROPER(TRIM(S127)), "Annual",1, "Semi-Annual",2, "Quarterly",4, "Monthly",12, "") -> 1
A128: 11ESPL25 | B128: EarlySalary Service Pvt Ltd. | C128: =RATE(U128,V128,-F128,H128) -> 0.11826489 | D128: =C128*AD128 -> 0.11826489 | F128: 98600 | G128: INR | H128: 100000 | J128: 1 | L128: 13.254387 | M128: 0.11 | N128: 45434 | O128: 45996 | P128: =ROUND(YEARFRAC(N128,O128),0) -> 2 | Q128: =(M128*H128)/F128 -> 0.11156187 | R128: =IF(S128="Quarterly",4,IF(S128="Semi-annual",2,IF(S128="Annual",1,IF(S128="Pays at maturity",0,IF(S128="Monthly",12,0))))) -> 1 | S128: Annual | U128: =R128*P128 -> 2 | V128: =(H128*M128)/AD128 -> 11000 | W128: =RATE(U128,V128,-F128,H128) -> 0.11826489 | X128: =W128*AD128 -> 0.11826489 | Y128: =DURATION(N128,O128,M128,D128,AD128) -> 1.4363477 | Z128: =Y128/(1+C128) -> 1.2844432 | AA128: =-Z128*F128 -> -126646.1 | AB128: None | AC128: India | AD128: =_xlfn.SWITCH(PROPER(TRIM(S128)), "Annual",1, "Semi-Annual",2, "Quarterly",4, "Monthly",12, "") -> 1
A129: 855MFSL25 | B129: MAS Financial Services Ltd. | C129: =RATE(U129,V129,-F129,H129) -> 0.089476457 | D129: =C129*AD129 -> 0.089476457 | F129: 99300 | G129: INR | H129: 100000 | J129: 1 | L129: 9.8967774 | M129: 0.0855 | N129: 45449 | O129: 45997 | P129: =ROUND(YEARFRAC(N129,O129),0) -> 2 | Q129: =(M129*H129)/F129 -> 0.086102719 | R129: =IF(S129="Quarterly",4,IF(S129="Semi-annual",2,IF(S129="Annual",1,IF(S129="Pays at maturity",0,IF(S129="Monthly",12,0))))) -> 1 | S129: Annual | U129: =R129*P129 -> 2 | V129: =(H129*M129)/AD129 -> 8550 | W129: =RATE(U129,V129,-F129,H129) -> 0.089476457 | X129: =W129*AD129 -> 0.089476457 | Y129: =DURATION(N129,O129,M129,D129,AD129) -> 1.4209687 | Z129: =Y129/(1+C129) -> 1.3042675 | AA129: =-Z129*F129 -> -129513.76 | AB129: None | AC129: India | AD129: =_xlfn.SWITCH(PROPER(TRIM(S129)), "Annual",1, "Semi-Annual",2, "Quarterly",4, "Monthly",12, "") -> 1
A132: 888IHFL25F | B132: Cholamandalam Investment & Finance Co. Ltd. | C132: =RATE(U132,V132,-F132,H132) -> 0.063580478 | D132: =C132*AD132 -> 0.063580478 | F132: 1037.25 | G132: INR | H132: 1000 | J132: 1 | L132: -1.0680811 | M132: 0.084 | N132: 45267 | O132: 45998 | P132: =ROUND(YEARFRAC(N132,O132),0) -> 2 | Q132: =(M132*H132)/F132 -> 0.080983369 | R132: =IF(S132="Quarterly",4,IF(S132="Semi-annual",2,IF(S132="Annual",1,IF(S132="Pays at maturity",0,IF(S132="Monthly",12,0))))) -> 1 | S132: Annual | U132: =R132*P132 -> 2 | V132: =(H132*M132)/AD132 -> 84 | W132: =RATE(U132,V132,-F132,H132) -> 0.063580478 | X132: =W132*AD132 -> 0.063580478 | Y132: =DURATION(N132,O132,M132,D132,AD132) -> 1.9238578 | Z132: =Y132/(1+C132) -> 1.8088502 | AA132: =-Z132*F132 -> -1876.2299 | AB132: None | AC132: India | AD132: =_xlfn.SWITCH(PROPER(TRIM(S132)), "Annual",1, "Semi-Annual",2, "Quarterly",4, "Monthly",12, "") -> 1
A133: 1050NBSP25 | B133: Nirmal Bang Securities Pvt Ltd. | C133: =RATE(U133,V133,-F133,H133) -> 0.105 | D133: =C133*AD133 -> 0.105 | F133: 100000 | G133: INR | H133: 100000 | J133: 3 | L133: 10.5 | M133: 0.105 | N133: 45453 | O133: 46001 | P133: =ROUND(YEARFRAC(N133,O133),0) -> 2 | Q133: =(M133*H133)/F133 -> 0.105 | R133: =IF(S133="Quarterly",4,IF(S133="Semi-annual",2,IF(S133="Annual",1,IF(S133="Pays at maturity",0,IF(S133="Monthly",12,0))))) -> 1 | S133: Annual | U133: =R133*P133 -> 2 | V133: =(H133*M133)/AD133 -> 10500 | W133: =RATE(U133,V133,-F133,H133) -> 0.105 | X133: =W133*AD133 -> 0.105 | Y133: =DURATION(N133,O133,M133,D133,AD133) -> 1.4049774 | Z133: =Y133/(1+C133) -> 1.2714727 | AA133: =-Z133*F133 -> -127147.27 | AB133: Callable | AC133: India | AD133: =_xlfn.SWITCH(PROPER(TRIM(S133)), "Annual",1, "Semi-Annual",2, "Quarterly",4, "Monthly",12, "") -> 1
A134: 1175ICLF25 | B134: ICL Fincorp Ltd. | C134: =RATE(U134,V134,-F134,H134) -> 0.072019485 | D134: =C134*AD134 -> 0.072019485 | F134: 1082 | G134: INR | H134: 1000 | J134: 1 | L134: 3.9613305 | M134: 0.1175 | N134: 45274 | O134: 46003 | P134: =ROUND(YEARFRAC(N134,O134),0) -> 2 | Q134: =(M134*H134)/F134 -> 0.10859519 | R134: =IF(S134="Quarterly",4,IF(S134="Semi-annual",2,IF(S134="Annual",1,IF(S134="Pays at maturity",0,IF(S134="Monthly",12,0))))) -> 1 | S134: Annual | U134: =R134*P134 -> 2 | V134: =(H134*M134)/AD134 -> 117.5 | W134: =RATE(U134,V134,-F134,H134) -> 0.072019485 | X134: =W134*AD134 -> 0.072019485 | Y134: =DURATION(N134,O134,M134,D134,AD134) -> 1.8931448 | Z134: =Y134/(1+C134) -> 1.7659612 | AA134: =-Z134*F134 -> -1910.77 | AB134: None | AC134: India | AD134: =_xlfn.SWITCH(PROPER(TRIM(S134)), "Annual",1, "Semi-Annual",2, "Quarterly",4, "Monthly",12, "") -> 1
A135: 115ICLFL25 | B135: ICL Fincorp Ltd. | C135: =RATE(U135,V135,-F135,H135) -> 0.12130648 | D135: =C135*AD135 -> 0.12130648 | F135: 989.36 | G135: INR | H135: 1000 | J135: 19 | L135: 13.352912 | M135: 0.115 | N135: 45274 | O135: 46003 | P135: =ROUND(YEARFRAC(N135,O135),0) -> 2 | Q135: =(M135*H135)/F135 -> 0.11623676 | R135: =IF(S135="Quarterly",4,IF(S135="Semi-annual",2,IF(S135="Annual",1,IF(S135="Pays at maturity",0,IF(S135="Monthly",12,0))))) -> 1 | S135: Annual | U135: =R135*P135 -> 2 | V135: =(H135*M135)/AD135 -> 115 | W135: =RATE(U135,V135,-F135,H135) -> 0.12130648 | X135: =W135*AD135 -> 0.12130648 | Y135: =DURATION(N135,O135,M135,D135,AD135) -> 1.8907825 | Z135: =Y135/(1+C135) -> 1.6862317 | AA135: =-Z135*F135 -> -1668.2902 | AB135: None | AC135: India | AD135: =_xlfn.SWITCH(PROPER(TRIM(S135)), "Annual",1, "Semi-Annual",2, "Quarterly",4, "Monthly",12, "") -> 1
A136: 125KSPL25A | B136: KrazyBee Services Pvt. Ltd. | C136: =RATE(U136,V136,-F136,H136) -> 0.06664574 | D136: =C136*AD136 -> 0.79974888 | F136: 33565 | G136: INR | H136: 100000 | J136: 1 | M136: 0.125 | N136: 45455 | O136: 46003 | P136: =ROUND(YEARFRAC(N136,O136),0) -> 2 | Q136: =(M136*H136)/F136 -> 0.37241174 | R136: =IF(S136="Quarterly",4,IF(S136="Semi-annual",2,IF(S136="Annual",1,IF(S136="Pays at maturity",0,IF(S136="Monthly",12,0))))) -> 12 | S136: Monthly | U136: =R136*P136 -> 24 | V136: =(H136*M136)/AD136 -> 1041.6667 | W136: =RATE(U136,V136,-F136,H136) -> 0.06664574 | X136: =W136*AD136 -> 0.79974888 | Y136: =DURATION(N136,O136,M136,D136,AD136) -> #NUM! | Z136: =Y136/(1+C136) -> #NUM! | AA136: =-Z136*F136 -> #NUM! | AB136: None | AC136: India | AD136: =_xlfn.SWITCH(PROPER(TRIM(S136)), "Annual",1, "Semi-Annual",2, "Quarterly",4, "Monthly",12, "") -> 12
A137: 916ONE25 | B137: 360 ONE Prime Ltd. | C137: =RATE(U137,V137,-F137,H137) -> 0.0916 | D137: =C137*AD137 -> 0.0916 | F137: 1000 | G137: INR | H137: 1000 | J137: 20 | L137: 9.16 | M137: 0.0916 | N137: 45455 | O137: 46003 | P137: =ROUND(YEARFRAC(N137,O137),0) -> 2 | Q137: =(M137*H137)/F137 -> 0.0916 | R137: =IF(S137="Quarterly",4,IF(S137="Semi-annual",2,IF(S137="Annual",1,IF(S137="Pays at maturity",0,IF(S137="Monthly",12,0))))) -> 1 | S137: Annual | U137: =R137*P137 -> 2 | V137: =(H137*M137)/AD137 -> 91.6 | W137: =RATE(U137,V137,-F137,H137) -> 0.0916 | X137: =W137*AD137 -> 0.0916 | Y137: =DURATION(N137,O137,M137,D137,AD137) -> 1.4160865 | Z137: =Y137/(1+C137) -> 1.2972577 | AA137: =-Z137*F137 -> -1297.2577 | AB137: None | AC137: India | AD137: =_xlfn.SWITCH(PROPER(TRIM(S137)), "Annual",1, "Semi-Annual",2, "Quarterly",4, "Monthly",12, "") -> 1
A139: 886ONE25 | B139: 360 ONE Prime Ltd. | C139: =RATE(U139,V139,-F139,H139) -> 0.094318004 | D139: =C139*AD139 -> 0.094318004 | F139: 990 | G139: INR | H139: 1000 | J139: 20 | L139: 11.032472 | M139: 0.0886 | N139: 45455 | O139: 46003 | P139: =ROUND(YEARFRAC(N139,O139),0) -> 2 | Q139: =(M139*H139)/F139 -> 0.089494949 | R139: =IF(S139="Quarterly",4,IF(S139="Semi-annual",2,IF(S139="Annual",1,IF(S139="Pays at maturity",0,IF(S139="Monthly",12,0))))) -> 1 | S139: Annual | U139: =R139*P139 -> 2 | V139: =(H139*M139)/AD139 -> 88.6 | W139: =RATE(U139,V139,-F139,H139) -> 0.094318004 | X139: =W139*AD139 -> 0.094318004 | Y139: =DURATION(N139,O139,M139,D139,AD139) -> 1.4182185 | Z139: =Y139/(1+C139) -> 1.2959839 | AA139: =-Z139*F139 -> -1283.0241 | AB139: None | AC139: India | AD139: =_xlfn.SWITCH(PROPER(TRIM(S139)), "Annual",1, "Semi-Annual",2, "Quarterly",4, "Monthly",12, "") -> 1
A140: 1011SSFL25 | B140: Spandana Sphoorty Financial Ltd. | C140: =RATE(U140,V140,-F140,H140) -> 0.025416112 | D140: =C140*AD140 -> 0.10166445 | F140: 99899 | G140: INR | H140: 100000 | J140: 1 | M140: 0.1011 | N140: 45278 | O140: 46009 | P140: =ROUND(YEARFRAC(N140,O140),0) -> 2 | Q140: =(M140*H140)/F140 -> 0.10120221 | R140: =IF(S140="Quarterly",4,IF(S140="Semi-annual",2,IF(S140="Annual",1,IF(S140="Pays at maturity",0,IF(S140="Monthly",12,0))))) -> 4 | S140: Quarterly | U140: =R140*P140 -> 8 | V140: =(H140*M140)/AD140 -> 2527.5 | W140: =RATE(U140,V140,-F140,H140) -> 0.025416112 | X140: =W140*AD140 -> 0.10166445 | Y140: =DURATION(N140,O140,M140,D140,AD140) -> 1.8355876 | Z140: =Y140/(1+C140) -> 1.7900905 | AA140: =-Z140*F140 -> -178828.25 | AB140: None | AC140: India | AD140: =_xlfn.SWITCH(PROPER(TRIM(S140)), "Annual",1, "Semi-Annual",2, "Quarterly",4, "Monthly",12, "") -> 4
A141: 1020KSPL25 | B141: Finnovation Tech Solutions Pvt Ltd. | C141: =RATE(U141,V141,-F141,H141) -> 0.0534558 | D141: =C141*AD141 -> 0.6414696 | F141: 40000 | G141: INR | H141: 100000 | J141: 1 | M141: 0.102 | N141: 45462 | O141: 46010 | P141: =ROUND(YEARFRAC(N141,O141),0) -> 2 | Q141: =(M141*H141)/F141 -> 0.255 | R141: =IF(S141="Quarterly",4,IF(S141="Semi-annual",2,IF(S141="Annual",1,IF(S141="Pays at maturity",0,IF(S141="Monthly",12,0))))) -> 12 | S141: Monthly | U141: =R141*P141 -> 24 | V141: =(H141*M141)/AD141 -> 850 | W141: =RATE(U141,V141,-F141,H141) -> 0.0534558 | X141: =W141*AD141 -> 0.6414696 | Y141: =DURATION(N141,O141,M141,D141,AD141) -> #NUM! | Z141: =Y141/(1+C141) -> #NUM! | AA141: =-Z141*F141 -> #NUM! | AB141: None | AC141: India | AD141: =_xlfn.SWITCH(PROPER(TRIM(S141)), "Annual",1, "Semi-Annual",2, "Quarterly",4, "Monthly",12, "") -> 12
A142: 11KFL25 | B142: Kanakadurga Finance Ltd. | C142: =RATE(U142,V142,-F142,H142) -> 0.1165435 | D142: =C142*AD142 -> 0.1165435 | F142: 99413.95 | G142: INR | H142: 100000 | J142: 1 | L142: 12.140692 | M142: 0.11 | N142: 45524 | O142: 46011 | P142: =ROUND(YEARFRAC(N142,O142),0) -> 1 | Q142: =(M142*H142)/F142 -> 0.11064846 | R142: =IF(S142="Quarterly",4,IF(S142="Semi-annual",2,IF(S142="Annual",1,IF(S142="Pays at maturity",0,IF(S142="Monthly",12,0))))) -> 1 | S142: Annual | U142: =R142*P142 -> 1 | V142: =(H142*M142)/AD142 -> 11000 | W142: =RATE(U142,V142,-F142,H142) -> 0.1165435 | X142: =W142*AD142 -> 0.1165435 | Y142: =DURATION(N142,O142,M142,D142,AD142) -> 1.2337082 | Z142: =Y142/(1+C142) -> 1.1049352 | AA142: =-Z142*F142 -> -109845.97 | AB142: None | AC142: India | AD142: =_xlfn.SWITCH(PROPER(TRIM(S142)), "Annual",1, "Semi-Annual",2, "Quarterly",4, "Monthly",12, "") -> 1
A143: 12CVL25 | B143: Crest Ventures Ltd. | C143: =RATE(U143,V143,-F143,H143) -> 0.03 | D143: =C143*AD143 -> 0.12 | F143: 100000 | G143: INR | H143: 100000 | J143: 150 | M143: 0.12 | N143: 45463 | O143: 46011 | P143: =ROUND(YEARFRAC(N143,O143),0) -> 2 | Q143: =(M143*H143)/F143 -> 0.12 | R143: =IF(S143="Quarterly",4,IF(S143="Semi-annual",2,IF(S143="Annual",1,IF(S143="Pays at maturity",0,IF(S143="Monthly",12,0))))) -> 4 | S143: Quarterly | U143: =R143*P143 -> 8 | V143: =(H143*M143)/AD143 -> 3000 | W143: =RATE(U143,V143,-F143,H143) -> 0.03 | X143: =W143*AD143 -> 0.12 | Y143: =DURATION(N143,O143,M143,D143,AD143) -> 1.3949268 | Z143: =Y143/(1+C143) -> 1.3542979 | AA143: =-Z143*F143 -> -135429.79 | AB143: None | AC143: India | AD143: =_xlfn.SWITCH(PROPER(TRIM(S143)), "Annual",1, "Semi-Annual",2, "Quarterly",4, "Monthly",12, "") -> 4
A145: 707IRFC25 | B145: Indian Railway Finance Corp. Ltd. | C145: =RATE(U145,V145,-F145,H145) -> 0.063777584 | D145: =C145*AD145 -> 0.063777584 | F145: 1050.05 | G145: INR | H145: 1000 | J145: 614 | L145: -2.0536059 | M145: 0.0707 | N145: 42359 | O145: 46012 | P145: =ROUND(YEARFRAC(N145,O145),0) -> 10 | Q145: =(M145*H145)/F145 -> 0.067330127 | R145: =IF(S145="Quarterly",4,IF(S145="Semi-annual",2,IF(S145="Annual",1,IF(S145="Pays at maturity",0,IF(S145="Monthly",12,0))))) -> 1 | S145: Annual | U145: =R145*P145 -> 10 | V145: =(H145*M145)/AD145 -> 70.7 | W145: =RATE(U145,V145,-F145,H145) -> 0.063777584 | X145: =W145*AD145 -> 0.063777584 | Y145: =DURATION(N145,O145,M145,D145,AD145) -> 7.5626531 | Z145: =Y145/(1+C145) -> 7.1092428 | AA145: =-Z145*F145 -> -7465.0604 | AB145: None | AC145: India | AD145: =_xlfn.SWITCH(PROPER(TRIM(S145)), "Annual",1, "Semi-Annual",2, "Quarterly",4, "Monthly",12, "") -> 1
...

Sheet Steps in Analyzing a Bond
A1: Steps | B1: Description | C1: Sheets
A2: Step 1 | B2: IRR (Frequency based) | C2: Bond pricing from Base data
A3: Step 2 | B3: IRR (Annualised) | C3: Bond pricing from Base data, Base Data
A4: Step 3 | B4: Formation of Yield Cluster | C4: Base data
A5: Step 4 | B5: Average of yield cluster | C5: Cluster details, Base data
A6: Step 5 | B6: Effective Yield from cluster | C6: Bond pricing from Base data
A7: Step 6 | B7: Macaulay duration | C7: Bond pricing from Base data, DurationTemplate, Base Data
A8: Step 7 | B8: Modified duration | C8: Bond pricing from Base data, Duration Template, Base Data
A9: Step 8 | B9: Convexity Measure (in coupon frequency terms) | C9: Convexity Template
A10: Step 9 | B10: Convexity Measure (Years) | C10: Convexity Template
A11: Step 10 | B11: % Price change due to Duration and Convexity | C11: Convexity Template
A12: Step 11 | B12: Rich/Cheap Analysis | C12: Bond pricing from Base data

Sheet Base Data
A1: INPUTS | S1: CALCULATED FIELDS
A2: By MJK | X2: Step 2 | Y2: Step 3 | Z2: Step 6 | AA2: Step 7 | AB2: Step 4 | AD2: bps shock input --> | AE2: 100 | AF2: =AE2/10000 -> 0.01
A3: Symbol | B3: Issuer Name | C3: BOND TYPE | D3: Issue date | E3: Maturity date | F3: Face value | G3: Face value - Currency | H3: Ask Price | I3: Price - Currency | J3: Price % of face value | K3: Volume 1 day | L3: Current coupon % | M3: Coupon frequency | N3: Term to maturity | O3: Current yield % (Coupon/Current Ask Price) | P3: S&P rating | Q3: Yield to maturity % | R3: Exchange | S3: Term to Maturity (Years) | T3: Coupon Frequency2 | U3: Total No. of Coupons | V3: Coupon Amount | W3: IRR | X3: Yield (Annualised) | Y3: Yield Cluster | Z3: Macaulay Duration in Years | AA3: Modified Duration in Years | AB3: Average Cluster Yield | AC3: Calculated Bond Price | AD3: Rich/Cheap | AE3: P (+ shock) | AF3: P (-shock) | AG3: Convexity Estimation | AH3: Column4 | AI3: Coupon Yield | AJ3: Column5 | AK3: IRR2 | AL3: Yield (Annual) | AM3: Dollar Duration | AN3: Bond Type2 | AO3: Country | AP3: Yearly Payment Frequency
A4: 737NTPC35C | B4: NTPC Limited 7.37% 05-OCT-2035 | C4: Corporate | D4: 42282 | E4: 49587 | F4: 1000 | G4: INR | H4: 2088.8 | I4: INR | J4: 208.88 | K4: 20 | L4: 0.0737 | M4: Annual | N4: 3670 | O4: 3.5283416 | P4: BBB | R4: BSE | S4: =ROUND(YEARFRAC(D4,E4),0) -> 20 | T4: {=_xlfn.IFS(Table1[[#This Row],[Coupon frequency]]="Semi-annual",2,Table1[[#This Row],[Coupon frequency]]="Quarterly",4,Table1[[#This Row],[Coupon frequency]]="Annual",1,Table1[[#This Row],[Coupon frequency]]="Every 4 months",3,Table1[[#This Row],[Coupon frequency]]="Monthly",12)} -> 1 | U4: =Table1[[#This Row],[Term to Maturity (Years)]]*Table1[[#This Row],[Coupon Frequency2]] -> 20 | V4: =Table1[[#This Row],[Face value]]*Table1[[#This Row],[Current coupon %]] -> 73.7 | W4: =RATE(Table1[[#This Row],[Total No. of Coupons]],Table1[[#This Row],[Coupon Amount]],-Table1[[#This Row],[Ask Price]],Table1[[#This Row],[Face value]]) -> 0.012087753 | X4: =Table1[[#This Row],[IRR]]*Table1[[#This Row],[Coupon Frequency2]] -> 0.012087753 | Y4: {=_xlfn.IFS(Table1[[#This Row],[Yield (Annualised)]]<0.05,1,Table1[[#This Row],[Yield (Annualised)]]<0.1,2,Table1[[#This Row],[Yield (Annualised)]]<0.15,3,Table1[[#This Row],[Yield (Annualised)]]<0.2,4,Table1[[#This Row],[Yield (Annualised)]]<0.25,5,Table1[[#This Row],[Yield (Annualised)]]<0.3,6,Table1[[#This Row],[Yield (Annualised)]]<0.35,7,Table1[[#This Row],[Yield (Annualised)]]<0.4,8,Table1[[#This Row],[Yield (Annualised)]]<0.45,9,Table1[[#This Row],[Yield (Annualised)]]<0.5,10,Table1[[#This Row],[Yield (Annualised)]]<0.55,11,Table1[[#This Row],[Yield (Annualised)]]<0.6,12,Table1[[#This Row],[Yield (Annualised)]]<0.65,13,Table1[[#This Row],[Yield (Annualised)]]<0.7,14,Table1[[#This Row],[Yield (Annualised)]]>0.7,15)} -> 1 | Z4: =DURATION(Table1[[#This Row],[Issue date]],Table1[[#This Row],[Maturity date]],Table1[[#This Row],[Current coupon %]],Table1[[#This Row],[Yield (Annualised)]],Table1[[#This Row],[Coupon Frequency2]]) -> 13.82768 | AA4: =Table1[[#This Row],[Macaulay Duration in Years]]/(1+Table1[[#This Row],[IRR]]) -> 13.662531 | AB4: =VLOOKUP(Table1[[#This Row],[Yield Cluster]],'Cluster Details'!$B$3:$C$16,2,0) -> 0.034641747 | AC4: =PRICE(Table1[[#This Row],[Issue date]],Table1[[#This Row],[Maturity date]],Table1[[#This Row],[Current coupon %]],Table1[[#This Row],[Average Cluster Yield]],100,Table1[[#This Row],[Coupon Frequency2]])*Table1[[#This Row],[Face value]]/100 -> 1556.9154 | AD4: =IF(Table1[[#This Row],[Ask Price]]>Table1[[#This Row],[Calculated Bond Price]],"Rich","Cheap") -> Rich | AE4: =PRICE(Table1[[#This Row],[Issue date]],Table1[[#This Row],[Maturity date]],Table1[[#This Row],[Current coupon %]],Table1[[#This Row],[Yield (Annualised)]]+$AF$2,100,Table1[[#This Row],[Coupon Frequency2]])*Table1[[#This Row],[Face value]]/100 -> 1827.1753 | AF4: =PRICE(Table1[[#This Row],[Issue date]],Table1[[#This Row],[Maturity date]],Table1[[#This Row],[Current coupon %]],Table1[[#This Row],[Yield (Annualised)]]-$AF$2,100,Table1[[#This Row],[Coupon Frequency2]])*Table1[[#This Row],[Face value]]/100 -> 2401.3231 | AG4: =(Table1[[#This Row],[P (+ shock)]]+Table1[[#This Row],[P (-shock)]]-2*Table1[[#This Row],[Ask Price]])/(2*Table1[[#This Row],[Ask Price]]*($AF$2^2)) -> 121.83653 | AH4: 11.444721 | AI4: =(L4*F4)/H4 -> 0.035283416 | AK4: =RATE(Table1[[#This Row],[Total No. of Coupons]],Table1[[#This Row],[Coupon Amount]],-Table1[[#This Row],[Ask Price]],Table1[[#This Row],[Face value]]) -> 0.012087753 | AL4: =Table1[[#This Row],[IRR]]*Table1[[#This Row],[Coupon Frequency2]] -> 0.012087753 | AM4: =-AA4*H4 -> -28538.295 | AN4: None | AO4: India | AP4: =_xlfn.SWITCH(PROPER(TRIM(M4)), "Annual",1, "Semi-Annual",2, "Quarterly",4, "Monthly",12, "") -> 1
A5: 997MCSL25 | B5: Muthoot Capital Services Limited 9.97% 05-DEC-2025 | C5: Corporate | D5: 45601 | E5: 45996 | F5: 100000 | G5: INR | H5: 107624.42 | I5: INR | J5: 107.62442 | K5: 2 | L5: 0.0997 | M5: Annual | N5: 79 | O5: 9.2636968 | R5: BSE | S5: =ROUND(YEARFRAC(D5,E5),0) -> 1 | T5: {=_xlfn.IFS(Table1[[#This Row],[Coupon frequency]]="Semi-annual",2,Table1[[#This Row],[Coupon frequency]]="Quarterly",4,Table1[[#This Row],[Coupon frequency]]="Annual",1,Table1[[#This Row],[Coupon frequency]]="Every 4 months",3,Table1[[#This Row],[Coupon frequency]]="Monthly",12)} -> 1 | U5: =Table1[[#This Row],[Term to Maturity (Years)]]*Table1[[#This Row],[Coupon Frequency2]] -> 1 | V5: =Table1[[#This Row],[Face value]]*Table1[[#This Row],[Current coupon %]] -> 9970 | W5: =RATE(Table1[[#This Row],[Total No. of Coupons]],Table1[[#This Row],[Coupon Amount]],-Table1[[#This Row],[Ask Price]],Table1[[#This Row],[Face value]]) -> 0.021794124 | X5: =Table1[[#This Row],[IRR]]*Table1[[#This Row],[Coupon Frequency2]] -> 0.021794124 | Y5: {=_xlfn.IFS(Table1[[#This Row],[Yield (Annualised)]]<0.05,1,Table1[[#This Row],[Yield (Annualised)]]<0.1,2,Table1[[#This Row],[Yield (Annualised)]]<0.15,3,Table1[[#This Row],[Yield (Annualised)]]<0.2,4,Table1[[#This Row],[Yield (Annualised)]]<0.25,5,Table1[[#This Row],[Yield (Annualised)]]<0.3,6,Table1[[#This Row],[Yield (Annualised)]]<0.35,7,Table1[[#This Row],[Yield (Annualised)]]<0.4,8,Table1[[#This Row],[Yield (Annualised)]]<0.45,9,Table1[[#This Row],[Yield (Annualised)]]<0.5,10,Table1[[#This Row],[Yield (Annualised)]]<0.55,11,Table1[[#This Row],[Yield (Annualised)]]<0.6,12,Table1[[#This Row],[Yield (Annualised)]]<0.65,13,Table1[[#This Row],[Yield (Annualised)]]<0.7,14,Table1[[#This Row],[Yield (Annualised)]]>0.7,15)} -> 1 | Z5: =DURATION(Table1[[#This Row],[Issue date]],Table1[[#This Row],[Maturity date]],Table1[[#This Row],[Current coupon %]],Table1[[#This Row],[Yield (Annualised)]],Table1[[#This Row],[Coupon Frequency2]]) -> 0.9985504 | AA5: =Table1[[#This Row],[Macaulay Duration in Years]]/(1+Table1[[#This Row],[IRR]]) -> 0.97725205 | AB5: =VLOOKUP(Table1[[#This Row],[Yield Cluster]],'Cluster Details'!$B$3:$C$16,2,0) -> 0.034641747 | AC5: =PRICE(Table1[[#This Row],[Issue date]],Table1[[#This Row],[Maturity date]],Table1[[#This Row],[Current coupon %]],Table1[[#This Row],[Average Cluster Yield]],100,Table1[[#This Row],[Coupon Frequency2]])*Table1[[#This Row],[Face value]]/100 -> 106789.37 | AD5: =IF(Table1[[#This Row],[Ask Price]]>Table1[[#This Row],[Calculated Bond Price]],"Rich","Cheap") -> Rich | AE5: =PRICE(Table1[[#This Row],[Issue date]],Table1[[#This Row],[Maturity date]],Table1[[#This Row],[Current coupon %]],Table1[[#This Row],[Yield (Annualised)]]+$AF$2,100,Table1[[#This Row],[Coupon Frequency2]])*Table1[[#This Row],[Face value]]/100 -> 107108.57 | AF5: =PRICE(Table1[[#This Row],[Issue date]],Table1[[#This Row],[Maturity date]],Table1[[#This Row],[Current coupon %]],Table1[[#This Row],[Yield (Annualised)]]-$AF$2,100,Table1[[#This Row],[Coupon Frequency2]])*Table1[[#This Row],[Face value]]/100 -> 109403.07 | AG5: =(Table1[[#This Row],[P (+ shock)]]+Table1[[#This Row],[P (-shock)]]-2*Table1[[#This Row],[Ask Price]])/(2*Table1[[#This Row],[Ask Price]]*($AF$2^2)) -> 58.667042 | AH5: 9.5 | AI5: =(L5*F5)/H5 -> 0.092636968 | AK5: =RATE(Table1[[#This Row],[Total No. of Coupons]],Table1[[#This Row],[Coupon Amount]],-Table1[[#This Row],[Ask Price]],Table1[[#This Row],[Face value]]) -> 0.021794124 | AL5: =Table1[[#This Row],[IRR]]*Table1[[#This Row],[Coupon Frequency2]] -> 0.021794124 | AM5: =-AA5*H5 -> -105176.18 | AN5: None | AO5: India | AP5: =_xlfn.SWITCH(PROPER(TRIM(M5)), "Annual",1, "Semi-Annual",2, "Quarterly",4, "Monthly",12, "") -> 1
A6: 925IHFL25E | B6: Cholamandalam Investment and finance Company Limited 8.3% 09-SEP-2026 | C6: Corporate | D6: 45147 | E6: 46274 | F6: 1000 | G6: INR | H6: 1168.8 | I6: INR | J6: 116.88 | K6: 120 | L6: 0.083 | M6: Annual | N6: 357 | O6: 7.1013005 | R6: BSE | S6: =ROUND(YEARFRAC(D6,E6),0) -> 3 | T6: {=_xlfn.IFS(Table1[[#This Row],[Coupon frequency]]="Semi-annual",2,Table1[[#This Row],[Coupon frequency]]="Quarterly",4,Table1[[#This Row],[Coupon frequency]]="Annual",1,Table1[[#This Row],[Coupon frequency]]="Every 4 months",3,Table1[[#This Row],[Coupon frequency]]="Monthly",12)} -> 1 | U6: =Table1[[#This Row],[Term to Maturity (Years)]]*Table1[[#This Row],[Coupon Frequency2]] -> 3 | V6: =Table1[[#This Row],[Face value]]*Table1[[#This Row],[Current coupon %]] -> 83 | W6: =RATE(Table1[[#This Row],[Total No. of Coupons]],Table1[[#This Row],[Coupon Amount]],-Table1[[#This Row],[Ask Price]],Table1[[#This Row],[Face value]]) -> 0.024010037 | X6: =Table1[[#This Row],[IRR]]*Table1[[#This Row],[Coupon Frequency2]] -> 0.024010037 | Y6: {=_xlfn.IFS(Table1[[#This Row],[Yield (Annualised)]]<0.05,1,Table1[[#This Row],[Yield (Annualised)]]<0.1,2,Table1[[#This Row],[Yield (Annualised)]]<0.15,3,Table1[[#This Row],[Yield (Annualised)]]<0.2,4,Table1[[#This Row],[Yield (Annualised)]]<0.25,5,Table1[[#This Row],[Yield (Annualised)]]<0.3,6,Table1[[#This Row],[Yield (Annualised)]]<0.35,7,Table1[[#This Row],[Yield (Annualised)]]<0.4,8,Table1[[#This Row],[Yield (Annualised)]]<0.45,9,Table1[[#This Row],[Yield (Annualised)]]<0.5,10,Table1[[#This Row],[Yield (Annualised)]]<0.55,11,Table1[[#This Row],[Yield (Annualised)]]<0.6,12,Table1[[#This Row],[Yield (Annualised)]]<0.65,13,Table1[[#This Row],[Yield (Annualised)]]<0.7,14,Table1[[#This Row],[Yield (Annualised)]]>0.7,15)} -> 1 | Z6: =DURATION(Table1[[#This Row],[Issue date]],Table1[[#This Row],[Maturity date]],Table1[[#This Row],[Current coupon %]],Table1[[#This Row],[Yield (Annualised)]],Table1[[#This Row],[Coupon Frequency2]]) -> 2.6916883 | AA6: =Table1[[#This Row],[Macaulay Duration in Years]]/(1+Table1[[#This Row],[IRR]]) -> 2.6285761 | AB6: =VLOOKUP(Table1[[#This Row],[Yield Cluster]],'Cluster Details'!$B$3:$C$16,2,0) -> 0.034641747 | AC6: =PRICE(Table1[[#This Row],[Issue date]],Table1[[#This Row],[Maturity date]],Table1[[#This Row],[Current coupon %]],Table1[[#This Row],[Average Cluster Yield]],100,Table1[[#This Row],[Coupon Frequency2]])*Table1[[#This Row],[Face value]]/100 -> 1139.0384 | AD6: =IF(Table1[[#This Row],[Ask Price]]>Table1[[#This Row],[Calculated Bond Price]],"Rich","Cheap") -> Rich | AE6: =PRICE(Table1[[#This Row],[Issue date]],Table1[[#This Row],[Maturity date]],Table1[[#This Row],[Current coupon %]],Table1[[#This Row],[Yield (Annualised)]]+$AF$2,100,Table1[[#This Row],[Coupon Frequency2]])*Table1[[#This Row],[Face value]]/100 -> 1141.0318 | AF6: =PRICE(Table1[[#This Row],[Issue date]],Table1[[#This Row],[Maturity date]],Table1[[#This Row],[Current coupon %]],Table1[[#This Row],[Yield (Annualised)]]-$AF$2,100,Table1[[#This Row],[Coupon Frequency2]])*Table1[[#This Row],[Face value]]/100 -> 1206.7317 | AG6: =(Table1[[#This Row],[P (+ shock)]]+Table1[[#This Row],[P (-shock)]]-2*Table1[[#This Row],[Ask Price]])/(2*Table1[[#This Row],[Ask Price]]*($AF$2^2)) -> 43.478563 | AI6: =(L6*F6)/H6 -> 0.071013005 | AK6: =RATE(Table1[[#This Row],[Total No. of Coupons]],Table1[[#This Row],[Coupon Amount]],-Table1[[#This Row],[Ask Price]],Table1[[#This Row],[Face value]]) -> 0.024010037 | AL6: =Table1[[#This Row],[IRR]]*Table1[[#This Row],[Coupon Frequency2]] -> 0.024010037 | AM6: =-AA6*H6 -> -3072.2798 | AN6: None | AO6: India | AP6: =_xlfn.SWITCH(PROPER(TRIM(M6)), "Annual",1, "Semi-Annual",2, "Quarterly",4, "Monthly",12, "") -> 1
A7: 99SCL27V | B7: Sammaan Capital Limited 9.9% 27-DEC-2027 | C7: Corporate | D7: 45653 | E7: 46748 | F7: 1000 | G7: INR | H7: 1199 | I7: INR | J7: 119.9 | K7: 401 | L7: 0.099 | M7: Annual | N7: 831 | O7: 8.2568807 | P7: B+ | R7: BSE | S7: =ROUND(YEARFRAC(D7,E7),0) -> 3 | T7: {=_xlfn.IFS(Table1[[#This Row],[Coupon frequency]]="Semi-annual",2,Table1[[#This Row],[Coupon frequency]]="Quarterly",4,Table1[[#This Row],[Coupon frequency]]="Annual",1,Table1[[#This Row],[Coupon frequency]]="Every 4 months",3,Table1[[#This Row],[Coupon frequency]]="Monthly",12)} -> 1 | U7: =Table1[[#This Row],[Term to Maturity (Years)]]*Table1[[#This Row],[Coupon Frequency2]] -> 3 | V7: =Table1[[#This Row],[Face value]]*Table1[[#This Row],[Current coupon %]] -> 99 | W7: =RATE(Table1[[#This Row],[Total No. of Coupons]],Table1[[#This Row],[Coupon Amount]],-Table1[[#This Row],[Ask Price]],Table1[[#This Row],[Face value]]) -> 0.028808554 | X7: =Table1[[#This Row],[IRR]]*Table1[[#This Row],[Coupon Frequency2]] -> 0.028808554 | Y7: {=_xlfn.IFS(Table1[[#This Row],[Yield (Annualised)]]<0.05,1,Table1[[#This Row],[Yield (Annualised)]]<0.1,2,Table1[[#This Row],[Yield (Annualised)]]<0.15,3,Table1[[#This Row],[Yield (Annualised)]]<0.2,4,Table1[[#This Row],[Yield (Annualised)]]<0.25,5,Table1[[#This Row],[Yield (Annualised)]]<0.3,6,Table1[[#This Row],[Yield (Annualised)]]<0.35,7,Table1[[#This Row],[Yield (Annualised)]]<0.4,8,Table1[[#This Row],[Yield (Annualised)]]<0.45,9,Table1[[#This Row],[Yield (Annualised)]]<0.5,10,Table1[[#This Row],[Yield (Annualised)]]<0.55,11,Table1[[#This Row],[Yield (Annualised)]]<0.6,12,Table1[[#This Row],[Yield (Annualised)]]<0.65,13,Table1[[#This Row],[Yield (Annualised)]]<0.7,14,Table1[[#This Row],[Yield (Annualised)]]>0.7,15)} -> 1 | Z7: =DURATION(Table1[[#This Row],[Issue date]],Table1[[#This Row],[Maturity date]],Table1[[#This Row],[Current coupon %]],Table1[[#This Row],[Yield (Annualised)]],Table1[[#This Row],[Coupon Frequency2]]) -> 2.7614772 | AA7: =Table1[[#This Row],[Macaulay Duration in Years]]/(1+Table1[[#This Row],[IRR]]) -> 2.6841507 | AB7: =VLOOKUP(Table1[[#This Row],[Yield Cluster]],'Cluster Details'!$B$3:$C$16,2,0) -> 0.034641747 | AC7: =PRICE(Table1[[#This Row],[Issue date]],Table1[[#This Row],[Maturity date]],Table1[[#This Row],[Current coupon %]],Table1[[#This Row],[Average Cluster Yield]],100,Table1[[#This Row],[Coupon Frequency2]])*Table1[[#This Row],[Face value]]/100 -> 1180.4319 | AD7: =IF(Table1[[#This Row],[Ask Price]]>Table1[[#This Row],[Calculated Bond Price]],"Rich","Cheap") -> Rich | AE7: =PRICE(Table1[[#This Row],[Issue date]],Table1[[#This Row],[Maturity date]],Table1[[#This Row],[Current coupon %]],Table1[[#This Row],[Yield (Annualised)]]+$AF$2,100,Table1[[#This Row],[Coupon Frequency2]])*Table1[[#This Row],[Face value]]/100 -> 1167.4152 | AF7: =PRICE(Table1[[#This Row],[Issue date]],Table1[[#This Row],[Maturity date]],Table1[[#This Row],[Current coupon %]],Table1[[#This Row],[Yield (Annualised)]]-$AF$2,100,Table1[[#This Row],[Coupon Frequency2]])*Table1[[#This Row],[Face value]]/100 -> 1231.8005 | AG7: =(Table1[[#This Row],[P (+ shock)]]+Table1[[#This Row],[P (-shock)]]-2*Table1[[#This Row],[Ask Price]])/(2*Table1[[#This Row],[Ask Price]]*($AF$2^2)) -> 5.0696214 | AI7: =(L7*F7)/H7 -> 0.082568807 | AK7: =RATE(Table1[[#This Row],[Total No. of Coupons]],Table1[[#This Row],[Coupon Amount]],-Table1[[#This Row],[Ask Price]],Table1[[#This Row],[Face value]]) -> 0.028808554 | AL7: =Table1[[#This Row],[IRR]]*Table1[[#This Row],[Coupon Frequency2]] -> 0.028808554 | AM7: =-AA7*H7 -> -3218.2966 | AN7: Callable | AO7: India | AP7: =_xlfn.SWITCH(PROPER(TRIM(M7)), "Annual",1, "Semi-Annual",2, "Quarterly",4, "Monthly",12, "") -> 1
A8: 725IRFC35 | B8: Indian Railway Finance Corporation Limited 7.25% 21-DEC-2035 | C8: Corporate | D8: 42359 | E8: 49664 | F8: 1000 | G8: INR | H8: 1475 | I8: INR | J8: 147.5 | K8: 5 | L8: 0.0725 | M8: Annual | N8: 3747 | O8: 4.9152542 | P8: BBB | R8: BSE | S8: =ROUND(YEARFRAC(D8,E8),0) -> 20 | T8: {=_xlfn.IFS(Table1[[#This Row],[Coupon frequency]]="Semi-annual",2,Table1[[#This Row],[Coupon frequency]]="Quarterly",4,Table1[[#This Row],[Coupon frequency]]="Annual",1,Table1[[#This Row],[Coupon frequency]]="Every 4 months",3,Table1[[#This Row],[Coupon frequency]]="Monthly",12)} -> 1 | U8: =Table1[[#This Row],[Term to Maturity (Years)]]*Table1[[#This Row],[Coupon Frequency2]] -> 20 | V8: =Table1[[#This Row],[Face value]]*Table1[[#This Row],[Current coupon %]] -> 72.5 | W8: =RATE(Table1[[#This Row],[Total No. of Coupons]],Table1[[#This Row],[Coupon Amount]],-Table1[[#This Row],[Ask Price]],Table1[[#This Row],[Face value]]) -> 0.038126145 | X8: =Table1[[#This Row],[IRR]]*Table1[[#This Row],[Coupon Frequency2]] -> 0.038126145 | Y8: {=_xlfn.IFS(Table1[[#This Row],[Yield (Annualised)]]<0.05,1,Table1[[#This Row],[Yield (Annualised)]]<0.1,2,Table1[[#This Row],[Yield (Annualised)]]<0.15,3,Table1[[#This Row],[Yield (Annualised)]]<0.2,4,Table1[[#This Row],[Yield (Annualised)]]<0.25,5,Table1[[#This Row],[Yield (Annualised)]]<0.3,6,Table1[[#This Row],[Yield (Annualised)]]<0.35,7,Table1[[#This Row],[Yield (Annualised)]]<0.4,8,Table1[[#This Row],[Yield (Annualised)]]<0.45,9,Table1[[#This Row],[Yield (Annualised)]]<0.5,10,Table1[[#This Row],[Yield (Annualised)]]<0.55,11,Table1[[#This Row],[Yield (Annualised)]]<0.6,12,Table1[[#This Row],[Yield (Annualised)]]<0.65,13,Table1[[#This Row],[Yield (Annualised)]]<0.7,14,Table1[[#This Row],[Yield (Annualised)]]>0.7,15)} -> 1 | Z8: =DURATION(Table1[[#This Row],[Issue date]],Table1[[#This Row],[Maturity date]],Table1[[#This Row],[Current coupon %]],Table1[[#This Row],[Yield (Annualised)]],Table1[[#This Row],[Coupon Frequency2]]) -> 12.710163 | AA8: =Table1[[#This Row],[Macaulay Duration in Years]]/(1+Table1[[#This Row],[IRR]]) -> 12.243371 | AB8: =VLOOKUP(Table1[[#This Row],[Yield Cluster]],'Cluster Details'!$B$3:$C$16,2,0) -> 0.034641747 | AC8: =PRICE(Table1[[#This Row],[Issue date]],Table1[[#This Row],[Maturity date]],Table1[[#This Row],[Current coupon %]],Table1[[#This Row],[Average Cluster Yield]],100,Table1[[#This Row],[Coupon Frequency2]])*Table1[[#This Row],[Face value]]/100 -> 1539.8051 | AD8: =IF(Table1[[#This Row],[Ask Price]]>Table1[[#This Row],[Calculated Bond Price]],"Rich","Cheap") -> Cheap | AE8: =PRICE(Table1[[#This Row],[Issue date]],Table1[[#This Row],[Maturity date]],Table1[[#This Row],[Current coupon %]],Table1[[#This Row],[Yield (Annualised)]]+$AF$2,100,Table1[[#This Row],[Coupon Frequency2]])*Table1[[#This Row],[Face value]]/100 -> 1308.6368 | AF8: =PRICE(Table1[[#This Row],[Issue date]],Table1[[#This Row],[Maturity date]],Table1[[#This Row],[Current coupon %]],Table1[[#This Row],[Yield (Annualised)]]-$AF$2,100,Table1[[#This Row],[Coupon Frequency2]])*Table1[[#This Row],[Face value]]/100 -> 1671.7549 | AG8: =(Table1[[#This Row],[P (+ shock)]]+Table1[[#This Row],[P (-shock)]]-2*Table1[[#This Row],[Ask Price]])/(2*Table1[[#This Row],[Ask Price]]*($AF$2^2)) -> 103.02263 | AH8: 3.4759956 | AI8: =(L8*F8)/H8 -> 0.049152542 | AK8: =RATE(Table1[[#This Row],[Total No. of Coupons]],Table1[[#This Row],[Coupon Amount]],-Table1[[#This Row],[Ask Price]],Table1[[#This Row],[Face value]]) -> 0.038126145 | AL8: =Table1[[#This Row],[IRR]]*Table1[[#This Row],[Coupon Frequency2]] -> 0.038126145 | AM8: =-AA8*H8 -> -18058.972 | AN8: None | AO8: India | AP8: =_xlfn.SWITCH(PROPER(TRIM(M8)), "Annual",1, "Semi-Annual",2, "Quarterly",4, "Monthly",12, "") -> 1
A9: 711PFCL25 | B9: Power Finance Corporation Limited 7.11% 17-OCT-2025 | C9: Corporate | D9: 42294 | E9: 45947 | F9: 1000 | G9: INR | H9: 1235.8 | I9: INR | J9: 123.58 | K9: 8 | L9: 0.0711 | M9: Annual | N9: 30 | O9: 5.7533581 | P9: NR | R9: BSE | S9: =ROUND(YEARFRAC(D9,E9),0) -> 10 | T9: {=_xlfn.IFS(Table1[[#This Row],[Coupon frequency]]="Semi-annual",2,Table1[[#This Row],[Coupon frequency]]="Quarterly",4,Table1[[#This Row],[Coupon frequency]]="Annual",1,Table1[[#This Row],[Coupon frequency]]="Every 4 months",3,Table1[[#This Row],[Coupon frequency]]="Monthly",12)} -> 1 | U9: =Table1[[#This Row],[Term to Maturity (Years)]]*Table1[[#This Row],[Coupon Frequency2]] -> 10 | V9: =Table1[[#This Row],[Face value]]*Table1[[#This Row],[Current coupon %]] -> 71.1 | W9: =RATE(Table1[[#This Row],[Total No. of Coupons]],Table1[[#This Row],[Coupon Amount]],-Table1[[#This Row],[Ask Price]],Table1[[#This Row],[Face value]]) -> 0.041771107 | X9: =Table1[[#This Row],[IRR]]*Table1[[#This Row],[Coupon Frequency2]] -> 0.041771107 | Y9: {=_xlfn.IFS(Table1[[#This Row],[Yield (Annualised)]]<0.05,1,Table1[[#This Row],[Yield (Annualised)]]<0.1,2,Table1[[#This Row],[Yield (Annualised)]]<0.15,3,Table1[[#This Row],[Yield (Annualised)]]<0.2,4,Table1[[#This Row],[Yield (Annualised)]]<0.25,5,Table1[[#This Row],[Yield (Annualised)]]<0.3,6,Table1[[#This Row],[Yield (Annualised)]]<0.35,7,Table1[[#This Row],[Yield (Annualised)]]<0.4,8,Table1[[#This Row],[Yield (Annualised)]]<0.45,9,Table1[[#This Row],[Yield (Annualised)]]<0.5,10,Table1[[#This Row],[Yield (Annualised)]]<0.55,11,Table1[[#This Row],[Yield (Annualised)]]<0.6,12,Table1[[#This Row],[Yield (Annualised)]]<0.65,13,Table1[[#This Row],[Yield (Annualised)]]<0.7,14,Table1[[#This Row],[Yield (Annualised)]]>0.7,15)} -> 1 | Z9: =DURATION(Table1[[#This Row],[Issue date]],Table1[[#This Row],[Maturity date]],Table1[[#This Row],[Current coupon %]],Table1[[#This Row],[Yield (Annualised)]],Table1[[#This Row],[Coupon Frequency2]]) -> 7.7627467 | AA9: =Table1[[#This Row],[Macaulay Duration in Years]]/(1+Table1[[#This Row],[IRR]]) -> 7.4514897 | AB9: =VLOOKUP(Table1[[#This Row],[Yield Cluster]],'Cluster Details'!$B$3:$C$16,2,0) -> 0.034641747 | AC9: =PRICE(Table1[[#This Row],[Issue date]],Table1[[#This Row],[Maturity date]],Table1[[#This Row],[Current coupon %]],Table1[[#This Row],[Average Cluster Yield]],100,Table1[[#This Row],[Coupon Frequency2]])*Table1[[#This Row],[Face value]]/100 -> 1303.7571 | AD9: =IF(Table1[[#This Row],[Ask Price]]>Table1[[#This Row],[Calculated Bond Price]],"Rich","Cheap") -> Cheap | AE9: =PRICE(Table1[[#This Row],[Issue date]],Table1[[#This Row],[Maturity date]],Table1[[#This Row],[Current coupon %]],Table1[[#This Row],[Yield (Annualised)]]+$AF$2,100,Table1[[#This Row],[Coupon Frequency2]])*Table1[[#This Row],[Face value]]/100 -> 1147.9772 | AF9: =PRICE(Table1[[#This Row],[Issue date]],Table1[[#This Row],[Maturity date]],Table1[[#This Row],[Current coupon %]],Table1[[#This Row],[Yield (Annualised)]]-$AF$2,100,Table1[[#This Row],[Coupon Frequency2]])*Table1[[#This Row],[Face value]]/100 -> 1332.4714 | AG9: =(Table1[[#This Row],[P (+ shock)]]+Table1[[#This Row],[P (-shock)]]-2*Table1[[#This Row],[Ask Price]])/(2*Table1[[#This Row],[Ask Price]]*($AF$2^2)) -> 35.800889 | AH9: 0.8432257 | AI9: =(L9*F9)/H9 -> 0.057533581 | AK9: =RATE(Table1[[#This Row],[Total No. of Coupons]],Table1[[#This Row],[Coupon Amount]],-Table1[[#This Row],[Ask Price]],Table1[[#This Row],[Face value]]) -> 0.041771107 | AL9: =Table1[[#This Row],[IRR]]*Table1[[#This Row],[Coupon Frequency2]] -> 0.041771107 | AM9: =-AA9*H9 -> -9208.551 | AN9: None | AO9: India | AP9: =_xlfn.SWITCH(PROPER(TRIM(M9)), "Annual",1, "Semi-Annual",2, "Quarterly",4, "Monthly",12, "") -> 1
A10: 1050ICFL26 | B10: IndoStar Capital Finance Limited 10.5% 25-SEP-2026 | C10: Corporate | D10: 45560 | E10: 46290 | F10: 1000 | G10: INR | H10: 1109.52 | I10: INR | J10: 110.952 | K10: 5 | L10: 0.105 | M10: Annual | N10: 373 | O10: 9.4635518 | R10: BSE | S10: =ROUND(YEARFRAC(D10,E10),0) -> 2 | T10: {=_xlfn.IFS(Table1[[#This Row],[Coupon frequency]]="Semi-annual",2,Table1[[#This Row],[Coupon frequency]]="Quarterly",4,Table1[[#This Row],[Coupon frequency]]="Annual",1,Table1[[#This Row],[Coupon frequency]]="Every 4 months",3,Table1[[#This Row],[Coupon frequency]]="Monthly",12)} -> 1 | U10: =Table1[[#This Row],[Term to Maturity (Years)]]*Table1[[#This Row],[Coupon Frequency2]] -> 2 | V10: =Table1[[#This Row],[Face value]]*Table1[[#This Row],[Current coupon %]] -> 105 | W10: =RATE(Table1[[#This Row],[Total No. of Coupons]],Table1[[#This Row],[Coupon Amount]],-Table1[[#This Row],[Ask Price]],Table1[[#This Row],[Face value]]) -> 0.046399906 | X10: =Table1[[#This Row],[IRR]]*Table1[[#This Row],[Coupon Frequency2]] -> 0.046399906 | Y10: {=_xlfn.IFS(Table1[[#This Row],[Yield (Annualised)]]<0.05,1,Table1[[#This Row],[Yield (Annualised)]]<0.1,2,Table1[[#This Row],[Yield (Annualised)]]<0.15,3,Table1[[#This Row],[Yield (Annualised)]]<0.2,4,Table1[[#This Row],[Yield (Annualised)]]<0.25,5,Table1[[#This Row],[Yield (Annualised)]]<0.3,6,Table1[[#This Row],[Yield (Annualised)]]<0.35,7,Table1[[#This Row],[Yield (Annualised)]]<0.4,8,Table1[[#This Row],[Yield (Annualised)]]<0.45,9,Table1[[#This Row],[Yield (Annualised)]]<0.5,10,Table1[[#This Row],[Yield (Annualised)]]<0.55,11,Table1[[#This Row],[Yield (Annualised)]]<0.6,12,Table1[[#This Row],[Yield (Annualised)]]<0.65,13,Table1[[#This Row],[Yield (Annualised)]]<0.7,14,Table1[[#This Row],[Yield (Annualised)]]>0.7,15)} -> 1 | Z10: =DURATION(Table1[[#This Row],[Issue date]],Table1[[#This Row],[Maturity date]],Table1[[#This Row],[Current coupon %]],Table1[[#This Row],[Yield (Annualised)]],Table1[[#This Row],[Coupon Frequency2]]) -> 1.9095609 | AA10: =Table1[[#This Row],[Macaulay Duration in Years]]/(1+Table1[[#This Row],[IRR]]) -> 1.8248863 | AB10: =VLOOKUP(Table1[[#This Row],[Yield Cluster]],'Cluster Details'!$B$3:$C$16,2,0) -> 0.034641747 | AC10: =PRICE(Table1[[#This Row],[Issue date]],Table1[[#This Row],[Maturity date]],Table1[[#This Row],[Current coupon %]],Table1[[#This Row],[Average Cluster Yield]],100,Table1[[#This Row],[Coupon Frequency2]])*Table1[[#This Row],[Face value]]/100 -> 1133.7282 | AD10: =IF(Table1[[#This Row],[Ask Price]]>Table1[[#This Row],[Calculated Bond Price]],"Rich","Cheap") -> Cheap | AE10: =PRICE(Table1[[#This Row],[Issue date]],Table1[[#This Row],[Maturity date]],Table1[[#This Row],[Current coupon %]],Table1[[#This Row],[Yield (Annualised)]]+$AF$2,100,Table1[[#This Row],[Coupon Frequency2]])*Table1[[#This Row],[Face value]]/100 -> 1089.5546 | AF10: =PRICE(Table1[[#This Row],[Issue date]],Table1[[#This Row],[Maturity date]],Table1[[#This Row],[Current coupon %]],Table1[[#This Row],[Yield (Annualised)]]-$AF$2,100,Table1[[#This Row],[Coupon Frequency2]])*Table1[[#This Row],[Face value]]/100 -> 1130.0568 | AG10: =(Table1[[#This Row],[P (+ shock)]]+Table1[[#This Row],[P (-shock)]]-2*Table1[[#This Row],[Ask Price]])/(2*Table1[[#This Row],[Ask Price]]*($AF$2^2)) -> 2.5750383 | AI10: =(L10*F10)/H10 -> 0.094635518 | AK10: =RATE(Table1[[#This Row],[Total No. of Coupons]],Table1[[#This Row],[Coupon Amount]],-Table1[[#This Row],[Ask Price]],Table1[[#This Row],[Face value]]) -> 0.046399906 | AL10: =Table1[[#This Row],[IRR]]*Table1[[#This Row],[Coupon Frequency2]] -> 0.046399906 | AM10: =-AA10*H10 -> -2024.7478 | AN10: None | AO10: India | AP10: =_xlfn.SWITCH(PROPER(TRIM(M10)), "Annual",1, "Semi-Annual",2, "Quarterly",4, "Monthly",12, "") -> 1
A11: 775MFLTD25 | B11: Muthoot Finance Limited 7.75% 04-OCT-2025 | C11: Corporate | D11: 45203 | E11: 45934 | F11: 1000 | G11: INR | H11: 1052.52 | I11: INR | J11: 105.252 | K11: 31 | L11: 0.0775 | M11: Annual | N11: 17 | O11: 7.3632805 | P11: BB+ | R11: BSE | S11: =ROUND(YEARFRAC(D11,E11),0) -> 2 | T11: {=_xlfn.IFS(Table1[[#This Row],[Coupon frequency]]="Semi-annual",2,Table1[[#This Row],[Coupon frequency]]="Quarterly",4,Table1[[#This Row],[Coupon frequency]]="Annual",1,Table1[[#This Row],[Coupon frequency]]="Every 4 months",3,Table1[[#This Row],[Coupon frequency]]="Monthly",12)} -> 1 | U11: =Table1[[#This Row],[Term to Maturity (Years)]]*Table1[[#This Row],[Coupon Frequency2]] -> 2 | V11: =Table1[[#This Row],[Face value]]*Table1[[#This Row],[Current coupon %]] -> 77.5 | W11: =RATE(Table1[[#This Row],[Total No. of Coupons]],Table1[[#This Row],[Coupon Amount]],-Table1[[#This Row],[Ask Price]],Table1[[#This Row],[Face value]]) -> 0.049283174 | X11: =Table1[[#This Row],[IRR]]*Table1[[#This Row],[Coupon Frequency2]] -> 0.049283174 | Y11: {=_xlfn.IFS(Table1[[#This Row],[Yield (Annualised)]]<0.05,1,Table1[[#This Row],[Yield (Annualised)]]<0.1,2,Table1[[#This Row],[Yield (Annualised)]]<0.15,3,Table1[[#This Row],[Yield (Annualised)]]<0.2,4,Table1[[#This Row],[Yield (Annualised)]]<0.25,5,Table1[[#This Row],[Yield (Annualised)]]<0.3,6,Table1[[#This Row],[Yield (Annualised)]]<0.35,7,Table1[[#This Row],[Yield (Annualised)]]<0.4,8,Table1[[#This Row],[Yield (Annualised)]]<0.45,9,Table1[[#This Row],[Yield (Annualised)]]<0.5,10,Table1[[#This Row],[Yield (Annualised)]]<0.55,11,Table1[[#This Row],[Yield (Annualised)]]<0.6,12,Table1[[#This Row],[Yield (Annualised)]]<0.65,13,Table1[[#This Row],[Yield (Annualised)]]<0.7,14,Table1[[#This Row],[Yield (Annualised)]]>0.7,15)} -> 1 | Z11: =DURATION(Table1[[#This Row],[Issue date]],Table1[[#This Row],[Maturity date]],Table1[[#This Row],[Current coupon %]],Table1[[#This Row],[Yield (Annualised)]],Table1[[#This Row],[Coupon Frequency2]]) -> 1.9298256 | AA11: =Table1[[#This Row],[Macaulay Duration in Years]]/(1+Table1[[#This Row],[IRR]]) -> 1.8391847 | AB11: =VLOOKUP(Table1[[#This Row],[Yield Cluster]],'Cluster Details'!$B$3:$C$16,2,0) -> 0.034641747 | AC11: =PRICE(Table1[[#This Row],[Issue date]],Table1[[#This Row],[Maturity date]],Table1[[#This Row],[Current coupon %]],Table1[[#This Row],[Average Cluster Yield]],100,Table1[[#This Row],[Coupon Frequency2]])*Table1[[#This Row],[Face value]]/100 -> 1081.4596 | AD11: =IF(Table1[[#This Row],[Ask Price]]>Table1[[#This Row],[Calculated Bond Price]],"Rich","Cheap") -> Cheap | AE11: =PRICE(Table1[[#This Row],[Issue date]],Table1[[#This Row],[Maturity date]],Table1[[#This Row],[Current coupon %]],Table1[[#This Row],[Yield (Annualised)]]+$AF$2,100,Table1[[#This Row],[Coupon Frequency2]])*Table1[[#This Row],[Face value]]/100 -> 1033.4322 | AF11: =PRICE(Table1[[#This Row],[Issue date]],Table1[[#This Row],[Maturity date]],Table1[[#This Row],[Current coupon %]],Table1[[#This Row],[Yield (Annualised)]]-$AF$2,100,Table1[[#This Row],[Coupon Frequency2]])*Table1[[#This Row],[Face value]]/100 -> 1072.1547 | AG11: =(Table1[[#This Row],[P (+ shock)]]+Table1[[#This Row],[P (-shock)]]-2*Table1[[#This Row],[Ask Price]])/(2*Table1[[#This Row],[Ask Price]]*($AF$2^2)) -> 2.5977225 | AH11: 9.5 | AI11: =(L11*F11)/H11 -> 0.073632805 | AK11: =RATE(Table1[[#This Row],[Total No. of Coupons]],Table1[[#This Row],[Coupon Amount]],-Table1[[#This Row],[Ask Price]],Table1[[#This Row],[Face value]]) -> 0.049283174 | AL11: =Table1[[#This Row],[IRR]]*Table1[[#This Row],[Coupon Frequency2]] -> 0.049283174 | AM11: =-AA11*H11 -> -1935.7787 | AN11: None | AO11: India | AP11: =_xlfn.SWITCH(PROPER(TRIM(M11)), "Annual",1, "Semi-Annual",2, "Quarterly",4, "Monthly",12, "") -> 1
A12: 995ICFL626 | B12: IndoStar Capital Finance Limited 9.95% 26-JUN-2026 | C12: Corporate | D12: 45715 | E12: 46199 | F12: 100000 | G12: INR | H12: 104764.68 | I12: INR | J12: 104.76468 | K12: 1 | L12: 0.0995 | M12: Annual | N12: 282 | O12: 9.4974757 | R12: BSE | S12: =ROUND(YEARFRAC(D12,E12),0) -> 1 | T12: {=_xlfn.IFS(Table1[[#This Row],[Coupon frequency]]="Semi-annual",2,Table1[[#This Row],[Coupon frequency]]="Quarterly",4,Table1[[#This Row],[Coupon frequency]]="Annual",1,Table1[[#This Row],[Coupon frequency]]="Every 4 months",3,Table1[[#This Row],[Coupon frequency]]="Monthly",12)} -> 1 | U12: =Table1[[#This Row],[Term to Maturity (Years)]]*Table1[[#This Row],[Coupon Frequency2]] -> 1 | V12: =Table1[[#This Row],[Face value]]*Table1[[#This Row],[Current coupon %]] -> 9950 | W12: =RATE(Table1[[#This Row],[Total No. of Coupons]],Table1[[#This Row],[Coupon Amount]],-Table1[[#This Row],[Ask Price]],Table1[[#This Row],[Face value]]) -> 0.049494925 | X12: =Table1[[#This Row],[IRR]]*Table1[[#This Row],[Coupon Frequency2]] -> 0.049494925 | Y12: {=_xlfn.IFS(Table1[[#This Row],[Yield (Annualised)]]<0.05,1,Table1[[#This Row],[Yield (Annualised)]]<0.1,2,Table1[[#This Row],[Yield (Annualised)]]<0.15,3,Table1[[#This Row],[Yield (Annualised)]]<0.2,4,Table1[[#This Row],[Yield (Annualised)]]<0.25,5,Table1[[#This Row],[Yield (Annualised)]]<0.3,6,Table1[[#This Row],[Yield (Annualised)]]<0.35,7,Table1[[#This Row],[Yield (Annualised)]]<0.4,8,Table1[[#This Row],[Yield (Annualised)]]<0.45,9,Table1[[#This Row],[Yield (Annualised)]]<0.5,10,Table1[[#This Row],[Yield (Annualised)]]<0.55,11,Table1[[#This Row],[Yield (Annualised)]]<0.6,12,Table1[[#This Row],[Yield (Annualised)]]<0.65,13,Table1[[#This Row],[Yield (Annualised)]]<0.7,14,Table1[[#This Row],[Yield (Annualised)]]>0.7,15)} -> 1 | Z12: =DURATION(Table1[[#This Row],[Issue date]],Table1[[#This Row],[Maturity date]],Table1[[#This Row],[Current coupon %]],Table1[[#This Row],[Yield (Annualised)]],Table1[[#This Row],[Coupon Frequency2]]) -> 1.2438186 | AA12: =Table1[[#This Row],[Macaulay Duration in Years]]/(1+Table1[[#This Row],[IRR]]) -> 1.1851592 | AB12: =VLOOKUP(Table1[[#This Row],[Yield Cluster]],'Cluster Details'!$B$3:$C$16,2,0) -> 0.034641747 | AC12: =PRICE(Table1[[#This Row],[Issue date]],Table1[[#This Row],[Maturity date]],Table1[[#This Row],[Current coupon %]],Table1[[#This Row],[Average Cluster Yield]],100,Table1[[#This Row],[Coupon Frequency2]])*Table1[[#This Row],[Face value]]/100 -> 108256.74 | AD12: =IF(Table1[[#This Row],[Ask Price]]>Table1[[#This Row],[Calculated Bond Price]],"Rich","Cheap") -> Cheap | AE12: =PRICE(Table1[[#This Row],[Issue date]],Table1[[#This Row],[Maturity date]],Table1[[#This Row],[Current coupon %]],Table1[[#This Row],[Yield (Annualised)]]+$AF$2,100,Table1[[#This Row],[Coupon Frequency2]])*Table1[[#This Row],[Face value]]/100 -> 104912.94 | AF12: =PRICE(Table1[[#This Row],[Issue date]],Table1[[#This Row],[Maturity date]],Table1[[#This Row],[Current coupon %]],Table1[[#This Row],[Yield (Annualised)]]-$AF$2,100,Table1[[#This Row],[Coupon Frequency2]])*Table1[[#This Row],[Face value]]/100 -> 107589.28 | AG12: =(Table1[[#This Row],[P (+ shock)]]+Table1[[#This Row],[P (-shock)]]-2*Table1[[#This Row],[Ask Price]])/(2*Table1[[#This Row],[Ask Price]]*($AF$2^2)) -> 141.88272 | AH12: 23.811976 | AI12: =(L12*F12)/H12 -> 0.094974757 | AK12: =RATE(Table1[[#This Row],[Total No. of Coupons]],Table1[[#This Row],[Coupon Amount]],-Table1[[#This Row],[Ask Price]],Table1[[#This Row],[Face value]]) -> 0.049494925 | AL12: =Table1[[#This Row],[IRR]]*Table1[[#This Row],[Coupon Frequency2]] -> 0.049494925 | AM12: =-AA12*H12 -> -124162.83 | AN12: Putable | AO12: India | AP12: =_xlfn.SWITCH(PROPER(TRIM(M12)), "Annual",1, "Semi-Annual",2, "Quarterly",4, "Monthly",12, "") -> 1
A13: 9PEL25 | B13: Piramal Enterprises Ltd 9.0% 03-NOV-2025 | C13: Corporate | D13: 45233 | E13: 45964 | F13: 1000 | G13: INR | H13: 1074 | I13: INR | J13: 107.4 | K13: 6 | L13: 0.09 | M13: Annual | N13: 47 | O13: 8.3798883 | R13: BSE | S13: =ROUND(YEARFRAC(D13,E13),0) -> 2 | T13: {=_xlfn.IFS(Table1[[#This Row],[Coupon frequency]]="Semi-annual",2,Table1[[#This Row],[Coupon frequency]]="Quarterly",4,Table1[[#This Row],[Coupon frequency]]="Annual",1,Table1[[#This Row],[Coupon frequency]]="Every 4 months",3,Table1[[#This Row],[Coupon frequency]]="Monthly",12)} -> 1 | U13: =Table1[[#This Row],[Term to Maturity (Years)]]*Table1[[#This Row],[Coupon Frequency2]] -> 2 | V13: =Table1[[#This Row],[Face value]]*Table1[[#This Row],[Current coupon %]] -> 90 | W13: =RATE(Table1[[#This Row],[Total No. of Coupons]],Table1[[#This Row],[Coupon Amount]],-Table1[[#This Row],[Ask Price]],Table1[[#This Row],[Face value]]) -> 0.050191632 | X13: =Table1[[#This Row],[IRR]]*Table1[[#This Row],[Coupon Frequency2]] -> 0.050191632 | Y13: {=_xlfn.IFS(Table1[[#This Row],[Yield (Annualised)]]<0.05,1,Table1[[#This Row],[Yield (Annualised)]]<0.1,2,Table1[[#This Row],[Yield (Annualised)]]<0.15,3,Table1[[#This Row],[Yield (Annualised)]]<0.2,4,Table1[[#This Row],[Yield (Annualised)]]<0.25,5,Table1[[#This Row],[Yield (Annualised)]]<0.3,6,Table1[[#This Row],[Yield (Annualised)]]<0.35,7,Table1[[#This Row],[Yield (Annualised)]]<0.4,8,Table1[[#This Row],[Yield (Annualised)]]<0.45,9,Table1[[#This Row],[Yield (Annualised)]]<0.5,10,Table1[[#This Row],[Yield (Annualised)]]<0.55,11,Table1[[#This Row],[Yield (Annualised)]]<0.6,12,Table1[[#This Row],[Yield (Annualised)]]<0.65,13,Table1[[#This Row],[Yield (Annualised)]]<0.7,14,Table1[[#This Row],[Yield (Annualised)]]>0.7,15)} -> 2 | Z13: =DURATION(Table1[[#This Row],[Issue date]],Table1[[#This Row],[Maturity date]],Table1[[#This Row],[Current coupon %]],Table1[[#This Row],[Yield (Annualised)]],Table1[[#This Row],[Coupon Frequency2]]) -> 1.9202061 | AA13: =Table1[[#This Row],[Macaulay Duration in Years]]/(1+Table1[[#This Row],[IRR]]) -> 1.828434 | AB13: =VLOOKUP(Table1[[#This Row],[Yield Cluster]],'Cluster Details'!$B$3:$C$16,2,0) -> 0.078548802 | AC13: =PRICE(Table1[[#This Row],[Issue date]],Table1[[#This Row],[Maturity date]],Table1[[#This Row],[Current coupon %]],Table1[[#This Row],[Average Cluster Yield]],100,Table1[[#This Row],[Coupon Frequency2]])*Table1[[#This Row],[Face value]]/100 -> 1020.4612 | AD13: =IF(Table1[[#This Row],[Ask Price]]>Table1[[#This Row],[Calculated Bond Price]],"Rich","Cheap") -> Rich | AE13: =PRICE(Table1[[#This Row],[Issue date]],Table1[[#This Row],[Maturity date]],Table1[[#This Row],[Current coupon %]],Table1[[#This Row],[Yield (Annualised)]]+$AF$2,100,Table1[[#This Row],[Coupon Frequency2]])*Table1[[#This Row],[Face value]]/100 -> 1054.6358 | AF13: =PRICE(Table1[[#This Row],[Issue date]],Table1[[#This Row],[Maturity date]],Table1[[#This Row],[Current coupon %]],Table1[[#This Row],[Yield (Annualised)]]-$AF$2,100,Table1[[#This Row],[Coupon Frequency2]])*Table1[[#This Row],[Face value]]/100 -> 1093.9175 | AG13: =(Table1[[#This Row],[P (+ shock)]]+Table1[[#This Row],[P (-shock)]]-2*Table1[[#This Row],[Ask Price]])/(2*Table1[[#This Row],[Ask Price]]*($AF$2^2)) -> 2.5757823 | AH13: 11.863723 | AI13: =(L13*F13)/H13 -> 0.083798883 | AK13: =RATE(Table1[[#This Row],[Total No. of Coupons]],Table1[[#This Row],[Coupon Amount]],-Table1[[#This Row],[Ask Price]],Table1[[#This Row],[Face value]]) -> 0.050191632 | AL13: =Table1[[#This Row],[IRR]]*Table1[[#This Row],[Coupon Frequency2]] -> 0.050191632 | AM13: =-AA13*H13 -> -1963.7381 | AN13: None | AO13: India | AP13: =_xlfn.SWITCH(PROPER(TRIM(M13)), "Annual",1, "Semi-Annual",2, "Quarterly",4, "Monthly",12, "") -> 1
A14: 58PFCL26 | B14: Power Finance Corporation Limited 5.8% 22-JAN-2026 | C14: Corporate | D14: 44218 | E14: 46044 | F14: 1000 | G14: INR | H14: 1021.2 | I14: INR | J14: 102.12 | K14: 50 | L14: 0.058 | M14: Annual | N14: 127 | O14: 5.6795926 | P14: NR | R14: BSE | S14: =ROUND(YEARFRAC(D14,E14),0) -> 5 | T14: {=_xlfn.IFS(Table1[[#This Row],[Coupon frequency]]="Semi-annual",2,Table1[[#This Row],[Coupon frequency]]="Quarterly",4,Table1[[#This Row],[Coupon frequency]]="Annual",1,Table1[[#This Row],[Coupon frequency]]="Every 4 months",3,Table1[[#This Row],[Coupon frequency]]="Monthly",12)} -> 1 | U14: =Table1[[#This Row],[Term to Maturity (Years)]]*Table1[[#This Row],[Coupon Frequency2]] -> 5 | V14: =Table1[[#This Row],[Face value]]*Table1[[#This Row],[Current coupon %]] -> 58 | W14: =RATE(Table1[[#This Row],[Total No. of Coupons]],Table1[[#This Row],[Coupon Amount]],-Table1[[#This Row],[Ask Price]],Table1[[#This Row],[Face value]]) -> 0.053061817 | X14: =Table1[[#This Row],[IRR]]*Table1[[#This Row],[Coupon Frequency2]] -> 0.053061817 | Y14: {=_xlfn.IFS(Table1[[#This Row],[Yield (Annualised)]]<0.05,1,Table1[[#This Row],[Yield (Annualised)]]<0.1,2,Table1[[#This Row],[Yield (Annualised)]]<0.15,3,Table1[[#This Row],[Yield (Annualised)]]<0.2,4,Table1[[#This Row],[Yield (Annualised)]]<0.25,5,Table1[[#This Row],[Yield (Annualised)]]<0.3,6,Table1[[#This Row],[Yield (Annualised)]]<0.35,7,Table1[[#This Row],[Yield (Annualised)]]<0.4,8,Table1[[#This Row],[Yield (Annualised)]]<0.45,9,Table1[[#This Row],[Yield (Annualised)]]<0.5,10,Table1[[#This Row],[Yield (Annualised)]]<0.55,11,Table1[[#This Row],[Yield (Annualised)]]<0.6,12,Table1[[#This Row],[Yield (Annualised)]]<0.65,13,Table1[[#This Row],[Yield (Annualised)]]<0.7,14,Table1[[#This Row],[Yield (Annualised)]]>0.7,15)} -> 2 | Z14: =DURATION(Table1[[#This Row],[Issue date]],Table1[[#This Row],[Maturity date]],Table1[[#This Row],[Current coupon %]],Table1[[#This Row],[Yield (Annualised)]],Table1[[#This Row],[Coupon Frequency2]]) -> 4.4871577 | AA14: =Table1[[#This Row],[Macaulay Duration in Years]]/(1+Table1[[#This Row],[IRR]]) -> 4.2610582 | AB14: =VLOOKUP(Table1[[#This Row],[Yield Cluster]],'Cluster Details'!$B$3:$C$16,2,0) -> 0.078548802 | AC14: =PRICE(Table1[[#This Row],[Issue date]],Table1[[#This Row],[Maturity date]],Table1[[#This Row],[Current coupon %]],Table1[[#This Row],[Average Cluster Yield]],100,Table1[[#This Row],[Coupon Frequency2]])*Table1[[#This Row],[Face value]]/100 -> 917.63983 | AD14: =IF(Table1[[#This Row],[Ask Price]]>Table1[[#This Row],[Calculated Bond Price]],"Rich","Cheap") -> Rich | AE14: =PRICE(Table1[[#This Row],[Issue date]],Table1[[#This Row],[Maturity date]],Table1[[#This Row],[Current coupon %]],Table1[[#This Row],[Yield (Annualised)]]+$AF$2,100,Table1[[#This Row],[Coupon Frequency2]])*Table1[[#This Row],[Face value]]/100 -> 978.85422 | AF14: =PRICE(Table1[[#This Row],[Issue date]],Table1[[#This Row],[Maturity date]],Table1[[#This Row],[Current coupon %]],Table1[[#This Row],[Yield (Annualised)]]-$AF$2,100,Table1[[#This Row],[Coupon Frequency2]])*Table1[[#This Row],[Face value]]/100 -> 1065.934 | AG14: =(Table1[[#This Row],[P (+ shock)]]+Table1[[#This Row],[P (-shock)]]-2*Table1[[#This Row],[Ask Price]])/(2*Table1[[#This Row],[Ask Price]]*($AF$2^2)) -> 11.693129 | AH14: -19.204811 | AI14: =(L14*F14)/H14 -> 0.056795926 | AK14: =RATE(Table1[[#This Row],[Total No. of Coupons]],Table1[[#This Row],[Coupon Amount]],-Table1[[#This Row],[Ask Price]],Table1[[#This Row],[Face value]]) -> 0.053061817 | AL14: =Table1[[#This Row],[IRR]]*Table1[[#This Row],[Coupon Frequency2]] -> 0.053061817 | AM14: =-AA14*H14 -> -4351.3927 | AN14: None | AO14: India | AP14: =_xlfn.SWITCH(PROPER(TRIM(M14)), "Annual",1, "Semi-Annual",2, "Quarterly",4, "Monthly",12, "") -> 1
A15: MFLIV25 | B15: Muthoot Finance Limited 7.25% 03-NOV-2025 | C15: Corporate | D15: 44868 | E15: 45964 | F15: 1000 | G15: INR | H15: 1052 | I15: INR | J15: 105.2 | K15: 80 | L15: 0.0725 | M15: Annual | N15: 47 | O15: 6.891635 | P15: BB+ | R15: BSE | S15: =ROUND(YEARFRAC(D15,E15),0) -> 3 | T15: {=_xlfn.IFS(Table1[[#This Row],[Coupon frequency]]="Semi-annual",2,Table1[[#This Row],[Coupon frequency]]="Quarterly",4,Table1[[#This Row],[Coupon frequency]]="Annual",1,Table1[[#This Row],[Coupon frequency]]="Every 4 months",3,Table1[[#This Row],[Coupon frequency]]="Monthly",12)} -> 1 | U15: =Table1[[#This Row],[Term to Maturity (Years)]]*Table1[[#This Row],[Coupon Frequency2]] -> 3 | V15: =Table1[[#This Row],[Face value]]*Table1[[#This Row],[Current coupon %]] -> 72.5 | W15: =RATE(Table1[[#This Row],[Total No. of Coupons]],Table1[[#This Row],[Coupon Amount]],-Table1[[#This Row],[Ask Price]],Table1[[#This Row],[Face value]]) -> 0.053287416 | X15: =Table1[[#This Row],[IRR]]*Table1[[#This Row],[Coupon Frequency2]] -> 0.053287416 | Y15: {=_xlfn.IFS(Table1[[#This Row],[Yield (Annualised)]]<0.05,1,Table1[[#This Row],[Yield (Annualised)]]<0.1,2,Table1[[#This Row],[Yield (Annualised)]]<0.15,3,Table1[[#This Row],[Yield (Annualised)]]<0.2,4,Table1[[#This Row],[Yield (Annualised)]]<0.25,5,Table1[[#This Row],[Yield (Annualised)]]<0.3,6,Table1[[#This Row],[Yield (Annualised)]]<0.35,7,Table1[[#This Row],[Yield (Annualised)]]<0.4,8,Table1[[#This Row],[Yield (Annualised)]]<0.45,9,Table1[[#This Row],[Yield (Annualised)]]<0.5,10,Table1[[#This Row],[Yield (Annualised)]]<0.55,11,Table1[[#This Row],[Yield (Annualised)]]<0.6,12,Table1[[#This Row],[Yield (Annualised)]]<0.65,13,Table1[[#This Row],[Yield (Annualised)]]<0.7,14,Table1[[#This Row],[Yield (Annualised)]]>0.7,15)} -> 2 | Z15: =DURATION(Table1[[#This Row],[Issue date]],Table1[[#This Row],[Maturity date]],Table1[[#This Row],[Current coupon %]],Table1[[#This Row],[Yield (Annualised)]],Table1[[#This Row],[Coupon Frequency2]]) -> 2.8070209 | AA15: =Table1[[#This Row],[Macaulay Duration in Years]]/(1+Table1[[#This Row],[IRR]]) -> 2.6650094 | AB15: =VLOOKUP(Table1[[#This Row],[Yield Cluster]],'Cluster Details'!$B$3:$C$16,2,0) -> 0.078548802 | AC15: =PRICE(Table1[[#This Row],[Issue date]],Table1[[#This Row],[Maturity date]],Table1[[#This Row],[Current coupon %]],Table1[[#This Row],[Average Cluster Yield]],100,Table1[[#This Row],[Coupon Frequency2]])*Table1[[#This Row],[Face value]]/100 -> 984.37074 | AD15: =IF(Table1[[#This Row],[Ask Price]]>Table1[[#This Row],[Calculated Bond Price]],"Rich","Cheap") -> Rich | AE15: =PRICE(Table1[[#This Row],[Issue date]],Table1[[#This Row],[Maturity date]],Table1[[#This Row],[Current coupon %]],Table1[[#This Row],[Yield (Annualised)]]+$AF$2,100,Table1[[#This Row],[Coupon Frequency2]])*Table1[[#This Row],[Face value]]/100 -> 1024.4763 | AF15: =PRICE(Table1[[#This Row],[Issue date]],Table1[[#This Row],[Maturity date]],Table1[[#This Row],[Current coupon %]],Table1[[#This Row],[Yield (Annualised)]]-$AF$2,100,Table1[[#This Row],[Coupon Frequency2]])*Table1[[#This Row],[Face value]]/100 -> 1080.5644 | AG15: =(Table1[[#This Row],[P (+ shock)]]+Table1[[#This Row],[P (-shock)]]-2*Table1[[#This Row],[Ask Price]])/(2*Table1[[#This Row],[Ask Price]]*($AF$2^2)) -> 4.9464891 | AH15: 12.051015 | AI15: =(L15*F15)/H15 -> 0.06891635 | AK15: =RATE(Table1[[#This Row],[Total No. of Coupons]],Table1[[#This Row],[Coupon Amount]],-Table1[[#This Row],[Ask Price]],Table1[[#This Row],[Face value]]) -> 0.053287416 | AL15: =Table1[[#This Row],[IRR]]*Table1[[#This Row],[Coupon Frequency2]] -> 0.053287416 | AM15: =-AA15*H15 -> -2803.5899 | AN15: None | AO15: India | AP15: =_xlfn.SWITCH(PROPER(TRIM(M15)), "Annual",1, "Semi-Annual",2, "Quarterly",4, "Monthly",12, "") -> 1
A16: 895EFSL25A | B16: Edelweiss Financial Services Limited 8.95% 26-OCT-2025 | C16: Corporate | D16: 45225 | E16: 45956 | F16: 1000 | G16: INR | H16: 1066.5 | I16: INR | J16: 106.65 | K16: 5 | L16: 0.0895 | M16: Annual | N16: 39 | O16: 8.3919362 | R16: BSE | S16: =ROUND(YEARFRAC(D16,E16),0) -> 2 | T16: {=_xlfn.IFS(Table1[[#This Row],[Coupon frequency]]="Semi-annual",2,Table1[[#This Row],[Coupon frequency]]="Quarterly",4,Table1[[#This Row],[Coupon frequency]]="Annual",1,Table1[[#This Row],[Coupon frequency]]="Every 4 months",3,Table1[[#This Row],[Coupon frequency]]="Monthly",12)} -> 1 | U16: =Table1[[#This Row],[Term to Maturity (Years)]]*Table1[[#This Row],[Coupon Frequency2]] -> 2 | V16: =Table1[[#This Row],[Face value]]*Table1[[#This Row],[Current coupon %]] -> 89.5 | W16: =RATE(Table1[[#This Row],[Total No. of Coupons]],Table1[[#This Row],[Coupon Amount]],-Table1[[#This Row],[Ask Price]],Table1[[#This Row],[Face value]]) -> 0.05355569 | X16: =Table1[[#This Row],[IRR]]*Table1[[#This Row],[Coupon Frequency2]] -> 0.05355569 | Y16: {=_xlfn.IFS(Table1[[#This Row],[Yield (Annualised)]]<0.05,1,Table1[[#This Row],[Yield (Annualised)]]<0.1,2,Table1[[#This Row],[Yield (Annualised)]]<0.15,3,Table1[[#This Row],[Yield (Annualised)]]<0.2,4,Table1[[#This Row],[Yield (Annualised)]]<0.25,5,Table1[[#This Row],[Yield (Annualised)]]<0.3,6,Table1[[#This Row],[Yield (Annualised)]]<0.35,7,Table1[[#This Row],[Yield (Annualised)]]<0.4,8,Table1[[#This Row],[Yield (Annualised)]]<0.45,9,Table1[[#This Row],[Yield (Annualised)]]<0.5,10,Table1[[#This Row],[Yield (Annualised)]]<0.55,11,Table1[[#This Row],[Yield (Annualised)]]<0.6,12,Table1[[#This Row],[Yield (Annualised)]]<0.65,13,Table1[[#This Row],[Yield (Annualised)]]<0.7,14,Table1[[#This Row],[Yield (Annualised)]]>0.7,15)} -> 2 | Z16: =DURATION(Table1[[#This Row],[Issue date]],Table1[[#This Row],[Maturity date]],Table1[[#This Row],[Current coupon %]],Table1[[#This Row],[Yield (Annualised)]],Table1[[#This Row],[Coupon Frequency2]]) -> 1.9203465 | AA16: =Table1[[#This Row],[Macaulay Duration in Years]]/(1+Table1[[#This Row],[IRR]]) -> 1.822729 | AB16: =VLOOKUP(Table1[[#This Row],[Yield Cluster]],'Cluster Details'!$B$3:$C$16,2,0) -> 0.078548802 | AC16: =PRICE(Table1[[#This Row],[Issue date]],Table1[[#This Row],[Maturity date]],Table1[[#This Row],[Current coupon %]],Table1[[#This Row],[Average Cluster Yield]],100,Table1[[#This Row],[Coupon Frequency2]])*Table1[[#This Row],[Face value]]/100 -> 1019.5678 | AD16: =IF(Table1[[#This Row],[Ask Price]]>Table1[[#This Row],[Calculated Bond Price]],"Rich","Cheap") -> Rich | AE16: =PRICE(Table1[[#This Row],[Issue date]],Table1[[#This Row],[Maturity date]],Table1[[#This Row],[Current coupon %]],Table1[[#This Row],[Yield (Annualised)]]+$AF$2,100,Table1[[#This Row],[Coupon Frequency2]])*Table1[[#This Row],[Face value]]/100 -> 1047.3301 | AF16: =PRICE(Table1[[#This Row],[Issue date]],Table1[[#This Row],[Maturity date]],Table1[[#This Row],[Current coupon %]],Table1[[#This Row],[Yield (Annualised)]]-$AF$2,100,Table1[[#This Row],[Coupon Frequency2]])*Table1[[#This Row],[Face value]]/100 -> 1086.2158 | AG16: =(Table1[[#This Row],[P (+ shock)]]+Table1[[#This Row],[P (-shock)]]-2*Table1[[#This Row],[Ask Price]])/(2*Table1[[#This Row],[Ask Price]]*($AF$2^2)) -> 2.55961 | AH16: 14.483944 | AI16: =(L16*F16)/H16 -> 0.083919362 | AK16: =RATE(Table1[[#This Row],[Total No. of Coupons]],Table1[[#This Row],[Coupon Amount]],-Table1[[#This Row],[Ask Price]],Table1[[#This Row],[Face value]]) -> 0.05355569 | AL16: =Table1[[#This Row],[IRR]]*Table1[[#This Row],[Coupon Frequency2]] -> 0.05355569 | AM16: =-AA16*H16 -> -1943.9405 | AN16: None | AO16: India | AP16: =_xlfn.SWITCH(PROPER(TRIM(M16)), "Annual",1, "Semi-Annual",2, "Quarterly",4, "Monthly",12, "") -> 1
A17: 93ARKA25 | B17: Arka Fincap Ltd. 9.3% 27-DEC-2025 | C17: Corporate | D17: 45287 | E17: 46018 | F17: 1000 | G17: INR | H17: 1072.85 | I17: INR | J17: 107.285 | K17: 3 | L17: 0.093 | M17: Annual | N17: 101 | O17: 8.6684998 | R17: BSE | S17: =ROUND(YEARFRAC(D17,E17),0) -> 2 | T17: {=_xlfn.IFS(Table1[[#This Row],[Coupon frequency]]="Semi-annual",2,Table1[[#This Row],[Coupon frequency]]="Quarterly",4,Table1[[#This Row],[Coupon frequency]]="Annual",1,Table1[[#This Row],[Coupon frequency]]="Every 4 months",3,Table1[[#This Row],[Coupon frequency]]="Monthly",12)} -> 1 | U17: =Table1[[#This Row],[Term to Maturity (Years)]]*Table1[[#This Row],[Coupon Frequency2]] -> 2 | V17: =Table1[[#This Row],[Face value]]*Table1[[#This Row],[Current coupon %]] -> 93 | W17: =RATE(Table1[[#This Row],[Total No. of Coupons]],Table1[[#This Row],[Coupon Amount]],-Table1[[#This Row],[Ask Price]],Table1[[#This Row],[Face value]]) -> 0.053619848 | X17: =Table1[[#This Row],[IRR]]*Table1[[#This Row],[Coupon Frequency2]] -> 0.053619848 | Y17: {=_xlfn.IFS(Table1[[#This Row],[Yield (Annualised)]]<0.05,1,Table1[[#This Row],[Yield (Annualised)]]<0.1,2,Table1[[#This Row],[Yield (Annualised)]]<0.15,3,Table1[[#This Row],[Yield (Annualised)]]<0.2,4,Table1[[#This Row],[Yield (Annualised)]]<0.25,5,Table1[[#This Row],[Yield (Annualised)]]<0.3,6,Table1[[#This Row],[Yield (Annualised)]]<0.35,7,Table1[[#This Row],[Yield (Annualised)]]<0.4,8,Table1[[#This Row],[Yield (Annualised)]]<0.45,9,Table1[[#This Row],[Yield (Annualised)]]<0.5,10,Table1[[#This Row],[Yield (Annualised)]]<0.55,11,Table1[[#This Row],[Yield (Annualised)]]<0.6,12,Table1[[#This Row],[Yield (Annualised)]]<0.65,13,Table1[[#This Row],[Yield (Annualised)]]<0.7,14,Table1[[#This Row],[Yield (Annualised)]]>0.7,15)} -> 2 | Z17: =DURATION(Table1[[#This Row],[Issue date]],Table1[[#This Row],[Maturity date]],Table1[[#This Row],[Current coupon %]],Table1[[#This Row],[Yield (Annualised)]],Table1[[#This Row],[Coupon Frequency2]]) -> 1.9177265 | AA17: =Table1[[#This Row],[Macaulay Duration in Years]]/(1+Table1[[#This Row],[IRR]]) -> 1.8201313 | AB17: =VLOOKUP(Table1[[#This Row],[Yield Cluster]],'Cluster Details'!$B$3:$C$16,2,0) -> 0.078548802 | AC17: =PRICE(Table1[[#This Row],[Issue date]],Table1[[#This Row],[Maturity date]],Table1[[#This Row],[Current coupon %]],Table1[[#This Row],[Average Cluster Yield]],100,Table1[[#This Row],[Coupon Frequency2]])*Table1[[#This Row],[Face value]]/100 -> 1025.8217 | AD17: =IF(Table1[[#This Row],[Ask Price]]>Table1[[#This Row],[Calculated Bond Price]],"Rich","Cheap") -> Rich | AE17: =PRICE(Table1[[#This Row],[Issue date]],Table1[[#This Row],[Maturity date]],Table1[[#This Row],[Current coupon %]],Table1[[#This Row],[Yield (Annualised)]]+$AF$2,100,Table1[[#This Row],[Coupon Frequency2]])*Table1[[#This Row],[Face value]]/100 -> 1053.5933 | AF17: =PRICE(Table1[[#This Row],[Issue date]],Table1[[#This Row],[Maturity date]],Table1[[#This Row],[Current coupon %]],Table1[[#This Row],[Yield (Annualised)]]-$AF$2,100,Table1[[#This Row],[Coupon Frequency2]])*Table1[[#This Row],[Face value]]/100 -> 1092.6548 | AG17: =(Table1[[#This Row],[P (+ shock)]]+Table1[[#This Row],[P (-shock)]]-2*Table1[[#This Row],[Ask Price]])/(2*Table1[[#This Row],[Ask Price]]*($AF$2^2)) -> 2.5545771 | AH17: -50.500936 | AI17: =(L17*F17)/H17 -> 0.086684998 | AK17: =RATE(Table1[[#This Row],[Total No. of Coupons]],Table1[[#This Row],[Coupon Amount]],-Table1[[#This Row],[Ask Price]],Table1[[#This Row],[Face value]]) -> 0.053619848 | AL17: =Table1[[#This Row],[IRR]]*Table1[[#This Row],[Coupon Frequency2]] -> 0.053619848 | AM17: =-AA17*H17 -> -1952.7279 | AN17: None | AO17: India | AP17: =_xlfn.SWITCH(PROPER(TRIM(M17)), "Annual",1, "Semi-Annual",2, "Quarterly",4, "Monthly",12, "") -> 1
A18: 762NTPC35F | B18: NTPC Limited 7.62% 05-OCT-2035 | C18: Corporate | D18: 42282 | E18: 49587 | F18: 1000 | G18: INR | H18: 1269 | I18: INR | J18: 126.9 | K18: 5 | L18: 0.0762 | M18: Annual | N18: 3670 | O18: 6.0047281 | P18: BBB | R18: BSE | S18: =ROUND(YEARFRAC(D18,E18),0) -> 20 | T18: {=_xlfn.IFS(Table1[[#This Row],[Coupon frequency]]="Semi-annual",2,Table1[[#This Row],[Coupon frequency]]="Quarterly",4,Table1[[#This Row],[Coupon frequency]]="Annual",1,Table1[[#This Row],[Coupon frequency]]="Every 4 months",3,Table1[[#This Row],[Coupon frequency]]="Monthly",12)} -> 1 | U18: =Table1[[#This Row],[Term to Maturity (Years)]]*Table1[[#This Row],[Coupon Frequency2]] -> 20 | V18: =Table1[[#This Row],[Face value]]*Table1[[#This Row],[Current coupon %]] -> 76.2 | W18: =RATE(Table1[[#This Row],[Total No. of Coupons]],Table1[[#This Row],[Coupon Amount]],-Table1[[#This Row],[Ask Price]],Table1[[#This Row],[Face value]]) -> 0.05389599 | X18: =Table1[[#This Row],[IRR]]*Table1[[#This Row],[Coupon Frequency2]] -> 0.05389599 | Y18: {=_xlfn.IFS(Table1[[#This Row],[Yield (Annualised)]]<0.05,1,Table1[[#This Row],[Yield (Annualised)]]<0.1,2,Table1[[#This Row],[Yield (Annualised)]]<0.15,3,Table1[[#This Row],[Yield (Annualised)]]<0.2,4,Table1[[#This Row],[Yield (Annualised)]]<0.25,5,Table1[[#This Row],[Yield (Annualised)]]<0.3,6,Table1[[#This Row],[Yield (Annualised)]]<0.35,7,Table1[[#This Row],[Yield (Annualised)]]<0.4,8,Table1[[#This Row],[Yield (Annualised)]]<0.45,9,Table1[[#This Row],[Yield (Annualised)]]<0.5,10,Table1[[#This Row],[Yield (Annualised)]]<0.55,11,Table1[[#This Row],[Yield (Annualised)]]<0.6,12,Table1[[#This Row],[Yield (Annualised)]]<0.65,13,Table1[[#This Row],[Yield (Annualised)]]<0.7,14,Table1[[#This Row],[Yield (Annualised)]]>0.7,15)} -> 2 | Z18: =DURATION(Table1[[#This Row],[Issue date]],Table1[[#This Row],[Maturity date]],Table1[[#This Row],[Current coupon %]],Table1[[#This Row],[Yield (Annualised)]],Table1[[#This Row],[Coupon Frequency2]]) -> 11.878675 | AA18: =Table1[[#This Row],[Macaulay Duration in Years]]/(1+Table1[[#This Row],[IRR]]) -> 11.271203 | AB18: =VLOOKUP(Table1[[#This Row],[Yield Cluster]],'Cluster Details'!$B$3:$C$16,2,0) -> 0.078548802 | AC18: =PRICE(Table1[[#This Row],[Issue date]],Table1[[#This Row],[Maturity date]],Table1[[#This Row],[Current coupon %]],Table1[[#This Row],[Average Cluster Yield]],100,Table1[[#This Row],[Coupon Frequency2]])*Table1[[#This Row],[Face value]]/100 -> 976.68793 | AD18: =IF(Table1[[#This Row],[Ask Price]]>Table1[[#This Row],[Calculated Bond Price]],"Rich","Cheap") -> Rich | AE18: =PRICE(Table1[[#This Row],[Issue date]],Table1[[#This Row],[Maturity date]],Table1[[#This Row],[Current coupon %]],Table1[[#This Row],[Yield (Annualised)]]+$AF$2,100,Table1[[#This Row],[Coupon Frequency2]])*Table1[[#This Row],[Face value]]/100 -> 1136.7688 | AF18: =PRICE(Table1[[#This Row],[Issue date]],Table1[[#This Row],[Maturity date]],Table1[[#This Row],[Current coupon %]],Table1[[#This Row],[Yield (Annualised)]]-$AF$2,100,Table1[[#This Row],[Coupon Frequency2]])*Table1[[#This Row],[Face value]]/100 -> 1424.2574 | AG18: =(Table1[[#This Row],[P (+ shock)]]+Table1[[#This Row],[P (-shock)]]-2*Table1[[#This Row],[Ask Price]])/(2*Table1[[#This Row],[Ask Price]]*($AF$2^2)) -> 90.725872 | AH18: 26.787982 | AI18: =(L18*F18)/H18 -> 0.060047281 | AK18: =RATE(Table1[[#This Row],[Total No. of Coupons]],Table1[[#This Row],[Coupon Amount]],-Table1[[#This Row],[Ask Price]],Table1[[#This Row],[Face value]]) -> 0.05389599 | AL18: =Table1[[#This Row],[IRR]]*Table1[[#This Row],[Coupon Frequency2]] -> 0.05389599 | AM18: =-AA18*H18 -> -14303.156 | AN18: None | AO18: India | AP18: =_xlfn.SWITCH(PROPER(TRIM(M18)), "Annual",1, "Semi-Annual",2, "Quarterly",4, "Monthly",12, "") -> 1
A19: 888IHFL25F | B19: Cholamandalam Investment and finance Company Limited 8.4% 07-DEC-2025 | C19: Corporate | D19: 45267 | E19: 45998 | F19: 1000 | G19: INR | H19: 1055 | I19: INR | J19: 105.5 | K19: 100 | L19: 0.084 | M19: Annual | N19: 81 | O19: 7.9620853 | R19: BSE | S19: =ROUND(YEARFRAC(D19,E19),0) -> 2 | T19: {=_xlfn.IFS(Table1[[#This Row],[Coupon frequency]]="Semi-annual",2,Table1[[#This Row],[Coupon frequency]]="Quarterly",4,Table1[[#This Row],[Coupon frequency]]="Annual",1,Table1[[#This Row],[Coupon frequency]]="Every 4 months",3,Table1[[#This Row],[Coupon frequency]]="Monthly",12)} -> 1 | U19: =Table1[[#This Row],[Term to Maturity (Years)]]*Table1[[#This Row],[Coupon Frequency2]] -> 2 | V19: =Table1[[#This Row],[Face value]]*Table1[[#This Row],[Current coupon %]] -> 84 | W19: =RATE(Table1[[#This Row],[Total No. of Coupons]],Table1[[#This Row],[Coupon Amount]],-Table1[[#This Row],[Ask Price]],Table1[[#This Row],[Face value]]) -> 0.054242791 | X19: =Table1[[#This Row],[IRR]]*Table1[[#This Row],[Coupon Frequency2]] -> 0.054242791 | Y19: {=_xlfn.IFS(Table1[[#This Row],[Yield (Annualised)]]<0.05,1,Table1[[#This Row],[Yield (Annualised)]]<0.1,2,Table1[[#This Row],[Yield (Annualised)]]<0.15,3,Table1[[#This Row],[Yield (Annualised)]]<0.2,4,Table1[[#This Row],[Yield (Annualised)]]<0.25,5,Table1[[#This Row],[Yield (Annualised)]]<0.3,6,Table1[[#This Row],[Yield (Annualised)]]<0.35,7,Table1[[#This Row],[Yield (Annualised)]]<0.4,8,Table1[[#This Row],[Yield (Annualised)]]<0.45,9,Table1[[#This Row],[Yield (Annualised)]]<0.5,10,Table1[[#This Row],[Yield (Annualised)]]<0.55,11,Table1[[#This Row],[Yield (Annualised)]]<0.6,12,Table1[[#This Row],[Yield (Annualised)]]<0.65,13,Table1[[#This Row],[Yield (Annualised)]]<0.7,14,Table1[[#This Row],[Yield (Annualised)]]>0.7,15)} -> 2 | Z19: =DURATION(Table1[[#This Row],[Issue date]],Table1[[#This Row],[Maturity date]],Table1[[#This Row],[Current coupon %]],Table1[[#This Row],[Yield (Annualised)]],Table1[[#This Row],[Coupon Frequency2]]) -> 1.9244758 | AA19: =Table1[[#This Row],[Macaulay Duration in Years]]/(1+Table1[[#This Row],[IRR]]) -> 1.8254579 | AB19: =VLOOKUP(Table1[[#This Row],[Yield Cluster]],'Cluster Details'!$B$3:$C$16,2,0) -> 0.078548802 | AC19: =PRICE(Table1[[#This Row],[Issue date]],Table1[[#This Row],[Maturity date]],Table1[[#This Row],[Current coupon %]],Table1[[#This Row],[Average Cluster Yield]],100,Table1[[#This Row],[Coupon Frequency2]])*Table1[[#This Row],[Face value]]/100 -> 1009.7403 | AD19: =IF(Table1[[#This Row],[Ask Price]]>Table1[[#This Row],[Calculated Bond Price]],"Rich","Cheap") -> Rich | AE19: =PRICE(Table1[[#This Row],[Issue date]],Table1[[#This Row],[Maturity date]],Table1[[#This Row],[Current coupon %]],Table1[[#This Row],[Yield (Annualised)]]+$AF$2,100,Table1[[#This Row],[Coupon Frequency2]])*Table1[[#This Row],[Face value]]/100 -> 1036.0085 | AF19: =PRICE(Table1[[#This Row],[Issue date]],Table1[[#This Row],[Maturity date]],Table1[[#This Row],[Current coupon %]],Table1[[#This Row],[Yield (Annualised)]]-$AF$2,100,Table1[[#This Row],[Coupon Frequency2]])*Table1[[#This Row],[Face value]]/100 -> 1074.5324 | AG19: =(Table1[[#This Row],[P (+ shock)]]+Table1[[#This Row],[P (-shock)]]-2*Table1[[#This Row],[Ask Price]])/(2*Table1[[#This Row],[Ask Price]]*($AF$2^2)) -> 2.563706 | AI19: =(L19*F19)/H19 -> 0.079620853 | AK19: =RATE(Table1[[#This Row],[Total No. of Coupons]],Table1[[#This Row],[Coupon Amount]],-Table1[[#This Row],[Ask Price]],Table1[[#This Row],[Face value]]) -> 0.054242791 | AL19: =Table1[[#This Row],[IRR]]*Table1[[#This Row],[Coupon Frequency2]] -> 0.054242791 | AM19: =-AA19*H19 -> -1925.858 | AN19: None | AO19: India | AP19: =_xlfn.SWITCH(PROPER(TRIM(M19)), "Annual",1, "Semi-Annual",2, "Quarterly",4, "Monthly",12, "") -> 1
A20: 760MFL25 | B20: Muthoot Finance Limited 7.6% 23-DEC-2025 | C20: Corporate | D20: 44918 | E20: 46014 | F20: 1000 | G20: INR | H20: 1057 | I20: INR | J20: 105.7 | K20: 2 | L20: 0.076 | M20: Annual | N20: 97 | O20: 7.1901608 | P20: BB+ | R20: BSE | S20: =ROUND(YEARFRAC(D20,E20),0) -> 3 | T20: {=_xlfn.IFS(Table1[[#This Row],[Coupon frequency]]="Semi-annual",2,Table1[[#This Row],[Coupon frequency]]="Quarterly",4,Table1[[#This Row],[Coupon frequency]]="Annual",1,Table1[[#This Row],[Coupon frequency]]="Every 4 months",3,Table1[[#This Row],[Coupon frequency]]="Monthly",12)} -> 1 | U20: =Table1[[#This Row],[Term to Maturity (Years)]]*Table1[[#This Row],[Coupon Frequency2]] -> 3 | V20: =Table1[[#This Row],[Face value]]*Table1[[#This Row],[Current coupon %]] -> 76 | W20: =RATE(Table1[[#This Row],[Total No. of Coupons]],Table1[[#This Row],[Coupon Amount]],-Table1[[#This Row],[Ask Price]],Table1[[#This Row],[Face value]]) -> 0.054877535 | X20: =Table1[[#This Row],[IRR]]*Table1[[#This Row],[Coupon Frequency2]] -> 0.054877535 | Y20: {=_xlfn.IFS(Table1[[#This Row],[Yield (Annualised)]]<0.05,1,Table1[[#This Row],[Yield (Annualised)]]<0.1,2,Table1[[#This Row],[Yield (Annualised)]]<0.15,3,Table1[[#This Row],[Yield (Annualised)]]<0.2,4,Table1[[#This Row],[Yield (Annualised)]]<0.25,5,Table1[[#This Row],[Yield (Annualised)]]<0.3,6,Table1[[#This Row],[Yield (Annualised)]]<0.35,7,Table1[[#This Row],[Yield (Annualised)]]<0.4,8,Table1[[#This Row],[Yield (Annualised)]]<0.45,9,Table1[[#This Row],[Yield (Annualised)]]<0.5,10,Table1[[#This Row],[Yield (Annualised)]]<0.55,11,Table1[[#This Row],[Yield (Annualised)]]<0.6,12,Table1[[#This Row],[Yield (Annualised)]]<0.65,13,Table1[[#This Row],[Yield (Annualised)]]<0.7,14,Table1[[#This Row],[Yield (Annualised)]]>0.7,15)} -> 2 | Z20: =DURATION(Table1[[#This Row],[Issue date]],Table1[[#This Row],[Maturity date]],Table1[[#This Row],[Current coupon %]],Table1[[#This Row],[Yield (Annualised)]],Table1[[#This Row],[Coupon Frequency2]]) -> 2.7990626 | AA20: =Table1[[#This Row],[Macaulay Duration in Years]]/(1+Table1[[#This Row],[IRR]]) -> 2.653448 | AB20: =VLOOKUP(Table1[[#This Row],[Yield Cluster]],'Cluster Details'!$B$3:$C$16,2,0) -> 0.078548802 | AC20: =PRICE(Table1[[#This Row],[Issue date]],Table1[[#This Row],[Maturity date]],Table1[[#This Row],[Current coupon %]],Table1[[#This Row],[Average Cluster Yield]],100,Table1[[#This Row],[Coupon Frequency2]])*Table1[[#This Row],[Face value]]/100 -> 993.41425 | AD20: =IF(Table1[[#This Row],[Ask Price]]>Table1[[#This Row],[Calculated Bond Price]],"Rich","Cheap") -> Rich | AE20: =PRICE(Table1[[#This Row],[Issue date]],Table1[[#This Row],[Maturity date]],Table1[[#This Row],[Current coupon %]],Table1[[#This Row],[Yield (Annualised)]]+$AF$2,100,Table1[[#This Row],[Coupon Frequency2]])*Table1[[#This Row],[Face value]]/100 -> 1029.4642 | AF20: =PRICE(Table1[[#This Row],[Issue date]],Table1[[#This Row],[Maturity date]],Table1[[#This Row],[Current coupon %]],Table1[[#This Row],[Yield (Annualised)]]-$AF$2,100,Table1[[#This Row],[Coupon Frequency2]])*Table1[[#This Row],[Face value]]/100 -> 1085.5743 | AG20: =(Table1[[#This Row],[P (+ shock)]]+Table1[[#This Row],[P (-shock)]]-2*Table1[[#This Row],[Ask Price]])/(2*Table1[[#This Row],[Ask Price]]*($AF$2^2)) -> 4.9125785 | AH20: 8.4053452 | AI20: =(L20*F20)/H20 -> 0.071901608 | AK20: =RATE(Table1[[#This Row],[Total No. of Coupons]],Table1[[#This Row],[Coupon Amount]],-Table1[[#This Row],[Ask Price]],Table1[[#This Row],[Face value]]) -> 0.054877535 | AL20: =Table1[[#This Row],[IRR]]*Table1[[#This Row],[Coupon Frequency2]] -> 0.054877535 | AM20: =-AA20*H20 -> -2804.6945 | AN20: None | AO20: India | AP20: =_xlfn.SWITCH(PROPER(TRIM(M20)), "Annual",1, "Semi-Annual",2, "Quarterly",4, "Monthly",12, "") -> 1
A21: 837REC33 | B21: REC Limited 8.37% 24-SEP-2033 | C21: Corporate | D21: 41541 | E21: 48846 | F21: 1000 | G21: INR | H21: 1340 | I21: INR | J21: 134 | K21: 3 | L21: 0.0837 | M21: Annual | N21: 2929 | O21: 6.2462687 | R21: BSE | S21: =ROUND(YEARFRAC(D21,E21),0) -> 20 | T21: {=_xlfn.IFS(Table1[[#This Row],[Coupon frequency]]="Semi-annual",2,Table1[[#This Row],[Coupon frequency]]="Quarterly",4,Table1[[#This Row],[Coupon frequency]]="Annual",1,Table1[[#This Row],[Coupon frequency]]="Every 4 months",3,Table1[[#This Row],[Coupon frequency]]="Monthly",12)} -> 1 | U21: =Table1[[#This Row],[Term to Maturity (Years)]]*Table1[[#This Row],[Coupon Frequency2]] -> 20 | V21: =Table1[[#This Row],[Face value]]*Table1[[#This Row],[Current coupon %]] -> 83.7 | W21: =RATE(Table1[[#This Row],[Total No. of Coupons]],Table1[[#This Row],[Coupon Amount]],-Table1[[#This Row],[Ask Price]],Table1[[#This Row],[Face value]]) -> 0.055201456 | X21: =Table1[[#This Row],[IRR]]*Table1[[#This Row],[Coupon Frequency2]] -> 0.055201456 | Y21: {=_xlfn.IFS(Table1[[#This Row],[Yield (Annualised)]]<0.05,1,Table1[[#This Row],[Yield (Annualised)]]<0.1,2,Table1[[#This Row],[Yield (Annualised)]]<0.15,3,Table1[[#This Row],[Yield (Annualised)]]<0.2,4,Table1[[#This Row],[Yield (Annualised)]]<0.25,5,Table1[[#This Row],[Yield (Annualised)]]<0.3,6,Table1[[#This Row],[Yield (Annualised)]]<0.35,7,Table1[[#This Row],[Yield (Annualised)]]<0.4,8,Table1[[#This Row],[Yield (Annualised)]]<0.45,9,Table1[[#This Row],[Yield (Annualised)]]<0.5,10,Table1[[#This Row],[Yield (Annualised)]]<0.55,11,Table1[[#This Row],[Yield (Annualised)]]<0.6,12,Table1[[#This Row],[Yield (Annualised)]]<0.65,13,Table1[[#This Row],[Yield (Annualised)]]<0.7,14,Table1[[#This Row],[Yield (Annualised)]]>0.7,15)} -> 2 | Z21: =DURATION(Table1[[#This Row],[Issue date]],Table1[[#This Row],[Maturity date]],Table1[[#This Row],[Current coupon %]],Table1[[#This Row],[Yield (Annualised)]],Table1[[#This Row],[Coupon Frequency2]]) -> 11.614166 | AA21: =Table1[[#This Row],[Macaulay Duration in Years]]/(1+Table1[[#This Row],[IRR]]) -> 11.006586 | AB21: =VLOOKUP(Table1[[#This Row],[Yield Cluster]],'Cluster Details'!$B$3:$C$16,2,0) -> 0.078548802 | AC21: =PRICE(Table1[[#This Row],[Issue date]],Table1[[#This Row],[Maturity date]],Table1[[#This Row],[Current coupon %]],Table1[[#This Row],[Average Cluster Yield]],100,Table1[[#This Row],[Coupon Frequency2]])*Table1[[#This Row],[Face value]]/100 -> 1051.1261 | AD21: =IF(Table1[[#This Row],[Ask Price]]>Table1[[#This Row],[Calculated Bond Price]],"Rich","Cheap") -> Rich | AE21: =PRICE(Table1[[#This Row],[Issue date]],Table1[[#This Row],[Maturity date]],Table1[[#This Row],[Current coupon %]],Table1[[#This Row],[Yield (Annualised)]]+$AF$2,100,Table1[[#This Row],[Coupon Frequency2]])*Table1[[#This Row],[Face value]]/100 -> 1203.5006 | AF21: =PRICE(Table1[[#This Row],[Issue date]],Table1[[#This Row],[Maturity date]],Table1[[#This Row],[Current coupon %]],Table1[[#This Row],[Yield (Annualised)]]-$AF$2,100,Table1[[#This Row],[Coupon Frequency2]])*Table1[[#This Row],[Face value]]/100 -> 1499.9136 | AG21: =(Table1[[#This Row],[P (+ shock)]]+Table1[[#This Row],[P (-shock)]]-2*Table1[[#This Row],[Ask Price]])/(2*Table1[[#This Row],[Ask Price]]*($AF$2^2)) -> 87.366239 | AH21: 13.418656 | AI21: =(L21*F21)/H21 -> 0.062462687 | AK21: =RATE(Table1[[#This Row],[Total No. of Coupons]],Table1[[#This Row],[Coupon Amount]],-Table1[[#This Row],[Ask Price]],Table1[[#This Row],[Face value]]) -> 0.055201456 | AL21: =Table1[[#This Row],[IRR]]*Table1[[#This Row],[Coupon Frequency2]] -> 0.055201456 | AM21: =-AA21*H21 -> -14748.825 | AN21: None | AO21: India | AP21: =_xlfn.SWITCH(PROPER(TRIM(M21)), "Annual",1, "Semi-Annual",2, "Quarterly",4, "Monthly",12, "") -> 1
A22: 743REC35 | B22: REC Limited 7.43% 05-NOV-2035 | C22: Corporate | D22: 42313 | E22: 49618 | F22: 1000 | G22: INR | H22: 1224 | I22: INR | J22: 122.4 | K22: 20 | L22: 0.0743 | M22: Annual | N22: 3701 | O22: 6.0702614 | R22: BSE | S22: =ROUND(YEARFRAC(D22,E22),0) -> 20 | T22: {=_xlfn.IFS(Table1[[#This Row],[Coupon frequency]]="Semi-annual",2,Table1[[#This Row],[Coupon frequency]]="Quarterly",4,Table1[[#This Row],[Coupon frequency]]="Annual",1,Table1[[#This Row],[Coupon frequency]]="Every 4 months",3,Table1[[#This Row],[Coupon frequency]]="Monthly",12)} -> 1 | U22: =Table1[[#This Row],[Term to Maturity (Years)]]*Table1[[#This Row],[Coupon Frequency2]] -> 20 | V22: =Table1[[#This Row],[Face value]]*Table1[[#This Row],[Current coupon %]] -> 74.3 | W22: =RATE(Table1[[#This Row],[Total No. of Coupons]],Table1[[#This Row],[Coupon Amount]],-Table1[[#This Row],[Ask Price]],Table1[[#This Row],[Face value]]) -> 0.055480963 | X22: =Table1[[#This Row],[IRR]]*Table1[[#This Row],[Coupon Frequency2]] -> 0.055480963 | Y22: {=_xlfn.IFS(Table1[[#This Row],[Yield (Annualised)]]<0.05,1,Table1[[#This Row],[Yield (Annualised)]]<0.1,2,Table1[[#This Row],[Yield (Annualised)]]<0.15,3,Table1[[#This Row],[Yield (Annualised)]]<0.2,4,Table1[[#This Row],[Yield (Annualised)]]<0.25,5,Table1[[#This Row],[Yield (Annualised)]]<0.3,6,Table1[[#This Row],[Yield (Annualised)]]<0.35,7,Table1[[#This Row],[Yield (Annualised)]]<0.4,8,Table1[[#This Row],[Yield (Annualised)]]<0.45,9,Table1[[#This Row],[Yield (Annualised)]]<0.5,10,Table1[[#This Row],[Yield (Annualised)]]<0.55,11,Table1[[#This Row],[Yield (Annualised)]]<0.6,12,Table1[[#This Row],[Yield (Annualised)]]<0.65,13,Table1[[#This Row],[Yield (Annualised)]]<0.7,14,Table1[[#This Row],[Yield (Annualised)]]>0.7,15)} -> 2 | Z22: =DURATION(Table1[[#This Row],[Issue date]],Table1[[#This Row],[Maturity date]],Table1[[#This Row],[Current coupon %]],Table1[[#This Row],[Yield (Annualised)]],Table1[[#This Row],[Coupon Frequency2]]) -> 11.863301 | AA22: =Table1[[#This Row],[Macaulay Duration in Years]]/(1+Table1[[#This Row],[IRR]]) -> 11.239711 | AB22: =VLOOKUP(Table1[[#This Row],[Yield Cluster]],'Cluster Details'!$B$3:$C$16,2,0) -> 0.078548802 | AC22: =PRICE(Table1[[#This Row],[Issue date]],Table1[[#This Row],[Maturity date]],Table1[[#This Row],[Current coupon %]],Table1[[#This Row],[Average Cluster Yield]],100,Table1[[#This Row],[Coupon Frequency2]])*Table1[[#This Row],[Face value]]/100 -> 957.83027 | AD22: =IF(Table1[[#This Row],[Ask Price]]>Table1[[#This Row],[Calculated Bond Price]],"Rich","Cheap") -> Rich | AE22: =PRICE(Table1[[#This Row],[Issue date]],Table1[[#This Row],[Maturity date]],Table1[[#This Row],[Current coupon %]],Table1[[#This Row],[Yield (Annualised)]]+$AF$2,100,Table1[[#This Row],[Coupon Frequency2]])*Table1[[#This Row],[Face value]]/100 -> 1096.8025 | AF22: =PRICE(Table1[[#This Row],[Issue date]],Table1[[#This Row],[Maturity date]],Table1[[#This Row],[Current coupon %]],Table1[[#This Row],[Yield (Annualised)]]-$AF$2,100,Table1[[#This Row],[Coupon Frequency2]])*Table1[[#This Row],[Face value]]/100 -> 1373.3187 | AG22: =(Table1[[#This Row],[P (+ shock)]]+Table1[[#This Row],[P (-shock)]]-2*Table1[[#This Row],[Ask Price]])/(2*Table1[[#This Row],[Ask Price]]*($AF$2^2)) -> 90.364487 | AH22: 12.476326 | AI22: =(L22*F22)/H22 -> 0.060702614 | AK22: =RATE(Table1[[#This Row],[Total No. of Coupons]],Table1[[#This Row],[Coupon Amount]],-Table1[[#This Row],[Ask Price]],Table1[[#This Row],[Face value]]) -> 0.055480963 | AL22: =Table1[[#This Row],[IRR]]*Table1[[#This Row],[Coupon Frequency2]] -> 0.055480963 | AM22: =-AA22*H22 -> -13757.406 | AN22: None | AO22: India | AP22: =_xlfn.SWITCH(PROPER(TRIM(M22)), "Annual",1, "Semi-Annual",2, "Quarterly",4, "Monthly",12, "") -> 1
A23: 965SCL25A | B23: Sammaan Capital Limited 9.65% 09-NOV-2025 | C23: Corporate | D23: 45239 | E23: 45970 | F23: 1000 | G23: INR | H23: 1075 | I23: INR | J23: 107.5 | K23: 50 | L23: 0.0965 | M23: Annual | N23: 53 | O23: 8.9767442 | P23: B+ | R23: BSE | S23: =ROUND(YEARFRAC(D23,E23),0) -> 2 | T23: {=_xlfn.IFS(Table1[[#This Row],[Coupon frequency]]="Semi-annual",2,Table1[[#This Row],[Coupon frequency]]="Quarterly",4,Table1[[#This Row],[Coupon frequency]]="Annual",1,Table1[[#This Row],[Coupon frequency]]="Every 4 months",3,Table1[[#This Row],[Coupon frequency]]="Monthly",12)} -> 1 | U23: =Table1[[#This Row],[Term to Maturity (Years)]]*Table1[[#This Row],[Coupon Frequency2]] -> 2 | V23: =Table1[[#This Row],[Face value]]*Table1[[#This Row],[Current coupon %]] -> 96.5 | W23: =RATE(Table1[[#This Row],[Total No. of Coupons]],Table1[[#This Row],[Coupon Amount]],-Table1[[#This Row],[Ask Price]],Table1[[#This Row],[Face value]]) -> 0.055831073 | X23: =Table1[[#This Row],[IRR]]*Table1[[#This Row],[Coupon Frequency2]] -> 0.055831073 | Y23: {=_xlfn.IFS(Table1[[#This Row],[Yield (Annualised)]]<0.05,1,Table1[[#This Row],[Yield (Annualised)]]<0.1,2,Table1[[#This Row],[Yield (Annualised)]]<0.15,3,Table1[[#This Row],[Yield (Annualised)]]<0.2,4,Table1[[#This Row],[Yield (Annualised)]]<0.25,5,Table1[[#This Row],[Yield (Annualised)]]<0.3,6,Table1[[#This Row],[Yield (Annualised)]]<0.35,7,Table1[[#This Row],[Yield (Annualised)]]<0.4,8,Table1[[#This Row],[Yield (Annualised)]]<0.45,9,Table1[[#This Row],[Yield (Annualised)]]<0.5,10,Table1[[#This Row],[Yield (Annualised)]]<0.55,11,Table1[[#This Row],[Yield (Annualised)]]<0.6,12,Table1[[#This Row],[Yield (Annualised)]]<0.65,13,Table1[[#This Row],[Yield (Annualised)]]<0.7,14,Table1[[#This Row],[Yield (Annualised)]]>0.7,15)} -> 2 | Z23: =DURATION(Table1[[#This Row],[Issue date]],Table1[[#This Row],[Maturity date]],Table1[[#This Row],[Current coupon %]],Table1[[#This Row],[Yield (Annualised)]],Table1[[#This Row],[Coupon Frequency2]]) -> 1.9149794 | AA23: =Table1[[#This Row],[Macaulay Duration in Years]]/(1+Table1[[#This Row],[IRR]]) -> 1.8137176 | AB23: =VLOOKUP(Table1[[#This Row],[Yield Cluster]],'Cluster Details'!$B$3:$C$16,2,0) -> 0.078548802 | AC23: =PRICE(Table1[[#This Row],[Issue date]],Table1[[#This Row],[Maturity date]],Table1[[#This Row],[Current coupon %]],Table1[[#This Row],[Average Cluster Yield]],100,Table1[[#This Row],[Coupon Frequency2]])*Table1[[#This Row],[Face value]]/100 -> 1032.0755 | AD23: =IF(Table1[[#This Row],[Ask Price]]>Table1[[#This Row],[Calculated Bond Price]],"Rich","Cheap") -> Rich | AE23: =PRICE(Table1[[#This Row],[Issue date]],Table1[[#This Row],[Maturity date]],Table1[[#This Row],[Current coupon %]],Table1[[#This Row],[Yield (Annualised)]]+$AF$2,100,Table1[[#This Row],[Coupon Frequency2]])*Table1[[#This Row],[Face value]]/100 -> 1055.7721 | AF23: =PRICE(Table1[[#This Row],[Issue date]],Table1[[#This Row],[Maturity date]],Table1[[#This Row],[Current coupon %]],Table1[[#This Row],[Yield (Annualised)]]-$AF$2,100,Table1[[#This Row],[Coupon Frequency2]])*Table1[[#This Row],[Face value]]/100 -> 1094.7738 | AG23: =(Table1[[#This Row],[P (+ shock)]]+Table1[[#This Row],[P (-shock)]]-2*Table1[[#This Row],[Ask Price]])/(2*Table1[[#This Row],[Ask Price]]*($AF$2^2)) -> 2.5389572 | AH23: 22.086306 | AI23: =(L23*F23)/H23 -> 0.089767442 | AK23: =RATE(Table1[[#This Row],[Total No. of Coupons]],Table1[[#This Row],[Coupon Amount]],-Table1[[#This Row],[Ask Price]],Table1[[#This Row],[Face value]]) -> 0.055831073 | AL23: =Table1[[#This Row],[IRR]]*Table1[[#This Row],[Coupon Frequency2]] -> 0.055831073 | AM23: =-AA23*H23 -> -1949.7464 | AN23: None | AO23: India | AP23: =_xlfn.SWITCH(PROPER(TRIM(M23)), "Annual",1, "Semi-Annual",2, "Quarterly",4, "Monthly",12, "") -> 1
A24: 760PFCL35 | B24: Power Finance Corporation Limited 7.6% 17-OCT-2035 | C24: Corporate | D24: 42294 | E24: 49599 | F24: 1000 | G24: INR | H24: 1237.85 | I24: INR | J24: 123.785 | K24: 70 | L24: 0.076 | M24: Annual | N24: 3682 | O24: 6.1396777 | P24: NR | R24: BSE | S24: =ROUND(YEARFRAC(D24,E24),0) -> 20 | T24: {=_xlfn.IFS(Table1[[#This Row],[Coupon frequency]]="Semi-annual",2,Table1[[#This Row],[Coupon frequency]]="Quarterly",4,Table1[[#This Row],[Coupon frequency]]="Annual",1,Table1[[#This Row],[Coupon frequency]]="Every 4 months",3,Table1[[#This Row],[Coupon frequency]]="Monthly",12)} -> 1 | U24: =Table1[[#This Row],[Term to Maturity (Years)]]*Table1[[#This Row],[Coupon Frequency2]] -> 20 | V24: =Table1[[#This Row],[Face value]]*Table1[[#This Row],[Current coupon %]] -> 76 | W24: =RATE(Table1[[#This Row],[Total No. of Coupons]],Table1[[#This Row],[Coupon Amount]],-Table1[[#This Row],[Ask Price]],Table1[[#This Row],[Face value]]) -> 0.055941169 | X24: =Table1[[#This Row],[IRR]]*Table1[[#This Row],[Coupon Frequency2]] -> 0.055941169 | Y24: {=_xlfn.IFS(Table1[[#This Row],[Yield (Annualised)]]<0.05,1,Table1[[#This Row],[Yield (Annualised)]]<0.1,2,Table1[[#This Row],[Yield (Annualised)]]<0.15,3,Table1[[#This Row],[Yield (Annualised)]]<0.2,4,Table1[[#This Row],[Yield (Annualised)]]<0.25,5,Table1[[#This Row],[Yield (Annualised)]]<0.3,6,Table1[[#This Row],[Yield (Annualised)]]<0.35,7,Table1[[#This Row],[Yield (Annualised)]]<0.4,8,Table1[[#This Row],[Yield (Annualised)]]<0.45,9,Table1[[#This Row],[Yield (Annualised)]]<0.5,10,Table1[[#This Row],[Yield (Annualised)]]<0.55,11,Table1[[#This Row],[Yield (Annualised)]]<0.6,12,Table1[[#This Row],[Yield (Annualised)]]<0.65,13,Table1[[#This Row],[Yield (Annualised)]]<0.7,14,Table1[[#This Row],[Yield (Annualised)]]>0.7,15)} -> 2 | Z24: =DURATION(Table1[[#This Row],[Issue date]],Table1[[#This Row],[Maturity date]],Table1[[#This Row],[Current coupon %]],Table1[[#This Row],[Yield (Annualised)]],Table1[[#This Row],[Coupon Frequency2]]) -> 11.791562 | AA24: =Table1[[#This Row],[Macaulay Duration in Years]]/(1+Table1[[#This Row],[IRR]]) -> 11.166874 | AB24: =VLOOKUP(Table1[[#This Row],[Yield Cluster]],'Cluster Details'!$B$3:$C$16,2,0) -> 0.078548802 | AC24: =PRICE(Table1[[#This Row],[Issue date]],Table1[[#This Row],[Maturity date]],Table1[[#This Row],[Current coupon %]],Table1[[#This Row],[Average Cluster Yield]],100,Table1[[#This Row],[Coupon Frequency2]])*Table1[[#This Row],[Face value]]/100 -> 974.70292 | AD24: =IF(Table1[[#This Row],[Ask Price]]>Table1[[#This Row],[Calculated Bond Price]],"Rich","Cheap") -> Rich | AE24: =PRICE(Table1[[#This Row],[Issue date]],Table1[[#This Row],[Maturity date]],Table1[[#This Row],[Current coupon %]],Table1[[#This Row],[Yield (Annualised)]]+$AF$2,100,Table1[[#This Row],[Coupon Frequency2]])*Table1[[#This Row],[Face value]]/100 -> 1110.0095 | AF24: =PRICE(Table1[[#This Row],[Issue date]],Table1[[#This Row],[Maturity date]],Table1[[#This Row],[Current coupon %]],Table1[[#This Row],[Yield (Annualised)]]-$AF$2,100,Table1[[#This Row],[Coupon Frequency2]])*Table1[[#This Row],[Face value]]/100 -> 1387.834 | AG24: =(Table1[[#This Row],[P (+ shock)]]+Table1[[#This Row],[P (-shock)]]-2*Table1[[#This Row],[Ask Price]])/(2*Table1[[#This Row],[Ask Price]]*($AF$2^2)) -> 89.443452 | AH24: 12.102345 | AI24: =(L24*F24)/H24 -> 0.061396777 | AK24: =RATE(Table1[[#This Row],[Total No. of Coupons]],Table1[[#This Row],[Coupon Amount]],-Table1[[#This Row],[Ask Price]],Table1[[#This Row],[Face value]]) -> 0.055941169 | AL24: =Table1[[#This Row],[IRR]]*Table1[[#This Row],[Coupon Frequency2]] -> 0.055941169 | AM24: =-AA24*H24 -> -13822.915 | AN24: None | AO24: India | AP24: =_xlfn.SWITCH(PROPER(TRIM(M24)), "Annual",1, "Semi-Annual",2, "Quarterly",4, "Monthly",12, "") -> 1
A25: 718REC35 | B25: REC Limited 7.18% 05-NOV-2035 | C25: Corporate | D25: 42313 | E25: 49618 | F25: 1000 | G25: INR | H25: 1186 | I25: INR | J25: 118.6 | K25: 2000 | L25: 0.0718 | M25: Annual | N25: 3701 | O25: 6.0539629 | R25: BSE | S25: =ROUND(YEARFRAC(D25,E25),0) -> 20 | T25: {=_xlfn.IFS(Table1[[#This Row],[Coupon frequency]]="Semi-annual",2,Table1[[#This Row],[Coupon frequency]]="Quarterly",4,Table1[[#This Row],[Coupon frequency]]="Annual",1,Table1[[#This Row],[Coupon frequency]]="Every 4 months",3,Table1[[#This Row],[Coupon frequency]]="Monthly",12)} -> 1 | U25: =Table1[[#This Row],[Term to Maturity (Years)]]*Table1[[#This Row],[Coupon Frequency2]] -> 20 | V25: =Table1[[#This Row],[Face value]]*Table1[[#This Row],[Current coupon %]] -> 71.8 | W25: =RATE(Table1[[#This Row],[Total No. of Coupons]],Table1[[#This Row],[Coupon Amount]],-Table1[[#This Row],[Ask Price]],Table1[[#This Row],[Face value]]) -> 0.056094062 | X25: =Table1[[#This Row],[IRR]]*Table1[[#This Row],[Coupon Frequency2]] -> 0.056094062 | Y25: {=_xlfn.IFS(Table1[[#This Row],[Yield (Annualised)]]<0.05,1,Table1[[#This Row],[Yield (Annualised)]]<0.1,2,Table1[[#This Row],[Yield (Annualised)]]<0.15,3,Table1[[#This Row],[Yield (Annualised)]]<0.2,4,Table1[[#This Row],[Yield (Annualised)]]<0.25,5,Table1[[#This Row],[Yield (Annualised)]]<0.3,6,Table1[[#This Row],[Yield (Annualised)]]<0.35,7,Table1[[#This Row],[Yield (Annualised)]]<0.4,8,Table1[[#This Row],[Yield (Annualised)]]<0.45,9,Table1[[#This Row],[Yield (Annualised)]]<0.5,10,Table1[[#This Row],[Yield (Annualised)]]<0.55,11,Table1[[#This Row],[Yield (Annualised)]]<0.6,12,Table1[[#This Row],[Yield (Annualised)]]<0.65,13,Table1[[#This Row],[Yield (Annualised)]]<0.7,14,Table1[[#This Row],[Yield (Annualised)]]>0.7,15)} -> 2 | Z25: =DURATION(Table1[[#This Row],[Issue date]],Table1[[#This Row],[Maturity date]],Table1[[#This Row],[Current coupon %]],Table1[[#This Row],[Yield (Annualised)]],Table1[[#This Row],[Coupon Frequency2]]) -> 11.913118 | AA25: =Table1[[#This Row],[Macaulay Duration in Years]]/(1+Table1[[#This Row],[IRR]]) -> 11.280357 | AB25: =VLOOKUP(Table1[[#This Row],[Yield Cluster]],'Cluster Details'!$B$3:$C$16,2,0) -> 0.078548802 | AC25: =PRICE(Table1[[#This Row],[Issue date]],Table1[[#This Row],[Maturity date]],Table1[[#This Row],[Current coupon %]],Table1[[#This Row],[Average Cluster Yield]],100,Table1[[#This Row],[Coupon Frequency2]])*Table1[[#This Row],[Face value]]/100 -> 933.01754 | AD25: =IF(Table1[[#This Row],[Ask Price]]>Table1[[#This Row],[Calculated Bond Price]],"Rich","Cheap") -> Rich | AE25: =PRICE(Table1[[#This Row],[Issue date]],Table1[[#This Row],[Maturity date]],Table1[[#This Row],[Current coupon %]],Table1[[#This Row],[Yield (Annualised)]]+$AF$2,100,Table1[[#This Row],[Coupon Frequency2]])*Table1[[#This Row],[Face value]]/100 -> 1062.3282 | AF25: =PRICE(Table1[[#This Row],[Issue date]],Table1[[#This Row],[Maturity date]],Table1[[#This Row],[Current coupon %]],Table1[[#This Row],[Yield (Annualised)]]-$AF$2,100,Table1[[#This Row],[Coupon Frequency2]])*Table1[[#This Row],[Face value]]/100 -> 1331.2336 | AG25: =(Table1[[#This Row],[P (+ shock)]]+Table1[[#This Row],[P (-shock)]]-2*Table1[[#This Row],[Ask Price]])/(2*Table1[[#This Row],[Ask Price]]*($AF$2^2)) -> 90.901525 | AH25: -29.629328 | AI25: =(L25*F25)/H25 -> 0.060539629 | AK25: =RATE(Table1[[#This Row],[Total No. of Coupons]],Table1[[#This Row],[Coupon Amount]],-Table1[[#This Row],[Ask Price]],Table1[[#This Row],[Face value]]) -> 0.056094062 | AL25: =Table1[[#This Row],[IRR]]*Table1[[#This Row],[Coupon Frequency2]] -> 0.056094062 | AM25: =-AA25*H25 -> -13378.504 | AN25: None | AO25: India | AP25: =_xlfn.SWITCH(PROPER(TRIM(M25)), "Annual",1, "Semi-Annual",2, "Quarterly",4, "Monthly",12, "") -> 1
A26: 750IRFC35 | B26: Indian Railway Finance Corporation Limited 7.5% 21-DEC-2035 | C26: Corporate | D26: 42359 | E26: 49664 | F26: 1000 | G26: INR | H26: 1218 | I26: INR | J26: 121.8 | K26: 300 | L26: 0.075 | M26: Annual | N26: 3747 | O26: 6.1576355 | P26: BBB | R26: BSE | S26: =ROUND(YEARFRAC(D26,E26),0) -> 20 | T26: {=_xlfn.IFS(Table1[[#This Row],[Coupon frequency]]="Semi-annual",2,Table1[[#This Row],[Coupon frequency]]="Quarterly",4,Table1[[#This Row],[Coupon frequency]]="Annual",1,Table1[[#This Row],[Coupon frequency]]="Every 4 months",3,Table1[[#This Row],[Coupon frequency]]="Monthly",12)} -> 1 | U26: =Table1[[#This Row],[Term to Maturity (Years)]]*Table1[[#This Row],[Coupon Frequency2]] -> 20 | V26: =Table1[[#This Row],[Face value]]*Table1[[#This Row],[Current coupon %]] -> 75 | W26: =RATE(Table1[[#This Row],[Total No. of Coupons]],Table1[[#This Row],[Coupon Amount]],-Table1[[#This Row],[Ask Price]],Table1[[#This Row],[Face value]]) -> 0.056526221 | X26: =Table1[[#This Row],[IRR]]*Table1[[#This Row],[Coupon Frequency2]] -> 0.056526221 | Y26: {=_xlfn.IFS(Table1[[#This Row],[Yield (Annualised)]]<0.05,1,Table1[[#This Row],[Yield (Annualised)]]<0.1,2,Table1[[#This Row],[Yield (Annualised)]]<0.15,3,Table1[[#This Row],[Yield (Annualised)]]<0.2,4,Table1[[#This Row],[Yield (Annualised)]]<0.25,5,Table1[[#This Row],[Yield (Annualised)]]<0.3,6,Table1[[#This Row],[Yield (Annualised)]]<0.35,7,Table1[[#This Row],[Yield (Annualised)]]<0.4,8,Table1[[#This Row],[Yield (Annualised)]]<0.45,9,Table1[[#This Row],[Yield (Annualised)]]<0.5,10,Table1[[#This Row],[Yield (Annualised)]]<0.55,11,Table1[[#This Row],[Yield (Annualised)]]<0.6,12,Table1[[#This Row],[Yield (Annualised)]]<0.65,13,Table1[[#This Row],[Yield (Annualised)]]<0.7,14,Table1[[#This Row],[Yield (Annualised)]]>0.7,15)} -> 2 | Z26: =DURATION(Table1[[#This Row],[Issue date]],Table1[[#This Row],[Maturity date]],Table1[[#This Row],[Current coupon %]],Table1[[#This Row],[Yield (Annualised)]],Table1[[#This Row],[Coupon Frequency2]]) -> 11.794588 | AA26: =Table1[[#This Row],[Macaulay Duration in Years]]/(1+Table1[[#This Row],[IRR]]) -> 11.163554 | AB26: =VLOOKUP(Table1[[#This Row],[Yield Cluster]],'Cluster Details'!$B$3:$C$16,2,0) -> 0.078548802 | AC26: =PRICE(Table1[[#This Row],[Issue date]],Table1[[#This Row],[Maturity date]],Table1[[#This Row],[Current coupon %]],Table1[[#This Row],[Average Cluster Yield]],100,Table1[[#This Row],[Coupon Frequency2]])*Table1[[#This Row],[Face value]]/100 -> 964.77783 | AD26: =IF(Table1[[#This Row],[Ask Price]]>Table1[[#This Row],[Calculated Bond Price]],"Rich","Cheap") -> Rich | AE26: =PRICE(Table1[[#This Row],[Issue date]],Table1[[#This Row],[Maturity date]],Table1[[#This Row],[Current coupon %]],Table1[[#This Row],[Yield (Annualised)]]+$AF$2,100,Table1[[#This Row],[Coupon Frequency2]])*Table1[[#This Row],[Face value]]/100 -> 1092.247 | AF26: =PRICE(Table1[[#This Row],[Issue date]],Table1[[#This Row],[Maturity date]],Table1[[#This Row],[Current coupon %]],Table1[[#This Row],[Yield (Annualised)]]-$AF$2,100,Table1[[#This Row],[Coupon Frequency2]])*Table1[[#This Row],[Face value]]/100 -> 1365.535 | AG26: =(Table1[[#This Row],[P (+ shock)]]+Table1[[#This Row],[P (-shock)]]-2*Table1[[#This Row],[Ask Price]])/(2*Table1[[#This Row],[Ask Price]]*($AF$2^2)) -> 89.417216 | AI26: =(L26*F26)/H26 -> 0.061576355 | AK26: =RATE(Table1[[#This Row],[Total No. of Coupons]],Table1[[#This Row],[Coupon Amount]],-Table1[[#This Row],[Ask Price]],Table1[[#This Row],[Face value]]) -> 0.056526221 | AL26: =Table1[[#This Row],[IRR]]*Table1[[#This Row],[Coupon Frequency2]] -> 0.056526221 | AM26: =-AA26*H26 -> -13597.209 | AN26: None | AO26: India | AP26: =_xlfn.SWITCH(PROPER(TRIM(M26)), "Annual",1, "Semi-Annual",2, "Quarterly",4, "Monthly",12, "") -> 1
A27: 94MFCL26 | B27: Muthoot Fincorp Ltd. 9.4% 30-OCT-2026 | C27: Corporate | D27: 45595 | E27: 46325 | F27: 1000 | G27: INR | H27: 1069 | I27: INR | J27: 106.9 | K27: 2179 | L27: 0.094 | M27: Annual | N27: 408 | O27: 8.7932647 | R27: BSE | S27: =ROUND(YEARFRAC(D27,E27),0) -> 2 | T27: {=_xlfn.IFS(Table1[[#This Row],[Coupon frequency]]="Semi-annual",2,Table1[[#This Row],[Coupon frequency]]="Quarterly",4,Table1[[#This Row],[Coupon frequency]]="Annual",1,Table1[[#This Row],[Coupon frequency]]="Every 4 months",3,Table1[[#This Row],[Coupon frequency]]="Monthly",12)} -> 1 | U27: =Table1[[#This Row],[Term to Maturity (Years)]]*Table1[[#This Row],[Coupon Frequency2]] -> 2 | V27: =Table1[[#This Row],[Face value]]*Table1[[#This Row],[Current coupon %]] -> 94 | W27: =RATE(Table1[[#This Row],[Total No. of Coupons]],Table1[[#This Row],[Coupon Amount]],-Table1[[#This Row],[Ask Price]],Table1[[#This Row],[Face value]]) -> 0.056546878 | X27: =Table1[[#This Row],[IRR]]*Table1[[#This Row],[Coupon Frequency2]] -> 0.056546878 | Y27: {=_xlfn.IFS(Table1[[#This Row],[Yield (Annualised)]]<0.05,1,Table1[[#This Row],[Yield (Annualised)]]<0.1,2,Table1[[#This Row],[Yield (Annualised)]]<0.15,3,Table1[[#This Row],[Yield (Annualised)]]<0.2,4,Table1[[#This Row],[Yield (Annualised)]]<0.25,5,Table1[[#This Row],[Yield (Annualised)]]<0.3,6,Table1[[#This Row],[Yield (Annualised)]]<0.35,7,Table1[[#This Row],[Yield (Annualised)]]<0.4,8,Table1[[#This Row],[Yield (Annualised)]]<0.45,9,Table1[[#This Row],[Yield (Annualised)]]<0.5,10,Table1[[#This Row],[Yield (Annualised)]]<0.55,11,Table1[[#This Row],[Yield (Annualised)]]<0.6,12,Table1[[#This Row],[Yield (Annualised)]]<0.65,13,Table1[[#This Row],[Yield (Annualised)]]<0.7,14,Table1[[#This Row],[Yield (Annualised)]]>0.7,15)} -> 2 | Z27: =DURATION(Table1[[#This Row],[Issue date]],Table1[[#This Row],[Maturity date]],Table1[[#This Row],[Current coupon %]],Table1[[#This Row],[Yield (Annualised)]],Table1[[#This Row],[Coupon Frequency2]]) -> 1.9167735 | AA27: =Table1[[#This Row],[Macaulay Duration in Years]]/(1+Table1[[#This Row],[IRR]]) -> 1.8141869 | AB27: =VLOOKUP(Table1[[#This Row],[Yield Cluster]],'Cluster Details'!$B$3:$C$16,2,0) -> 0.078548802 | AC27: =PRICE(Table1[[#This Row],[Issue date]],Table1[[#This Row],[Maturity date]],Table1[[#This Row],[Current coupon %]],Table1[[#This Row],[Average Cluster Yield]],100,Table1[[#This Row],[Coupon Frequency2]])*Table1[[#This Row],[Face value]]/100 -> 1027.6085 | AD27: =IF(Table1[[#This Row],[Ask Price]]>Table1[[#This Row],[Calculated Bond Price]],"Rich","Cheap") -> Rich | AE27: =PRICE(Table1[[#This Row],[Issue date]],Table1[[#This Row],[Maturity date]],Table1[[#This Row],[Current coupon %]],Table1[[#This Row],[Yield (Annualised)]]+$AF$2,100,Table1[[#This Row],[Coupon Frequency2]])*Table1[[#This Row],[Face value]]/100 -> 1049.8743 | AF27: =PRICE(Table1[[#This Row],[Issue date]],Table1[[#This Row],[Maturity date]],Table1[[#This Row],[Current coupon %]],Table1[[#This Row],[Yield (Annualised)]]-$AF$2,100,Table1[[#This Row],[Coupon Frequency2]])*Table1[[#This Row],[Face value]]/100 -> 1088.6684 | AG27: =(Table1[[#This Row],[P (+ shock)]]+Table1[[#This Row],[P (-shock)]]-2*Table1[[#This Row],[Ask Price]])/(2*Table1[[#This Row],[Ask Price]]*($AF$2^2)) -> 2.5387327 | AH27: 13.108561 | AI27: =(L27*F27)/H27 -> 0.087932647 | AK27: =RATE(Table1[[#This Row],[Total No. of Coupons]],Table1[[#This Row],[Coupon Amount]],-Table1[[#This Row],[Ask Price]],Table1[[#This Row],[Face value]]) -> 0.056546878 | AL27: =Table1[[#This Row],[IRR]]*Table1[[#This Row],[Coupon Frequency2]] -> 0.056546878 | AM27: =-AA27*H27 -> -1939.3658 | AN27: None | AO27: India | AP27: =_xlfn.SWITCH(PROPER(TRIM(M27)), "Annual",1, "Semi-Annual",2, "Quarterly",4, "Monthly",12, "") -> 1
A28: 704IRFC26A | B28: Indian Railway Finance Corporation Limited 7.04% 03-MAR-2026 | C28: Corporate | D28: 42432 | E28: 46084 | F28: 1000000 | G28: INR | H28: 1100874 | I28: INR | J28: 110.0874 | K28: 3 | L28: 0.0704 | M28: Annual | N28: 167 | O28: 6.3949189 | P28: BBB | R28: BSE | S28: =ROUND(YEARFRAC(D28,E28),0) -> 10 | T28: {=_xlfn.IFS(Table1[[#This Row],[Coupon frequency]]="Semi-annual",2,Table1[[#This Row],[Coupon frequency]]="Quarterly",4,Table1[[#This Row],[Coupon frequency]]="Annual",1,Table1[[#This Row],[Coupon frequency]]="Every 4 months",3,Table1[[#This Row],[Coupon frequency]]="Monthly",12)} -> 1 | U28: =Table1[[#This Row],[Term to Maturity (Years)]]*Table1[[#This Row],[Coupon Frequency2]] -> 10 | V28: =Table1[[#This Row],[Face value]]*Table1[[#This Row],[Current coupon %]] -> 70400 | W28: =RATE(Table1[[#This Row],[Total No. of Coupons]],Table1[[#This Row],[Coupon Amount]],-Table1[[#This Row],[Ask Price]],Table1[[#This Row],[Face value]]) -> 0.056895339 | X28: =Table1[[#This Row],[IRR]]*Table1[[#This Row],[Coupon Frequency2]] -> 0.056895339 | Y28: {=_xlfn.IFS(Table1[[#This Row],[Yield (Annualised)]]<0.05,1,Table1[[#This Row],[Yield (Annualised)]]<0.1,2,Table1[[#This Row],[Yield (Annualised)]]<0.15,3,Table1[[#This Row],[Yield (Annualised)]]<0.2,4,Table1[[#This Row],[Yield (Annualised)]]<0.25,5,Table1[[#This Row],[Yield (Annualised)]]<0.3,6,Table1[[#This Row],[Yield (Annualised)]]<0.35,7,Table1[[#This Row],[Yield (Annualised)]]<0.4,8,Table1[[#This Row],[Yield (Annualised)]]<0.45,9,Table1[[#This Row],[Yield (Annualised)]]<0.5,10,Table1[[#This Row],[Yield (Annualised)]]<0.55,11,Table1[[#This Row],[Yield (Annualised)]]<0.6,12,Table1[[#This Row],[Yield (Annualised)]]<0.65,13,Table1[[#This Row],[Yield (Annualised)]]<0.7,14,Table1[[#This Row],[Yield (Annualised)]]>0.7,15)} -> 2 | Z28: =DURATION(Table1[[#This Row],[Issue date]],Table1[[#This Row],[Maturity date]],Table1[[#This Row],[Current coupon %]],Table1[[#This Row],[Yield (Annualised)]],Table1[[#This Row],[Coupon Frequency2]]) -> 7.6335209 | AA28: =Table1[[#This Row],[Macaulay Duration in Years]]/(1+Table1[[#This Row],[IRR]]) -> 7.2225892 | AB28: =VLOOKUP(Table1[[#This Row],[Yield Cluster]],'Cluster Details'!$B$3:$C$16,2,0) -> 0.078548802 | AC28: =PRICE(Table1[[#This Row],[Issue date]],Table1[[#This Row],[Maturity date]],Table1[[#This Row],[Current coupon %]],Table1[[#This Row],[Average Cluster Yield]],100,Table1[[#This Row],[Coupon Frequency2]])*Table1[[#This Row],[Face value]]/100 -> 944961.16 | AD28: =IF(Table1[[#This Row],[Ask Price]]>Table1[[#This Row],[Calculated Bond Price]],"Rich","Cheap") -> Rich | AE28: =PRICE(Table1[[#This Row],[Issue date]],Table1[[#This Row],[Maturity date]],Table1[[#This Row],[Current coupon %]],Table1[[#This Row],[Yield (Annualised)]]+$AF$2,100,Table1[[#This Row],[Coupon Frequency2]])*Table1[[#This Row],[Face value]]/100 -> 1024972.5 | AF28: =PRICE(Table1[[#This Row],[Issue date]],Table1[[#This Row],[Maturity date]],Table1[[#This Row],[Current coupon %]],Table1[[#This Row],[Yield (Annualised)]]-$AF$2,100,Table1[[#This Row],[Coupon Frequency2]])*Table1[[#This Row],[Face value]]/100 -> 1184264.6 | AG28: =(Table1[[#This Row],[P (+ shock)]]+Table1[[#This Row],[P (-shock)]]-2*Table1[[#This Row],[Ask Price]])/(2*Table1[[#This Row],[Ask Price]]*($AF$2^2)) -> 34.014287 | AH28: -29.815757 | AI28: =(L28*F28)/H28 -> 0.063949189 | AK28: =RATE(Table1[[#This Row],[Total No. of Coupons]],Table1[[#This Row],[Coupon Amount]],-Table1[[#This Row],[Ask Price]],Table1[[#This Row],[Face value]]) -> 0.056895339 | AL28: =Table1[[#This Row],[IRR]]*Table1[[#This Row],[Coupon Frequency2]] -> 0.056895339 | AM28: =-AA28*H28 -> -7951160.7 | AN28: None | AO28: India | AP28: =_xlfn.SWITCH(PROPER(TRIM(M28)), "Annual",1, "Semi-Annual",2, "Quarterly",4, "Monthly",12, "") -> 1
A29: 735IRFC31 | B29: Indian Railway Finance Corporation Limited 7.35% 22-MAR-2031 | C29: Corporate | D29: 42451 | E29: 47929 | F29: 1000 | G29: INR | H29: 1161 | I29: INR | J29: 116.1 | K29: 70540 | L29: 0.0735 | M29: Annual | N29: 2012 | O29: 6.3307494 | P29: BBB | R29: BSE | S29: =ROUND(YEARFRAC(D29,E29),0) -> 15 | T29: {=_xlfn.IFS(Table1[[#This Row],[Coupon frequency]]="Semi-annual",2,Table1[[#This Row],[Coupon frequency]]="Quarterly",4,Table1[[#This Row],[Coupon frequency]]="Annual",1,Table1[[#This Row],[Coupon frequency]]="Every 4 months",3,Table1[[#This Row],[Coupon frequency]]="Monthly",12)} -> 1 | U29: =Table1[[#This Row],[Term to Maturity (Years)]]*Table1[[#This Row],[Coupon Frequency2]] -> 15 | V29: =Table1[[#This Row],[Face value]]*Table1[[#This Row],[Current coupon %]] -> 73.5 | W29: =RATE(Table1[[#This Row],[Total No. of Coupons]],Table1[[#This Row],[Coupon Amount]],-Table1[[#This Row],[Ask Price]],Table1[[#This Row],[Face value]]) -> 0.057222515 | X29: =Table1[[#This Row],[IRR]]*Table1[[#This Row],[Coupon Frequency2]] -> 0.057222515 | Y29: {=_xlfn.IFS(Table1[[#This Row],[Yield (Annualised)]]<0.05,1,Table1[[#This Row],[Yield (Annualised)]]<0.1,2,Table1[[#This Row],[Yield (Annualised)]]<0.15,3,Table1[[#This Row],[Yield (Annualised)]]<0.2,4,Table1[[#This Row],[Yield (Annualised)]]<0.25,5,Table1[[#This Row],[Yield (Annualised)]]<0.3,6,Table1[[#This Row],[Yield (Annualised)]]<0.35,7,Table1[[#This Row],[Yield (Annualised)]]<0.4,8,Table1[[#This Row],[Yield (Annualised)]]<0.45,9,Table1[[#This Row],[Yield (Annualised)]]<0.5,10,Table1[[#This Row],[Yield (Annualised)]]<0.55,11,Table1[[#This Row],[Yield (Annualised)]]<0.6,12,Table1[[#This Row],[Yield (Annualised)]]<0.65,13,Table1[[#This Row],[Yield (Annualised)]]<0.7,14,Table1[[#This Row],[Yield (Annualised)]]>0.7,15)} -> 2 | Z29: =DURATION(Table1[[#This Row],[Issue date]],Table1[[#This Row],[Maturity date]],Table1[[#This Row],[Current coupon %]],Table1[[#This Row],[Yield (Annualised)]],Table1[[#This Row],[Coupon Frequency2]]) -> 9.973846 | AA29: =Table1[[#This Row],[Macaulay Duration in Years]]/(1+Table1[[#This Row],[IRR]]) -> 9.4340083 | AB29: =VLOOKUP(Table1[[#This Row],[Yield Cluster]],'Cluster Details'!$B$3:$C$16,2,0) -> 0.078548802 | AC29: =PRICE(Table1[[#This Row],[Issue date]],Table1[[#This Row],[Maturity date]],Table1[[#This Row],[Current coupon %]],Table1[[#This Row],[Average Cluster Yield]],100,Table1[[#This Row],[Coupon Frequency2]])*Table1[[#This Row],[Face value]]/100 -> 956.39931 | AD29: =IF(Table1[[#This Row],[Ask Price]]>Table1[[#This Row],[Calculated Bond Price]],"Rich","Cheap") -> Rich | AE29: =PRICE(Table1[[#This Row],[Issue date]],Table1[[#This Row],[Maturity date]],Table1[[#This Row],[Current coupon %]],Table1[[#This Row],[Yield (Annualised)]]+$AF$2,100,Table1[[#This Row],[Coupon Frequency2]])*Table1[[#This Row],[Face value]]/100 -> 1058.1915 | AF29: =PRICE(Table1[[#This Row],[Issue date]],Table1[[#This Row],[Maturity date]],Table1[[#This Row],[Current coupon %]],Table1[[#This Row],[Yield (Annualised)]]-$AF$2,100,Table1[[#This Row],[Coupon Frequency2]])*Table1[[#This Row],[Face value]]/100 -> 1277.945 | AG29: =(Table1[[#This Row],[P (+ shock)]]+Table1[[#This Row],[P (-shock)]]-2*Table1[[#This Row],[Ask Price]])/(2*Table1[[#This Row],[Ask Price]]*($AF$2^2)) -> 60.880394 | AH29: 14.756278 | AI29: =(L29*F29)/H29 -> 0.063307494 | AK29: =RATE(Table1[[#This Row],[Total No. of Coupons]],Table1[[#This Row],[Coupon Amount]],-Table1[[#This Row],[Ask Price]],Table1[[#This Row],[Face value]]) -> 0.057222515 | AL29: =Table1[[#This Row],[IRR]]*Table1[[#This Row],[Coupon Frequency2]] -> 0.057222515 | AM29: =-AA29*H29 -> -10952.884 | AN29: None | AO29: India | AP29: =_xlfn.SWITCH(PROPER(TRIM(M29)), "Annual",1, "Semi-Annual",2, "Quarterly",4, "Monthly",12, "") -> 1
A30: MFLV27 | B30: Muthoot Finance Limited 7.5% 03-NOV-2027 | C30: Corporate | D30: 44868 | E30: 46694 | F30: 1000 | G30: INR | H30: 1075 | I30: INR | J30: 107.5 | K30: 294 | L30: 0.075 | M30: Annual | N30: 777 | O30: 6.9767442 | P30: BB+ | R30: BSE | S30: =ROUND(YEARFRAC(D30,E30),0) -> 5 | T30: {=_xlfn.IFS(Table1[[#This Row],[Coupon frequency]]="Semi-annual",2,Table1[[#This Row],[Coupon frequency]]="Quarterly",4,Table1[[#This Row],[Coupon frequency]]="Annual",1,Table1[[#This Row],[Coupon frequency]]="Every 4 months",3,Table1[[#This Row],[Coupon frequency]]="Monthly",12)} -> 1 | U30: =Table1[[#This Row],[Term to Maturity (Years)]]*Table1[[#This Row],[Coupon Frequency2]] -> 5 | V30: =Table1[[#This Row],[Face value]]*Table1[[#This Row],[Current coupon %]] -> 75 | W30: =RATE(Table1[[#This Row],[Total No. of Coupons]],Table1[[#This Row],[Coupon Amount]],-Table1[[#This Row],[Ask Price]],Table1[[#This Row],[Face value]]) -> 0.057324658 | X30: =Table1[[#This Row],[IRR]]*Table1[[#This Row],[Coupon Frequency2]] -> 0.057324658 | Y30: {=_xlfn.IFS(Table1[[#This Row],[Yield (Annualised)]]<0.05,1,Table1[[#This Row],[Yield (Annualised)]]<0.1,2,Table1[[#This Row],[Yield (Annualised)]]<0.15,3,Table1[[#This Row],[Yield (Annualised)]]<0.2,4,Table1[[#This Row],[Yield (Annualised)]]<0.25,5,Table1[[#This Row],[Yield (Annualised)]]<0.3,6,Table1[[#This Row],[Yield (Annualised)]]<0.35,7,Table1[[#This Row],[Yield (Annualised)]]<0.4,8,Table1[[#This Row],[Yield (Annualised)]]<0.45,9,Table1[[#This Row],[Yield (Annualised)]]<0.5,10,Table1[[#This Row],[Yield (Annualised)]]<0.55,11,Table1[[#This Row],[Yield (Annualised)]]<0.6,12,Table1[[#This Row],[Yield (Annualised)]]<0.65,13,Table1[[#This Row],[Yield (Annualised)]]<0.7,14,Table1[[#This Row],[Yield (Annualised)]]>0.7,15)} -> 2 | Z30: =DURATION(Table1[[#This Row],[Issue date]],Table1[[#This Row],[Maturity date]],Table1[[#This Row],[Current coupon %]],Table1[[#This Row],[Yield (Annualised)]],Table1[[#This Row],[Coupon Frequency2]]) -> 4.3749667 | AA30: =Table1[[#This Row],[Macaulay Duration in Years]]/(1+Table1[[#This Row],[IRR]]) -> 4.1377705 | AB30: =VLOOKUP(Table1[[#This Row],[Yield Cluster]],'Cluster Details'!$B$3:$C$16,2,0) -> 0.078548802 | AC30: =PRICE(Table1[[#This Row],[Issue date]],Table1[[#This Row],[Maturity date]],Table1[[#This Row],[Current coupon %]],Table1[[#This Row],[Average Cluster Yield]],100,Table1[[#This Row],[Coupon Frequency2]])*Table1[[#This Row],[Face value]]/100 -> 985.7763 | AD30: =IF(Table1[[#This Row],[Ask Price]]>Table1[[#This Row],[Calculated Bond Price]],"Rich","Cheap") -> Rich | AE30: =PRICE(Table1[[#This Row],[Issue date]],Table1[[#This Row],[Maturity date]],Table1[[#This Row],[Current coupon %]],Table1[[#This Row],[Yield (Annualised)]]+$AF$2,100,Table1[[#This Row],[Coupon Frequency2]])*Table1[[#This Row],[Face value]]/100 -> 1031.6971 | AF30: =PRICE(Table1[[#This Row],[Issue date]],Table1[[#This Row],[Maturity date]],Table1[[#This Row],[Current coupon %]],Table1[[#This Row],[Yield (Annualised)]]-$AF$2,100,Table1[[#This Row],[Coupon Frequency2]])*Table1[[#This Row],[Face value]]/100 -> 1120.7111 | AG30: =(Table1[[#This Row],[P (+ shock)]]+Table1[[#This Row],[P (-shock)]]-2*Table1[[#This Row],[Ask Price]])/(2*Table1[[#This Row],[Ask Price]]*($AF$2^2)) -> 11.20102 | AH30: 11.200611 | AI30: =(L30*F30)/H30 -> 0.069767442 | AK30: =RATE(Table1[[#This Row],[Total No. of Coupons]],Table1[[#This Row],[Coupon Amount]],-Table1[[#This Row],[Ask Price]],Table1[[#This Row],[Face value]]) -> 0.057324658 | AL30: =Table1[[#This Row],[IRR]]*Table1[[#This Row],[Coupon Frequency2]] -> 0.057324658 | AM30: =-AA30*H30 -> -4448.1032 | AN30: None | AO30: India | AP30: =_xlfn.SWITCH(PROPER(TRIM(M30)), "Annual",1, "Semi-Annual",2, "Quarterly",4, "Monthly",12, "") -> 1
A31: 753NABRD28 | B31: National Bank for Agriculture & Rural Development 7.53% 24-MAR-2028 | C31: Corporate | D31: 45670 | E31: 46836 | F31: 100000 | G31: INR | H31: 104713 | I31: INR | J31: 104.713 | K31: 1500 | L31: 0.0753 | M31: Annual | N31: 919 | O31: 7.1910842 | R31: BSE | S31: =ROUND(YEARFRAC(D31,E31),0) -> 3 | T31: {=_xlfn.IFS(Table1[[#This Row],[Coupon frequency]]="Semi-annual",2,Table1[[#This Row],[Coupon frequency]]="Quarterly",4,Table1[[#This Row],[Coupon frequency]]="Annual",1,Table1[[#This Row],[Coupon frequency]]="Every 4 months",3,Table1[[#This Row],[Coupon frequency]]="Monthly",12)} -> 1 | U31: =Table1[[#This Row],[Term to Maturity (Years)]]*Table1[[#This Row],[Coupon Frequency2]] -> 3 | V31: =Table1[[#This Row],[Face value]]*Table1[[#This Row],[Current coupon %]] -> 7530 | W31: =RATE(Table1[[#This Row],[Total No. of Coupons]],Table1[[#This Row],[Coupon Amount]],-Table1[[#This Row],[Ask Price]],Table1[[#This Row],[Face value]]) -> 0.057741821 | X31: =Table1[[#This Row],[IRR]]*Table1[[#This Row],[Coupon Frequency2]] -> 0.057741821 | Y31: {=_xlfn.IFS(Table1[[#This Row],[Yield (Annualised)]]<0.05,1,Table1[[#This Row],[Yield (Annualised)]]<0.1,2,Table1[[#This Row],[Yield (Annualised)]]<0.15,3,Table1[[#This Row],[Yield (Annualised)]]<0.2,4,Table1[[#This Row],[Yield (Annualised)]]<0.25,5,Table1[[#This Row],[Yield (Annualised)]]<0.3,6,Table1[[#This Row],[Yield (Annualised)]]<0.35,7,Table1[[#This Row],[Yield (Annualised)]]<0.4,8,Table1[[#This Row],[Yield (Annualised)]]<0.45,9,Table1[[#This Row],[Yield (Annualised)]]<0.5,10,Table1[[#This Row],[Yield (Annualised)]]<0.55,11,Table1[[#This Row],[Yield (Annualised)]]<0.6,12,Table1[[#This Row],[Yield (Annualised)]]<0.65,13,Table1[[#This Row],[Yield (Annualised)]]<0.7,14,Table1[[#This Row],[Yield (Annualised)]]>0.7,15)} -> 2 | Z31: =DURATION(Table1[[#This Row],[Issue date]],Table1[[#This Row],[Maturity date]],Table1[[#This Row],[Current coupon %]],Table1[[#This Row],[Yield (Annualised)]],Table1[[#This Row],[Coupon Frequency2]]) -> 2.8091517 | AA31: =Table1[[#This Row],[Macaulay Duration in Years]]/(1+Table1[[#This Row],[IRR]]) -> 2.6558009 | AB31: =VLOOKUP(Table1[[#This Row],[Yield Cluster]],'Cluster Details'!$B$3:$C$16,2,0) -> 0.078548802 | AC31: =PRICE(Table1[[#This Row],[Issue date]],Table1[[#This Row],[Maturity date]],Table1[[#This Row],[Current coupon %]],Table1[[#This Row],[Average Cluster Yield]],100,Table1[[#This Row],[Coupon Frequency2]])*Table1[[#This Row],[Face value]]/100 -> 99066.342 | AD31: =IF(Table1[[#This Row],[Ask Price]]>Table1[[#This Row],[Calculated Bond Price]],"Rich","Cheap") -> Rich | AE31: =PRICE(Table1[[#This Row],[Issue date]],Table1[[#This Row],[Maturity date]],Table1[[#This Row],[Current coupon %]],Table1[[#This Row],[Yield (Annualised)]]+$AF$2,100,Table1[[#This Row],[Coupon Frequency2]])*Table1[[#This Row],[Face value]]/100 -> 102070.11 | AF31: =PRICE(Table1[[#This Row],[Issue date]],Table1[[#This Row],[Maturity date]],Table1[[#This Row],[Current coupon %]],Table1[[#This Row],[Yield (Annualised)]]-$AF$2,100,Table1[[#This Row],[Coupon Frequency2]])*Table1[[#This Row],[Face value]]/100 -> 107968.21 | AG31: =(Table1[[#This Row],[P (+ shock)]]+Table1[[#This Row],[P (-shock)]]-2*Table1[[#This Row],[Ask Price]])/(2*Table1[[#This Row],[Ask Price]]*($AF$2^2)) -> 29.238059 | AH31: 15.474703 | AI31: =(L31*F31)/H31 -> 0.071910842 | AK31: =RATE(Table1[[#This Row],[Total No. of Coupons]],Table1[[#This Row],[Coupon Amount]],-Table1[[#This Row],[Ask Price]],Table1[[#This Row],[Face value]]) -> 0.057741821 | AL31: =Table1[[#This Row],[IRR]]*Table1[[#This Row],[Coupon Frequency2]] -> 0.057741821 | AM31: =-AA31*H31 -> -278096.88 | AN31: None | AO31: India | AP31: =_xlfn.SWITCH(PROPER(TRIM(M31)), "Annual",1, "Semi-Annual",2, "Quarterly",4, "Monthly",12, "") -> 1
A32: 9MFL25 | B32: Muthoot Fincorp Ltd. 9.0% 01-NOV-2025 | C32: Corporate | D32: 45231 | E32: 45962 | F32: 1000 | G32: INR | H32: 1059.1 | I32: INR | J32: 105.91 | K32: 50 | L32: 0.09 | M32: Annual | N32: 45 | O32: 8.4977811 | R32: BSE | S32: =ROUND(YEARFRAC(D32,E32),0) -> 2 | T32: {=_xlfn.IFS(Table1[[#This Row],[Coupon frequency]]="Semi-annual",2,Table1[[#This Row],[Coupon frequency]]="Quarterly",4,Table1[[#This Row],[Coupon frequency]]="Annual",1,Table1[[#This Row],[Coupon frequency]]="Every 4 months",3,Table1[[#This Row],[Coupon frequency]]="Monthly",12)} -> 1 | U32: =Table1[[#This Row],[Term to Maturity (Years)]]*Table1[[#This Row],[Coupon Frequency2]] -> 2 | V32: =Table1[[#This Row],[Face value]]*Table1[[#This Row],[Current coupon %]] -> 90 | W32: =RATE(Table1[[#This Row],[Total No. of Coupons]],Table1[[#This Row],[Coupon Amount]],-Table1[[#This Row],[Ask Price]],Table1[[#This Row],[Face value]]) -> 0.057861262 | X32: =Table1[[#This Row],[IRR]]*Table1[[#This Row],[Coupon Frequency2]] -> 0.057861262 | Y32: {=_xlfn.IFS(Table1[[#This Row],[Yield (Annualised)]]<0.05,1,Table1[[#This Row],[Yield (Annualised)]]<0.1,2,Table1[[#This Row],[Yield (Annualised)]]<0.15,3,Table1[[#This Row],[Yield (Annualised)]]<0.2,4,Table1[[#This Row],[Yield (Annualised)]]<0.25,5,Table1[[#This Row],[Yield (Annualised)]]<0.3,6,Table1[[#This Row],[Yield (Annualised)]]<0.35,7,Table1[[#This Row],[Yield (Annualised)]]<0.4,8,Table1[[#This Row],[Yield (Annualised)]]<0.45,9,Table1[[#This Row],[Yield (Annualised)]]<0.5,10,Table1[[#This Row],[Yield (Annualised)]]<0.55,11,Table1[[#This Row],[Yield (Annualised)]]<0.6,12,Table1[[#This Row],[Yield (Annualised)]]<0.65,13,Table1[[#This Row],[Yield (Annualised)]]<0.7,14,Table1[[#This Row],[Yield (Annualised)]]>0.7,15)} -> 2 | Z32: =DURATION(Table1[[#This Row],[Issue date]],Table1[[#This Row],[Maturity date]],Table1[[#This Row],[Current coupon %]],Table1[[#This Row],[Yield (Annualised)]],Table1[[#This Row],[Coupon Frequency2]]) -> 1.9196702 | AA32: =Table1[[#This Row],[Macaulay Duration in Years]]/(1+Table1[[#This Row],[IRR]]) -> 1.814671 | AB32: =VLOOKUP(Table1[[#This Row],[Yield Cluster]],'Cluster Details'!$B$3:$C$16,2,0) -> 0.078548802 | AC32: =PRICE(Table1[[#This Row],[Issue date]],Table1[[#This Row],[Maturity date]],Table1[[#This Row],[Current coupon %]],Table1[[#This Row],[Average Cluster Yield]],100,Table1[[#This Row],[Coupon Frequency2]])*Table1[[#This Row],[Face value]]/100 -> 1020.4612 | AD32: =IF(Table1[[#This Row],[Ask Price]]>Table1[[#This Row],[Calculated Bond Price]],"Rich","Cheap") -> Rich | AE32: =PRICE(Table1[[#This Row],[Issue date]],Table1[[#This Row],[Maturity date]],Table1[[#This Row],[Current coupon %]],Table1[[#This Row],[Yield (Annualised)]]+$AF$2,100,Table1[[#This Row],[Coupon Frequency2]])*Table1[[#This Row],[Face value]]/100 -> 1040.1462 | AF32: =PRICE(Table1[[#This Row],[Issue date]],Table1[[#This Row],[Maturity date]],Table1[[#This Row],[Current coupon %]],Table1[[#This Row],[Yield (Annualised)]]-$AF$2,100,Table1[[#This Row],[Coupon Frequency2]])*Table1[[#This Row],[Face value]]/100 -> 1078.5913 | AG32: =(Table1[[#This Row],[P (+ shock)]]+Table1[[#This Row],[P (-shock)]]-2*Table1[[#This Row],[Ask Price]])/(2*Table1[[#This Row],[Ask Price]]*($AF$2^2)) -> 2.5376047 | AH32: -25.854442 | AI32: =(L32*F32)/H32 -> 0.084977811 | AK32: =RATE(Table1[[#This Row],[Total No. of Coupons]],Table1[[#This Row],[Coupon Amount]],-Table1[[#This Row],[Ask Price]],Table1[[#This Row],[Face value]]) -> 0.057861262 | AL32: =Table1[[#This Row],[IRR]]*Table1[[#This Row],[Coupon Frequency2]] -> 0.057861262 | AM32: =-AA32*H32 -> -1921.9181 | AN32: None | AO32: India | AP32: =_xlfn.SWITCH(PROPER(TRIM(M32)), "Annual",1, "Semi-Annual",2, "Quarterly",4, "Monthly",12, "") -> 1
A33: 728NTPC30B | B33: NTPC Limited 7.28% 05-OCT-2030 | C33: Corporate | D33: 42282 | E33: 47761 | F33: 1000 | G33: INR | H33: 1140 | I33: INR | J33: 114 | K33: 40 | L33: 0.0728 | M33: Annual | N33: 1844 | O33: 6.3859649 | P33: BBB | R33: BSE | S33: =ROUND(YEARFRAC(D33,E33),0) -> 15 | T33: {=_xlfn.IFS(Table1[[#This Row],[Coupon frequency]]="Semi-annual",2,Table1[[#This Row],[Coupon frequency]]="Quarterly",4,Table1[[#This Row],[Coupon frequency]]="Annual",1,Table1[[#This Row],[Coupon frequency]]="Every 4 months",3,Table1[[#This Row],[Coupon frequency]]="Monthly",12)} -> 1 | U33: =Table1[[#This Row],[Term to Maturity (Years)]]*Table1[[#This Row],[Coupon Frequency2]] -> 15 | V33: =Table1[[#This Row],[Face value]]*Table1[[#This Row],[Current coupon %]] -> 72.8 | W33: =RATE(Table1[[#This Row],[Total No. of Coupons]],Table1[[#This Row],[Coupon Amount]],-Table1[[#This Row],[Ask Price]],Table1[[#This Row],[Face value]]) -> 0.058523916 | X33: =Table1[[#This Row],[IRR]]*Table1[[#This Row],[Coupon Frequency2]] -> 0.058523916 | Y33: {=_xlfn.IFS(Table1[[#This Row],[Yield (Annualised)]]<0.05,1,Table1[[#This Row],[Yield (Annualised)]]<0.1,2,Table1[[#This Row],[Yield (Annualised)]]<0.15,3,Table1[[#This Row],[Yield (Annualised)]]<0.2,4,Table1[[#This Row],[Yield (Annualised)]]<0.25,5,Table1[[#This Row],[Yield (Annualised)]]<0.3,6,Table1[[#This Row],[Yield (Annualised)]]<0.35,7,Table1[[#This Row],[Yield (Annualised)]]<0.4,8,Table1[[#This Row],[Yield (Annualised)]]<0.45,9,Table1[[#This Row],[Yield (Annualised)]]<0.5,10,Table1[[#This Row],[Yield (Annualised)]]<0.55,11,Table1[[#This Row],[Yield (Annualised)]]<0.6,12,Table1[[#This Row],[Yield (Annualised)]]<0.65,13,Table1[[#This Row],[Yield (Annualised)]]<0.7,14,Table1[[#This Row],[Yield (Annualised)]]>0.7,15)} -> 2 | Z33: =DURATION(Table1[[#This Row],[Issue date]],Table1[[#This Row],[Maturity date]],Table1[[#This Row],[Current coupon %]],Table1[[#This Row],[Yield (Annualised)]],Table1[[#This Row],[Coupon Frequency2]]) -> 9.9593663 | AA33: =Table1[[#This Row],[Macaulay Duration in Years]]/(1+Table1[[#This Row],[IRR]]) -> 9.4087305 | AB33: =VLOOKUP(Table1[[#This Row],[Yield Cluster]],'Cluster Details'!$B$3:$C$16,2,0) -> 0.078548802 | AC33: =PRICE(Table1[[#This Row],[Issue date]],Table1[[#This Row],[Maturity date]],Table1[[#This Row],[Current coupon %]],Table1[[#This Row],[Average Cluster Yield]],100,Table1[[#This Row],[Coupon Frequency2]])*Table1[[#This Row],[Face value]]/100 -> 950.35422 | AD33: =IF(Table1[[#This Row],[Ask Price]]>Table1[[#This Row],[Calculated Bond Price]],"Rich","Cheap") -> Rich | AE33: =PRICE(Table1[[#This Row],[Issue date]],Table1[[#This Row],[Maturity date]],Table1[[#This Row],[Current coupon %]],Table1[[#This Row],[Yield (Annualised)]]+$AF$2,100,Table1[[#This Row],[Coupon Frequency2]])*Table1[[#This Row],[Face value]]/100 -> 1039.3119 | AF33: =PRICE(Table1[[#This Row],[Issue date]],Table1[[#This Row],[Maturity date]],Table1[[#This Row],[Current coupon %]],Table1[[#This Row],[Yield (Annualised)]]-$AF$2,100,Table1[[#This Row],[Coupon Frequency2]])*Table1[[#This Row],[Face value]]/100 -> 1254.5105 | AG33: =(Table1[[#This Row],[P (+ shock)]]+Table1[[#This Row],[P (-shock)]]-2*Table1[[#This Row],[Ask Price]])/(2*Table1[[#This Row],[Ask Price]]*($AF$2^2)) -> 60.624585 | AH33: 13.269205 | AI33: =(L33*F33)/H33 -> 0.063859649 | AK33: =RATE(Table1[[#This Row],[Total No. of Coupons]],Table1[[#This Row],[Coupon Amount]],-Table1[[#This Row],[Ask Price]],Table1[[#This Row],[Face value]]) -> 0.058523916 | AL33: =Table1[[#This Row],[IRR]]*Table1[[#This Row],[Coupon Frequency2]] -> 0.058523916 | AM33: =-AA33*H33 -> -10725.953 | AN33: None | AO33: India | AP33: =_xlfn.SWITCH(PROPER(TRIM(M33)), "Annual",1, "Semi-Annual",2, "Quarterly",4, "Monthly",12, "") -> 1
